Workbook

Sheet 使い方
B1: 使い方とルール
B3: ■ シートの役割
B4: 案件管理 | C4: 案件を1件1行で登録します。青文字＋うすい黄色の列だけ入力してください。
C5: グレー背景の列は自動計算です。緑文字は他のシートから集計した値です。
B6: 工数明細 | C6: 日々の工数を1行ずつ入れます。案件管理の「実績工数」と月次工数計画の「実績」に反映されます。
B7: 月次工数計画 | C7: どの案件に何月何人日を投入するかを入力します。下半分に工数明細からの実績が並びます。
B8: 発注・納品 | C8: 機器の発注を1明細1行で。発注日→希望納期→回答納期→入荷日→受入日 を追いかけます。
B9: 現地作業 | C9: 現地に行く日の予定と実施記録。作業日・時間・場所・作業者・状態を入れます。
B10: ダッシュボード | C10: C3に年度を入れると、クォーター別・ステータス別・担当者別・作業ステップ別、
C11: および機器の納品状況・現地作業の件数を自動集計します。
B12: マスタ | C12: 年度開始月（初期値4月）、1人日あたりの時間（初期値8h）、月次計画の開始年月、
C13: 各プルダウンの選択肢を変えられます。
B15: ■ 色のルール
B16: 青文字 | C16: 自分で入力するセル
B17: 黒文字＋グレー背景 | C17: そのシート内の数式による自動計算。編集しないでください。
B18: 緑文字＋グレー背景 | C18: 他のシートから集計している自動計算。編集しないでください。
B19: 黄色の塗り | C19: 設定値。会社のルールに合わせて変更してください（マスタシート）。
B20: うすい緑の行 | C20: サンプル行です。書き換えるか、行ごと削除してからお使いください。
B22: ■ 入力の順番（おすすめ）
B23: 1 | C23: マスタで年度開始月・1人日あたりの時間・月次計画の開始年月を決める
B24: 2 | C24: 案件管理に案件を登録する（案件IDは重複しない値にしてください）
B25: 3 | C25: 月次工数計画で、その案件に何月何人日を投入するか配分する
B26: 4 | C26: 機器があれば発注・納品に明細を登録する（金額は案件管理の機器原価に自動反映）
B27: 5 | C27: 現地作業に行く日を予定として登録しておく
B28: 6 | C28: 作業したら工数明細に工数を、現地作業の状態を「完了」に更新する
B30: ■ 自動でやってくれること
B31: クォーター判定 | C31: 「受注(予定)日」から年度とQ1〜Q4を自動判定します（年度開始月はマスタで変更可）。
B32: 金額まわり | C32: 機器原価＝発注・納品の金額合計、原価計＝原価(機器以外)＋機器原価、
C33: 粗利＝受注金額−原価計、加重金額＝受注金額×受注確度。
B34: 機器の納品状況 | C34: 発注件数・未入荷件数・最終入荷日・納品状況（機器なし/入荷待ち/受入待ち/受入完了）。
C35: 回答納期を過ぎても入荷していない明細は、納期差異が赤く表示されます。
B36: 現地作業 | C36: 予定件数・完了件数と、今日以降でいちばん近い「次回現地作業日」を表示します。
B37: 工数まわり | C37: 実績工数は工数明細から自動集計。残工数・消化率・予実判定（適正/注意/超過）も自動です。
C38: 月次工数計画では、予定工数に対して月配分が足りているか「差異」で確認できます。
B39: 進行状況 | C39: ステータスは色分け、進捗率はデータバー、失注行は打ち消し線になります。
B40: 遅延の検知 | C40: 完了予定日を過ぎて未完了の案件は「遅延日数」が赤く表示されます。
B42: ■ 行が足りなくなったら
B43: オートフィル | C43: 案件管理・発注・納品・現地作業は202行目、工数明細は302行目まで数式が入っています。
C44: 最終行を選択して右下を下へドラッグすると、数式・書式・プルダウンごと増やせます。
B45: 注意 | C45: 案件管理の行を増やしたら、月次工数計画の計画ブロック・実績ブロックの行も
C46: 同じだけ増やしてください（行の位置が対応しています）。
B48: ■ 前提としている値
B49: 年度開始月 | C49: 4月（日本の一般的な年度）。マスタ!B4 で変更できます。
B50: 1人日 | C50: 8時間。マスタ!B5 で変更できます。
B51: 月次計画の開始年月 | C51: 2026年4月から24ヶ月ぶん。マスタ!B7 で変更できます。
B52: 金額 | C52: すべて税抜・円で入力する前提です。
B53: 工数の入り口 | C53: 工数は工数明細だけに入れてください。現地作業シートの実働時間は参考値で、
C54: 実績工数には加算されません（二重計上を避けるためです）。
B55: サンプルの数値 | C55: 各シートのサンプル行の数値はすべて説明用の架空データです。
B57: 入力するセルの見た目
B58: 自動計算セルの見た目
B59: 他シート集計セルの見た目
B60: 設定値セルの見た目
B61: サンプル行の見た目

Sheet 案件管理
A1: 案件管理表 │ 金額・クォーター・機器納品・現地作業・工数・進行状況をまとめて管理
A2: 案件ID | B2: 案件名 | C2: 顧客名 | D2: 担当者 | E2: 案件区分 | F2: 受注確度 | G2: ステータス | H2: 現在の作業ステップ | I2: 進捗率 | J2: 受注(予定)日 | K2: 着手日 | L2: 完了予定日 | M2: 完了日 | N2: 年度 | O2: クォーター | P2: 遅延日数 | Q2: 受注金額 | R2: 加重金額 | S2: 原価(機器以外) | T2: 機器原価 | U2: 原価計 | V2: 粗利 | W2: 粗利率 | X2: 発注件数 | Y2: 未入荷件数 | Z2: 最終入荷日 | AA2: 納品状況 | AB2: 現地作業(予定) | AC2: 現地作業(完了) | AD2: 次回現地作業日 | AE2: 予定工数 | AF2: 月次計画計 | AG2: 実績工数 | AH2: 残工数 | AI2: 工数消化率 | AJ2: 予実判定 | AK2: 備考
A3: P-001 | B3: 本社ネットワーク更改 | C3: 株式会社アルファ商事 | D3: 山田 太郎 | E3: 新規 | F3: 1 | G3: 進行中 | H3: 現地作業 | I3: 0.45 | J3: 46162 | K3: 46174 | L3: 46265 | N3: =IF($J3="","",YEAR($J3)-IF(MONTH($J3)<マスタ!$B$4,1,0)) -> 2026 | O3: =IF($J3="","","Q"&(INT(MOD(MONTH($J3)-マスタ!$B$4+12,12)/3)+1)) -> Q1 | P3: =IF($L3="","",IF($M3<>"",$M3-$L3,IF(TODAY()>$L3,TODAY()-$L3,0))) -> 15 | Q3: 4800000 | R3: =IF($Q3="","",$Q3*N($F3)) -> 4800000 | S3: 600000 | T3: =IF($A3="","",SUMIFS(発注・納品!$H$3:$H$202,発注・納品!$B$3:$B$202,$A3)) -> 1820000 | U3: =IF($Q3="","",N($S3)+N($T3)) -> 2420000 | V3: =IF($Q3="","",$Q3-N($U3)) -> 2380000 | W3: =IF(N($Q3)=0,"",$V3/$Q3) -> 0.49583333 | X3: =IF($A3="","",COUNTIFS(発注・納品!$B$3:$B$202,$A3)) -> 3 | Y3: =IF($A3="","",COUNTIFS(発注・納品!$B$3:$B$202,$A3,発注・納品!$M$3:$M$202,"")) -> 1 | Z3: =IF(N($X3)=0,"",IF(_xlfn.MAXIFS(発注・納品!$M$3:$M$202,発注・納品!$B$3:$B$202,$A3)=0,"",_xlfn.MAXIFS(発注・納品!$M$3:$M$202,発注・納品!$B$3:$B$202,$A3))) -> 46192 | AA3: =IF($A3="","",IF(N($X3)=0,"機器なし",IF(N($Y3)>0,"入荷待ち",IF(COUNTIFS(発注・納品!$B$3:$B$202,$A3,発注・納品!$N$3:$N$202,"")>0,"受入待ち","受入完了")))) -> 入荷待ち | AB3: =IF($A3="","",COUNTIFS(現地作業!$A$3:$A$202,$A3,現地作業!$L$3:$L$202,"予定")) -> 1 | AC3: =IF($A3="","",COUNTIFS(現地作業!$A$3:$A$202,$A3,現地作業!$L$3:$L$202,"完了")) -> 2 | AD3: =IF(N($AB3)=0,"",IF(_xlfn.MINIFS(現地作業!$C$3:$C$202,現地作業!$A$3:$A$202,$A3,現地作業!$L$3:$L$202,"予定",現地作業!$C$3:$C$202,">="&TODAY())=0,"",_xlfn.MINIFS(現地作業!$C$3:$C$202,現地作業!$A$3:$A$202,$A3,現地作業!$L$3:$L$202,"予定",現地作業!$C$3:$C$202,">="&TODAY()))) -> 46309 | AE3: 45 | AF3: =IF($A3="","",SUM(月次工数計画!$G$8:$AD$8)) -> 45 | AG3: =IF($A3="","",SUMIFS(工数明細!$G$3:$G$302,工数明細!$B$3:$B$302,$A3)) -> 2.25 | AH3: =IF($AE3="","",$AE3-N($AG3)) -> 42.75 | AI3: =IF(N($AE3)=0,"",$AG3/$AE3) -> 0.05 | AJ3: =IF(N($AE3)=0,"",IF($AG3>$AE3,"超過",IF($AG3>=$AE3*0.9,"注意","適正"))) -> 適正 | AK3: ※サンプル行です。書き換えるか、行ごと削除してお使いください。
A4: P-002 | B4: 基幹システム保守（年間） | C4: ベータ工業株式会社 | D4: 佐藤 花子 | E4: 保守・運用 | F4: 1 | G4: 完了 | H4: 完了 | I4: 1 | J4: 46122 | K4: 46127 | L4: 46203 | M4: 46201 | N4: =IF($J4="","",YEAR($J4)-IF(MONTH($J4)<マスタ!$B$4,1,0)) -> 2026 | O4: =IF($J4="","","Q"&(INT(MOD(MONTH($J4)-マスタ!$B$4+12,12)/3)+1)) -> Q1 | P4: =IF($L4="","",IF($M4<>"",$M4-$L4,IF(TODAY()>$L4,TODAY()-$L4,0))) -> -2 | Q4: 1200000 | R4: =IF($Q4="","",$Q4*N($F4)) -> 1200000 | S4: 480000 | T4: =IF($A4="","",SUMIFS(発注・納品!$H$3:$H$202,発注・納品!$B$3:$B$202,$A4)) -> 0 | U4: =IF($Q4="","",N($S4)+N($T4)) -> 480000 | V4: =IF($Q4="","",$Q4-N($U4)) -> 720000 | W4: =IF(N($Q4)=0,"",$V4/$Q4) -> 0.6 | X4: =IF($A4="","",COUNTIFS(発注・納品!$B$3:$B$202,$A4)) -> 0 | Y4: =IF($A4="","",COUNTIFS(発注・納品!$B$3:$B$202,$A4,発注・納品!$M$3:$M$202,"")) -> 0 | Z4: =IF(N($X4)=0,"",IF(_xlfn.MAXIFS(発注・納品!$M$3:$M$202,発注・納品!$B$3:$B$202,$A4)=0,"",_xlfn.MAXIFS(発注・納品!$M$3:$M$202,発注・納品!$B$3:$B$202,$A4))) | AA4: =IF($A4="","",IF(N($X4)=0,"機器なし",IF(N($Y4)>0,"入荷待ち",IF(COUNTIFS(発注・納品!$B$3:$B$202,$A4,発注・納品!$N$3:$N$202,"")>0,"受入待ち","受入完了")))) -> 機器なし | AB4: =IF($A4="","",COUNTIFS(現地作業!$A$3:$A$202,$A4,現地作業!$L$3:$L$202,"予定")) -> 0 | AC4: =IF($A4="","",COUNTIFS(現地作業!$A$3:$A$202,$A4,現地作業!$L$3:$L$202,"完了")) -> 0 | AD4: =IF(N($AB4)=0,"",IF(_xlfn.MINIFS(現地作業!$C$3:$C$202,現地作業!$A$3:$A$202,$A4,現地作業!$L$3:$L$202,"予定",現地作業!$C$3:$C$202,">="&TODAY())=0,"",_xlfn.MINIFS(現地作業!$C$3:$C$202,現地作業!$A$3:$A$202,$A4,現地作業!$L$3:$L$202,"予定",現地作業!$C$3:$C$202,">="&TODAY()))) | AE4: 12 | AF4: =IF($A4="","",SUM(月次工数計画!$G$9:$AD$9)) -> 12 | AG4: =IF($A4="","",SUMIFS(工数明細!$G$3:$G$302,工数明細!$B$3:$B$302,$A4)) -> 0.5 | AH4: =IF($AE4="","",$AE4-N($AG4)) -> 11.5 | AI4: =IF(N($AE4)=0,"",$AG4/$AE4) -> 0.041666667 | AJ4: =IF(N($AE4)=0,"",IF($AG4>$AE4,"超過",IF($AG4>=$AE4*0.9,"注意","適正"))) -> 適正 | AK4: ※サンプル行です。
A5: P-003 | B5: Webサイトリニューアル | C5: ガンマデザイン合同会社 | D5: 鈴木 一郎 | E5: 新規 | F5: 0.5 | G5: 未着手 | H5: 要件定義 | I5: 0.1 | J5: 46331 | L5: 46446 | N5: =IF($J5="","",YEAR($J5)-IF(MONTH($J5)<マスタ!$B$4,1,0)) -> 2026 | O5: =IF($J5="","","Q"&(INT(MOD(MONTH($J5)-マスタ!$B$4+12,12)/3)+1)) -> Q3 | P5: =IF($L5="","",IF($M5<>"",$M5-$L5,IF(TODAY()>$L5,TODAY()-$L5,0))) -> 0 | Q5: 3000000 | R5: =IF($Q5="","",$Q5*N($F5)) -> 1500000 | S5: 1500000 | T5: =IF($A5="","",SUMIFS(発注・納品!$H$3:$H$202,発注・納品!$B$3:$B$202,$A5)) -> 0 | U5: =IF($Q5="","",N($S5)+N($T5)) -> 1500000 | V5: =IF($Q5="","",$Q5-N($U5)) -> 1500000 | W5: =IF(N($Q5)=0,"",$V5/$Q5) -> 0.5 | X5: =IF($A5="","",COUNTIFS(発注・納品!$B$3:$B$202,$A5)) -> 0 | Y5: =IF($A5="","",COUNTIFS(発注・納品!$B$3:$B$202,$A5,発注・納品!$M$3:$M$202,"")) -> 0 | Z5: =IF(N($X5)=0,"",IF(_xlfn.MAXIFS(発注・納品!$M$3:$M$202,発注・納品!$B$3:$B$202,$A5)=0,"",_xlfn.MAXIFS(発注・納品!$M$3:$M$202,発注・納品!$B$3:$B$202,$A5))) | AA5: =IF($A5="","",IF(N($X5)=0,"機器なし",IF(N($Y5)>0,"入荷待ち",IF(COUNTIFS(発注・納品!$B$3:$B$202,$A5,発注・納品!$N$3:$N$202,"")>0,"受入待ち","受入完了")))) -> 機器なし | AB5: =IF($A5="","",COUNTIFS(現地作業!$A$3:$A$202,$A5,現地作業!$L$3:$L$202,"予定")) -> 0 | AC5: =IF($A5="","",COUNTIFS(現地作業!$A$3:$A$202,$A5,現地作業!$L$3:$L$202,"完了")) -> 0 | AD5: =IF(N($AB5)=0,"",IF(_xlfn.MINIFS(現地作業!$C$3:$C$202,現地作業!$A$3:$A$202,$A5,現地作業!$L$3:$L$202,"予定",現地作業!$C$3:$C$202,">="&TODAY())=0,"",_xlfn.MINIFS(現地作業!$C$3:$C$202,現地作業!$A$3:$A$202,$A5,現地作業!$L$3:$L$202,"予定",現地作業!$C$3:$C$202,">="&TODAY()))) | AE5: 30 | AF5: =IF($A5="","",SUM(月次工数計画!$G$10:$AD$10)) -> 30 | AG5: =IF($A5="","",SUMIFS(工数明細!$G$3:$G$302,工数明細!$B$3:$B$302,$A5)) -> 0 | AH5: =IF($AE5="","",$AE5-N($AG5)) -> 30 | AI5: =IF(N($AE5)=0,"",$AG5/$AE5) -> 0 | AJ5: =IF(N($AE5)=0,"",IF($AG5>$AE5,"超過",IF($AG5>=$AE5*0.9,"注意","適正"))) -> 適正 | AK5: ※サンプル行です。提案中のため確度50%。
N6: =IF($J6="","",YEAR($J6)-IF(MONTH($J6)<マスタ!$B$4,1,0)) | O6: =IF($J6="","","Q"&(INT(MOD(MONTH($J6)-マスタ!$B$4+12,12)/3)+1)) | P6: =IF($L6="","",IF($M6<>"",$M6-$L6,IF(TODAY()>$L6,TODAY()-$L6,0))) | R6: =IF($Q6="","",$Q6*N($F6)) | T6: =IF($A6="","",SUMIFS(発注・納品!$H$3:$H$202,発注・納品!$B$3:$B$202,$A6)) | U6: =IF($Q6="","",N($S6)+N($T6)) | V6: =IF($Q6="","",$Q6-N($U6)) | W6: =IF(N($Q6)=0,"",$V6/$Q6) | X6: =IF($A6="","",COUNTIFS(発注・納品!$B$3:$B$202,$A6)) | Y6: =IF($A6="","",COUNTIFS(発注・納品!$B$3:$B$202,$A6,発注・納品!$M$3:$M$202,"")) | Z6: =IF(N($X6)=0,"",IF(_xlfn.MAXIFS(発注・納品!$M$3:$M$202,発注・納品!$B$3:$B$202,$A6)=0,"",_xlfn.MAXIFS(発注・納品!$M$3:$M$202,発注・納品!$B$3:$B$202,$A6))) | AA6: =IF($A6="","",IF(N($X6)=0,"機器なし",IF(N($Y6)>0,"入荷待ち",IF(COUNTIFS(発注・納品!$B$3:$B$202,$A6,発注・納品!$N$3:$N$202,"")>0,"受入待ち","受入完了")))) | AB6: =IF($A6="","",COUNTIFS(現地作業!$A$3:$A$202,$A6,現地作業!$L$3:$L$202,"予定")) | AC6: =IF($A6="","",COUNTIFS(現地作業!$A$3:$A$202,$A6,現地作業!$L$3:$L$202,"完了")) | AD6: =IF(N($AB6)=0,"",IF(_xlfn.MINIFS(現地作業!$C$3:$C$202,現地作業!$A$3:$A$202,$A6,現地作業!$L$3:$L$202,"予定",現地作業!$C$3:$C$202,">="&TODAY())=0,"",_xlfn.MINIFS(現地作業!$C$3:$C$202,現地作業!$A$3:$A$202,$A6,現地作業!$L$3:$L$202,"予定",現地作業!$C$3:$C$202,">="&TODAY()))) | AF6: =IF($A6="","",SUM(月次工数計画!$G$11:$AD$11)) | AG6: =IF($A6="","",SUMIFS(工数明細!$G$3:$G$302,工数明細!$B$3:$B$302,$A6)) | AH6: =IF($AE6="","",$AE6-N($AG6)) | AI6: =IF(N($AE6)=0,"",$AG6/$AE6) | AJ6: =IF(N($AE6)=0,"",IF($AG6>$AE6,"超過",IF($AG6>=$AE6*0.9,"注意","適正")))
N7: =IF($J7="","",YEAR($J7)-IF(MONTH($J7)<マスタ!$B$4,1,0)) | O7: =IF($J7="","","Q"&(INT(MOD(MONTH($J7)-マスタ!$B$4+12,12)/3)+1)) | P7: =IF($L7="","",IF($M7<>"",$M7-$L7,IF(TODAY()>$L7,TODAY()-$L7,0))) | R7: =IF($Q7="","",$Q7*N($F7)) | T7: =IF($A7="","",SUMIFS(発注・納品!$H$3:$H$202,発注・納品!$B$3:$B$202,$A7)) | U7: =IF($Q7="","",N($S7)+N($T7)) | V7: =IF($Q7="","",$Q7-N($U7)) | W7: =IF(N($Q7)=0,"",$V7/$Q7) | X7: =IF($A7="","",COUNTIFS(発注・納品!$B$3:$B$202,$A7)) | Y7: =IF($A7="","",COUNTIFS(発注・納品!$B$3:$B$202,$A7,発注・納品!$M$3:$M$202,"")) | Z7: =IF(N($X7)=0,"",IF(_xlfn.MAXIFS(発注・納品!$M$3:$M$202,発注・納品!$B$3:$B$202,$A7)=0,"",_xlfn.MAXIFS(発注・納品!$M$3:$M$202,発注・納品!$B$3:$B$202,$A7))) | AA7: =IF($A7="","",IF(N($X7)=0,"機器なし",IF(N($Y7)>0,"入荷待ち",IF(COUNTIFS(発注・納品!$B$3:$B$202,$A7,発注・納品!$N$3:$N$202,"")>0,"受入待ち","受入完了")))) | AB7: =IF($A7="","",COUNTIFS(現地作業!$A$3:$A$202,$A7,現地作業!$L$3:$L$202,"予定")) | AC7: =IF($A7="","",COUNTIFS(現地作業!$A$3:$A$202,$A7,現地作業!$L$3:$L$202,"完了")) | AD7: =IF(N($AB7)=0,"",IF(_xlfn.MINIFS(現地作業!$C$3:$C$202,現地作業!$A$3:$A$202,$A7,現地作業!$L$3:$L$202,"予定",現地作業!$C$3:$C$202,">="&TODAY())=0,"",_xlfn.MINIFS(現地作業!$C$3:$C$202,現地作業!$A$3:$A$202,$A7,現地作業!$L$3:$L$202,"予定",現地作業!$C$3:$C$202,">="&TODAY()))) | AF7: =IF($A7="","",SUM(月次工数計画!$G$12:$AD$12)) | AG7: =IF($A7="","",SUMIFS(工数明細!$G$3:$G$302,工数明細!$B$3:$B$302,$A7)) | AH7: =IF($AE7="","",$AE7-N($AG7)) | AI7: =IF(N($AE7)=0,"",$AG7/$AE7) | AJ7: =IF(N($AE7)=0,"",IF($AG7>$AE7,"超過",IF($AG7>=$AE7*0.9,"注意","適正")))
N8: =IF($J8="","",YEAR($J8)-IF(MONTH($J8)<マスタ!$B$4,1,0)) | O8: =IF($J8="","","Q"&(INT(MOD(MONTH($J8)-マスタ!$B$4+12,12)/3)+1)) | P8: =IF($L8="","",IF($M8<>"",$M8-$L8,IF(TODAY()>$L8,TODAY()-$L8,0))) | R8: =IF($Q8="","",$Q8*N($F8)) | T8: =IF($A8="","",SUMIFS(発注・納品!$H$3:$H$202,発注・納品!$B$3:$B$202,$A8)) | U8: =IF($Q8="","",N($S8)+N($T8)) | V8: =IF($Q8="","",$Q8-N($U8)) | W8: =IF(N($Q8)=0,"",$V8/$Q8) | X8: =IF($A8="","",COUNTIFS(発注・納品!$B$3:$B$202,$A8)) | Y8: =IF($A8="","",COUNTIFS(発注・納品!$B$3:$B$202,$A8,発注・納品!$M$3:$M$202,"")) | Z8: =IF(N($X8)=0,"",IF(_xlfn.MAXIFS(発注・納品!$M$3:$M$202,発注・納品!$B$3:$B$202,$A8)=0,"",_xlfn.MAXIFS(発注・納品!$M$3:$M$202,発注・納品!$B$3:$B$202,$A8))) | AA8: =IF($A8="","",IF(N($X8)=0,"機器なし",IF(N($Y8)>0,"入荷待ち",IF(COUNTIFS(発注・納品!$B$3:$B$202,$A8,発注・納品!$N$3:$N$202,"")>0,"受入待ち","受入完了")))) | AB8: =IF($A8="","",COUNTIFS(現地作業!$A$3:$A$202,$A8,現地作業!$L$3:$L$202,"予定")) | AC8: =IF($A8="","",COUNTIFS(現地作業!$A$3:$A$202,$A8,現地作業!$L$3:$L$202,"完了")) | AD8: =IF(N($AB8)=0,"",IF(_xlfn.MINIFS(現地作業!$C$3:$C$202,現地作業!$A$3:$A$202,$A8,現地作業!$L$3:$L$202,"予定",現地作業!$C$3:$C$202,">="&TODAY())=0,"",_xlfn.MINIFS(現地作業!$C$3:$C$202,現地作業!$A$3:$A$202,$A8,現地作業!$L$3:$L$202,"予定",現地作業!$C$3:$C$202,">="&TODAY()))) | AF8: =IF($A8="","",SUM(月次工数計画!$G$13:$AD$13)) | AG8: =IF($A8="","",SUMIFS(工数明細!$G$3:$G$302,工数明細!$B$3:$B$302,$A8)) | AH8: =IF($AE8="","",$AE8-N($AG8)) | AI8: =IF(N($AE8)=0,"",$AG8/$AE8) | AJ8: =IF(N($AE8)=0,"",IF($AG8>$AE8,"超過",IF($AG8>=$AE8*0.9,"注意","適正")))
N9: =IF($J9="","",YEAR($J9)-IF(MONTH($J9)<マスタ!$B$4,1,0)) | O9: =IF($J9="","","Q"&(INT(MOD(MONTH($J9)-マスタ!$B$4+12,12)/3)+1)) | P9: =IF($L9="","",IF($M9<>"",$M9-$L9,IF(TODAY()>$L9,TODAY()-$L9,0))) | R9: =IF($Q9="","",$Q9*N($F9)) | T9: =IF($A9="","",SUMIFS(発注・納品!$H$3:$H$202,発注・納品!$B$3:$B$202,$A9)) | U9: =IF($Q9="","",N($S9)+N($T9)) | V9: =IF($Q9="","",$Q9-N($U9)) | W9: =IF(N($Q9)=0,"",$V9/$Q9) | X9: =IF($A9="","",COUNTIFS(発注・納品!$B$3:$B$202,$A9)) | Y9: =IF($A9="","",COUNTIFS(発注・納品!$B$3:$B$202,$A9,発注・納品!$M$3:$M$202,"")) | Z9: =IF(N($X9)=0,"",IF(_xlfn.MAXIFS(発注・納品!$M$3:$M$202,発注・納品!$B$3:$B$202,$A9)=0,"",_xlfn.MAXIFS(発注・納品!$M$3:$M$202,発注・納品!$B$3:$B$202,$A9))) | AA9: =IF($A9="","",IF(N($X9)=0,"機器なし",IF(N($Y9)>0,"入荷待ち",IF(COUNTIFS(発注・納品!$B$3:$B$202,$A9,発注・納品!$N$3:$N$202,"")>0,"受入待ち","受入完了")))) | AB9: =IF($A9="","",COUNTIFS(現地作業!$A$3:$A$202,$A9,現地作業!$L$3:$L$202,"予定")) | AC9: =IF($A9="","",COUNTIFS(現地作業!$A$3:$A$202,$A9,現地作業!$L$3:$L$202,"完了")) | AD9: =IF(N($AB9)=0,"",IF(_xlfn.MINIFS(現地作業!$C$3:$C$202,現地作業!$A$3:$A$202,$A9,現地作業!$L$3:$L$202,"予定",現地作業!$C$3:$C$202,">="&TODAY())=0,"",_xlfn.MINIFS(現地作業!$C$3:$C$202,現地作業!$A$3:$A$202,$A9,現地作業!$L$3:$L$202,"予定",現地作業!$C$3:$C$202,">="&TODAY()))) | AF9: =IF($A9="","",SUM(月次工数計画!$G$14:$AD$14)) | AG9: =IF($A9="","",SUMIFS(工数明細!$G$3:$G$302,工数明細!$B$3:$B$302,$A9)) | AH9: =IF($AE9="","",$AE9-N($AG9)) | AI9: =IF(N($AE9)=0,"",$AG9/$AE9) | AJ9: =IF(N($AE9)=0,"",IF($AG9>$AE9,"超過",IF($AG9>=$AE9*0.9,"注意","適正")))
N10: =IF($J10="","",YEAR($J10)-IF(MONTH($J10)<マスタ!$B$4,1,0)) | O10: =IF($J10="","","Q"&(INT(MOD(MONTH($J10)-マスタ!$B$4+12,12)/3)+1)) | P10: =IF($L10="","",IF($M10<>"",$M10-$L10,IF(TODAY()>$L10,TODAY()-$L10,0))) | R10: =IF($Q10="","",$Q10*N($F10)) | T10: =IF($A10="","",SUMIFS(発注・納品!$H$3:$H$202,発注・納品!$B$3:$B$202,$A10)) | U10: =IF($Q10="","",N($S10)+N($T10)) | V10: =IF($Q10="","",$Q10-N($U10)) | W10: =IF(N($Q10)=0,"",$V10/$Q10) | X10: =IF($A10="","",COUNTIFS(発注・納品!$B$3:$B$202,$A10)) | Y10: =IF($A10="","",COUNTIFS(発注・納品!$B$3:$B$202,$A10,発注・納品!$M$3:$M$202,"")) | Z10: =IF(N($X10)=0,"",IF(_xlfn.MAXIFS(発注・納品!$M$3:$M$202,発注・納品!$B$3:$B$202,$A10)=0,"",_xlfn.MAXIFS(発注・納品!$M$3:$M$202,発注・納品!$B$3:$B$202,$A10))) | AA10: =IF($A10="","",IF(N($X10)=0,"機器なし",IF(N($Y10)>0,"入荷待ち",IF(COUNTIFS(発注・納品!$B$3:$B$202,$A10,発注・納品!$N$3:$N$202,"")>0,"受入待ち","受入完了")))) | AB10: =IF($A10="","",COUNTIFS(現地作業!$A$3:$A$202,$A10,現地作業!$L$3:$L$202,"予定")) | AC10: =IF($A10="","",COUNTIFS(現地作業!$A$3:$A$202,$A10,現地作業!$L$3:$L$202,"完了")) | AD10: =IF(N($AB10)=0,"",IF(_xlfn.MINIFS(現地作業!$C$3:$C$202,現地作業!$A$3:$A$202,$A10,現地作業!$L$3:$L$202,"予定",現地作業!$C$3:$C$202,">="&TODAY())=0,"",_xlfn.MINIFS(現地作業!$C$3:$C$202,現地作業!$A$3:$A$202,$A10,現地作業!$L$3:$L$202,"予定",現地作業!$C$3:$C$202,">="&TODAY()))) | AF10: =IF($A10="","",SUM(月次工数計画!$G$15:$AD$15)) | AG10: =IF($A10="","",SUMIFS(工数明細!$G$3:$G$302,工数明細!$B$3:$B$302,$A10)) | AH10: =IF($AE10="","",$AE10-N($AG10)) | AI10: =IF(N($AE10)=0,"",$AG10/$AE10) | AJ10: =IF(N($AE10)=0,"",IF($AG10>$AE10,"超過",IF($AG10>=$AE10*0.9,"注意","適正")))
N11: =IF($J11="","",YEAR($J11)-IF(MONTH($J11)<マスタ!$B$4,1,0)) | O11: =IF($J11="","","Q"&(INT(MOD(MONTH($J11)-マスタ!$B$4+12,12)/3)+1)) | P11: =IF($L11="","",IF($M11<>"",$M11-$L11,IF(TODAY()>$L11,TODAY()-$L11,0))) | R11: =IF($Q11="","",$Q11*N($F11)) | T11: =IF($A11="","",SUMIFS(発注・納品!$H$3:$H$202,発注・納品!$B$3:$B$202,$A11)) | U11: =IF($Q11="","",N($S11)+N($T11)) | V11: =IF($Q11="","",$Q11-N($U11)) | W11: =IF(N($Q11)=0,"",$V11/$Q11) | X11: =IF($A11="","",COUNTIFS(発注・納品!$B$3:$B$202,$A11)) | Y11: =IF($A11="","",COUNTIFS(発注・納品!$B$3:$B$202,$A11,発注・納品!$M$3:$M$202,"")) | Z11: =IF(N($X11)=0,"",IF(_xlfn.MAXIFS(発注・納品!$M$3:$M$202,発注・納品!$B$3:$B$202,$A11)=0,"",_xlfn.MAXIFS(発注・納品!$M$3:$M$202,発注・納品!$B$3:$B$202,$A11))) | AA11: =IF($A11="","",IF(N($X11)=0,"機器なし",IF(N($Y11)>0,"入荷待ち",IF(COUNTIFS(発注・納品!$B$3:$B$202,$A11,発注・納品!$N$3:$N$202,"")>0,"受入待ち","受入完了")))) | AB11: =IF($A11="","",COUNTIFS(現地作業!$A$3:$A$202,$A11,現地作業!$L$3:$L$202,"予定")) | AC11: =IF($A11="","",COUNTIFS(現地作業!$A$3:$A$202,$A11,現地作業!$L$3:$L$202,"完了")) | AD11: =IF(N($AB11)=0,"",IF(_xlfn.MINIFS(現地作業!$C$3:$C$202,現地作業!$A$3:$A$202,$A11,現地作業!$L$3:$L$202,"予定",現地作業!$C$3:$C$202,">="&TODAY())=0,"",_xlfn.MINIFS(現地作業!$C$3:$C$202,現地作業!$A$3:$A$202,$A11,現地作業!$L$3:$L$202,"予定",現地作業!$C$3:$C$202,">="&TODAY()))) | AF11: =IF($A11="","",SUM(月次工数計画!$G$16:$AD$16)) | AG11: =IF($A11="","",SUMIFS(工数明細!$G$3:$G$302,工数明細!$B$3:$B$302,$A11)) | AH11: =IF($AE11="","",$AE11-N($AG11)) | AI11: =IF(N($AE11)=0,"",$AG11/$AE11) | AJ11: =IF(N($AE11)=0,"",IF($AG11>$AE11,"超過",IF($AG11>=$AE11*0.9,"注意","適正")))
N12: =IF($J12="","",YEAR($J12)-IF(MONTH($J12)<マスタ!$B$4,1,0)) | O12: =IF($J12="","","Q"&(INT(MOD(MONTH($J12)-マスタ!$B$4+12,12)/3)+1)) | P12: =IF($L12="","",IF($M12<>"",$M12-$L12,IF(TODAY()>$L12,TODAY()-$L12,0))) | R12: =IF($Q12="","",$Q12*N($F12)) | T12: =IF($A12="","",SUMIFS(発注・納品!$H$3:$H$202,発注・納品!$B$3:$B$202,$A12)) | U12: =IF($Q12="","",N($S12)+N($T12)) | V12: =IF($Q12="","",$Q12-N($U12)) | W12: =IF(N($Q12)=0,"",$V12/$Q12) | X12: =IF($A12="","",COUNTIFS(発注・納品!$B$3:$B$202,$A12)) | Y12: =IF($A12="","",COUNTIFS(発注・納品!$B$3:$B$202,$A12,発注・納品!$M$3:$M$202,"")) | Z12: =IF(N($X12)=0,"",IF(_xlfn.MAXIFS(発注・納品!$M$3:$M$202,発注・納品!$B$3:$B$202,$A12)=0,"",_xlfn.MAXIFS(発注・納品!$M$3:$M$202,発注・納品!$B$3:$B$202,$A12))) | AA12: =IF($A12="","",IF(N($X12)=0,"機器なし",IF(N($Y12)>0,"入荷待ち",IF(COUNTIFS(発注・納品!$B$3:$B$202,$A12,発注・納品!$N$3:$N$202,"")>0,"受入待ち","受入完了")))) | AB12: =IF($A12="","",COUNTIFS(現地作業!$A$3:$A$202,$A12,現地作業!$L$3:$L$202,"予定")) | AC12: =IF($A12="","",COUNTIFS(現地作業!$A$3:$A$202,$A12,現地作業!$L$3:$L$202,"完了")) | AD12: =IF(N($AB12)=0,"",IF(_xlfn.MINIFS(現地作業!$C$3:$C$202,現地作業!$A$3:$A$202,$A12,現地作業!$L$3:$L$202,"予定",現地作業!$C$3:$C$202,">="&TODAY())=0,"",_xlfn.MINIFS(現地作業!$C$3:$C$202,現地作業!$A$3:$A$202,$A12,現地作業!$L$3:$L$202,"予定",現地作業!$C$3:$C$202,">="&TODAY()))) | AF12: =IF($A12="","",SUM(月次工数計画!$G$17:$AD$17)) | AG12: =IF($A12="","",SUMIFS(工数明細!$G$3:$G$302,工数明細!$B$3:$B$302,$A12)) | AH12: =IF($AE12="","",$AE12-N($AG12)) | AI12: =IF(N($AE12)=0,"",$AG12/$AE12) | AJ12: =IF(N($AE12)=0,"",IF($AG12>$AE12,"超過",IF($AG12>=$AE12*0.9,"注意","適正")))
N13: =IF($J13="","",YEAR($J13)-IF(MONTH($J13)<マスタ!$B$4,1,0)) | O13: =IF($J13="","","Q"&(INT(MOD(MONTH($J13)-マスタ!$B$4+12,12)/3)+1)) | P13: =IF($L13="","",IF($M13<>"",$M13-$L13,IF(TODAY()>$L13,TODAY()-$L13,0))) | R13: =IF($Q13="","",$Q13*N($F13)) | T13: =IF($A13="","",SUMIFS(発注・納品!$H$3:$H$202,発注・納品!$B$3:$B$202,$A13)) | U13: =IF($Q13="","",N($S13)+N($T13)) | V13: =IF($Q13="","",$Q13-N($U13)) | W13: =IF(N($Q13)=0,"",$V13/$Q13) | X13: =IF($A13="","",COUNTIFS(発注・納品!$B$3:$B$202,$A13)) | Y13: =IF($A13="","",COUNTIFS(発注・納品!$B$3:$B$202,$A13,発注・納品!$M$3:$M$202,"")) | Z13: =IF(N($X13)=0,"",IF(_xlfn.MAXIFS(発注・納品!$M$3:$M$202,発注・納品!$B$3:$B$202,$A13)=0,"",_xlfn.MAXIFS(発注・納品!$M$3:$M$202,発注・納品!$B$3:$B$202,$A13))) | AA13: =IF($A13="","",IF(N($X13)=0,"機器なし",IF(N($Y13)>0,"入荷待ち",IF(COUNTIFS(発注・納品!$B$3:$B$202,$A13,発注・納品!$N$3:$N$202,"")>0,"受入待ち","受入完了")))) | AB13: =IF($A13="","",COUNTIFS(現地作業!$A$3:$A$202,$A13,現地作業!$L$3:$L$202,"予定")) | AC13: =IF($A13="","",COUNTIFS(現地作業!$A$3:$A$202,$A13,現地作業!$L$3:$L$202,"完了")) | AD13: =IF(N($AB13)=0,"",IF(_xlfn.MINIFS(現地作業!$C$3:$C$202,現地作業!$A$3:$A$202,$A13,現地作業!$L$3:$L$202,"予定",現地作業!$C$3:$C$202,">="&TODAY())=0,"",_xlfn.MINIFS(現地作業!$C$3:$C$202,現地作業!$A$3:$A$202,$A13,現地作業!$L$3:$L$202,"予定",現地作業!$C$3:$C$202,">="&TODAY()))) | AF13: =IF($A13="","",SUM(月次工数計画!$G$18:$AD$18)) | AG13: =IF($A13="","",SUMIFS(工数明細!$G$3:$G$302,工数明細!$B$3:$B$302,$A13)) | AH13: =IF($AE13="","",$AE13-N($AG13)) | AI13: =IF(N($AE13)=0,"",$AG13/$AE13) | AJ13: =IF(N($AE13)=0,"",IF($AG13>$AE13,"超過",IF($AG13>=$AE13*0.9,"注意","適正")))
N14: =IF($J14="","",YEAR($J14)-IF(MONTH($J14)<マスタ!$B$4,1,0)) | O14: =IF($J14="","","Q"&(INT(MOD(MONTH($J14)-マスタ!$B$4+12,12)/3)+1)) | P14: =IF($L14="","",IF($M14<>"",$M14-$L14,IF(TODAY()>$L14,TODAY()-$L14,0))) | R14: =IF($Q14="","",$Q14*N($F14)) | T14: =IF($A14="","",SUMIFS(発注・納品!$H$3:$H$202,発注・納品!$B$3:$B$202,$A14)) | U14: =IF($Q14="","",N($S14)+N($T14)) | V14: =IF($Q14="","",$Q14-N($U14)) | W14: =IF(N($Q14)=0,"",$V14/$Q14) | X14: =IF($A14="","",COUNTIFS(発注・納品!$B$3:$B$202,$A14)) | Y14: =IF($A14="","",COUNTIFS(発注・納品!$B$3:$B$202,$A14,発注・納品!$M$3:$M$202,"")) | Z14: =IF(N($X14)=0,"",IF(_xlfn.MAXIFS(発注・納品!$M$3:$M$202,発注・納品!$B$3:$B$202,$A14)=0,"",_xlfn.MAXIFS(発注・納品!$M$3:$M$202,発注・納品!$B$3:$B$202,$A14))) | AA14: =IF($A14="","",IF(N($X14)=0,"機器なし",IF(N($Y14)>0,"入荷待ち",IF(COUNTIFS(発注・納品!$B$3:$B$202,$A14,発注・納品!$N$3:$N$202,"")>0,"受入待ち","受入完了")))) | AB14: =IF($A14="","",COUNTIFS(現地作業!$A$3:$A$202,$A14,現地作業!$L$3:$L$202,"予定")) | AC14: =IF($A14="","",COUNTIFS(現地作業!$A$3:$A$202,$A14,現地作業!$L$3:$L$202,"完了")) | AD14: =IF(N($AB14)=0,"",IF(_xlfn.MINIFS(現地作業!$C$3:$C$202,現地作業!$A$3:$A$202,$A14,現地作業!$L$3:$L$202,"予定",現地作業!$C$3:$C$202,">="&TODAY())=0,"",_xlfn.MINIFS(現地作業!$C$3:$C$202,現地作業!$A$3:$A$202,$A14,現地作業!$L$3:$L$202,"予定",現地作業!$C$3:$C$202,">="&TODAY()))) | AF14: =IF($A14="","",SUM(月次工数計画!$G$19:$AD$19)) | AG14: =IF($A14="","",SUMIFS(工数明細!$G$3:$G$302,工数明細!$B$3:$B$302,$A14)) | AH14: =IF($AE14="","",$AE14-N($AG14)) | AI14: =IF(N($AE14)=0,"",$AG14/$AE14) | AJ14: =IF(N($AE14)=0,"",IF($AG14>$AE14,"超過",IF($AG14>=$AE14*0.9,"注意","適正")))
N15: =IF($J15="","",YEAR($J15)-IF(MONTH($J15)<マスタ!$B$4,1,0)) | O15: =IF($J15="","","Q"&(INT(MOD(MONTH($J15)-マスタ!$B$4+12,12)/3)+1)) | P15: =IF($L15="","",IF($M15<>"",$M15-$L15,IF(TODAY()>$L15,TODAY()-$L15,0))) | R15: =IF($Q15="","",$Q15*N($F15)) | T15: =IF($A15="","",SUMIFS(発注・納品!$H$3:$H$202,発注・納品!$B$3:$B$202,$A15)) | U15: =IF($Q15="","",N($S15)+N($T15)) | V15: =IF($Q15="","",$Q15-N($U15)) | W15: =IF(N($Q15)=0,"",$V15/$Q15) | X15: =IF($A15="","",COUNTIFS(発注・納品!$B$3:$B$202,$A15)) | Y15: =IF($A15="","",COUNTIFS(発注・納品!$B$3:$B$202,$A15,発注・納品!$M$3:$M$202,"")) | Z15: =IF(N($X15)=0,"",IF(_xlfn.MAXIFS(発注・納品!$M$3:$M$202,発注・納品!$B$3:$B$202,$A15)=0,"",_xlfn.MAXIFS(発注・納品!$M$3:$M$202,発注・納品!$B$3:$B$202,$A15))) | AA15: =IF($A15="","",IF(N($X15)=0,"機器なし",IF(N($Y15)>0,"入荷待ち",IF(COUNTIFS(発注・納品!$B$3:$B$202,$A15,発注・納品!$N$3:$N$202,"")>0,"受入待ち","受入完了")))) | AB15: =IF($A15="","",COUNTIFS(現地作業!$A$3:$A$202,$A15,現地作業!$L$3:$L$202,"予定")) | AC15: =IF($A15="","",COUNTIFS(現地作業!$A$3:$A$202,$A15,現地作業!$L$3:$L$202,"完了")) | AD15: =IF(N($AB15)=0,"",IF(_xlfn.MINIFS(現地作業!$C$3:$C$202,現地作業!$A$3:$A$202,$A15,現地作業!$L$3:$L$202,"予定",現地作業!$C$3:$C$202,">="&TODAY())=0,"",_xlfn.MINIFS(現地作業!$C$3:$C$202,現地作業!$A$3:$A$202,$A15,現地作業!$L$3:$L$202,"予定",現地作業!$C$3:$C$202,">="&TODAY()))) | AF15: =IF($A15="","",SUM(月次工数計画!$G$20:$AD$20)) | AG15: =IF($A15="","",SUMIFS(工数明細!$G$3:$G$302,工数明細!$B$3:$B$302,$A15)) | AH15: =IF($AE15="","",$AE15-N($AG15)) | AI15: =IF(N($AE15)=0,"",$AG15/$AE15) | AJ15: =IF(N($AE15)=0,"",IF($AG15>$AE15,"超過",IF($AG15>=$AE15*0.9,"注意","適正")))
N16: =IF($J16="","",YEAR($J16)-IF(MONTH($J16)<マスタ!$B$4,1,0)) | O16: =IF($J16="","","Q"&(INT(MOD(MONTH($J16)-マスタ!$B$4+12,12)/3)+1)) | P16: =IF($L16="","",IF($M16<>"",$M16-$L16,IF(TODAY()>$L16,TODAY()-$L16,0))) | R16: =IF($Q16="","",$Q16*N($F16)) | T16: =IF($A16="","",SUMIFS(発注・納品!$H$3:$H$202,発注・納品!$B$3:$B$202,$A16)) | U16: =IF($Q16="","",N($S16)+N($T16)) | V16: =IF($Q16="","",$Q16-N($U16)) | W16: =IF(N($Q16)=0,"",$V16/$Q16) | X16: =IF($A16="","",COUNTIFS(発注・納品!$B$3:$B$202,$A16)) | Y16: =IF($A16="","",COUNTIFS(発注・納品!$B$3:$B$202,$A16,発注・納品!$M$3:$M$202,"")) | Z16: =IF(N($X16)=0,"",IF(_xlfn.MAXIFS(発注・納品!$M$3:$M$202,発注・納品!$B$3:$B$202,$A16)=0,"",_xlfn.MAXIFS(発注・納品!$M$3:$M$202,発注・納品!$B$3:$B$202,$A16))) | AA16: =IF($A16="","",IF(N($X16)=0,"機器なし",IF(N($Y16)>0,"入荷待ち",IF(COUNTIFS(発注・納品!$B$3:$B$202,$A16,発注・納品!$N$3:$N$202,"")>0,"受入待ち","受入完了")))) | AB16: =IF($A16="","",COUNTIFS(現地作業!$A$3:$A$202,$A16,現地作業!$L$3:$L$202,"予定")) | AC16: =IF($A16="","",COUNTIFS(現地作業!$A$3:$A$202,$A16,現地作業!$L$3:$L$202,"完了")) | AD16: =IF(N($AB16)=0,"",IF(_xlfn.MINIFS(現地作業!$C$3:$C$202,現地作業!$A$3:$A$202,$A16,現地作業!$L$3:$L$202,"予定",現地作業!$C$3:$C$202,">="&TODAY())=0,"",_xlfn.MINIFS(現地作業!$C$3:$C$202,現地作業!$A$3:$A$202,$A16,現地作業!$L$3:$L$202,"予定",現地作業!$C$3:$C$202,">="&TODAY()))) | AF16: =IF($A16="","",SUM(月次工数計画!$G$21:$AD$21)) | AG16: =IF($A16="","",SUMIFS(工数明細!$G$3:$G$302,工数明細!$B$3:$B$302,$A16)) | AH16: =IF($AE16="","",$AE16-N($AG16)) | AI16: =IF(N($AE16)=0,"",$AG16/$AE16) | AJ16: =IF(N($AE16)=0,"",IF($AG16>$AE16,"超過",IF($AG16>=$AE16*0.9,"注意","適正")))
N17: =IF($J17="","",YEAR($J17)-IF(MONTH($J17)<マスタ!$B$4,1,0)) | O17: =IF($J17="","","Q"&(INT(MOD(MONTH($J17)-マスタ!$B$4+12,12)/3)+1)) | P17: =IF($L17="","",IF($M17<>"",$M17-$L17,IF(TODAY()>$L17,TODAY()-$L17,0))) | R17: =IF($Q17="","",$Q17*N($F17)) | T17: =IF($A17="","",SUMIFS(発注・納品!$H$3:$H$202,発注・納品!$B$3:$B$202,$A17)) | U17: =IF($Q17="","",N($S17)+N($T17)) | V17: =IF($Q17="","",$Q17-N($U17)) | W17: =IF(N($Q17)=0,"",$V17/$Q17) | X17: =IF($A17="","",COUNTIFS(発注・納品!$B$3:$B$202,$A17)) | Y17: =IF($A17="","",COUNTIFS(発注・納品!$B$3:$B$202,$A17,発注・納品!$M$3:$M$202,"")) | Z17: =IF(N($X17)=0,"",IF(_xlfn.MAXIFS(発注・納品!$M$3:$M$202,発注・納品!$B$3:$B$202,$A17)=0,"",_xlfn.MAXIFS(発注・納品!$M$3:$M$202,発注・納品!$B$3:$B$202,$A17))) | AA17: =IF($A17="","",IF(N($X17)=0,"機器なし",IF(N($Y17)>0,"入荷待ち",IF(COUNTIFS(発注・納品!$B$3:$B$202,$A17,発注・納品!$N$3:$N$202,"")>0,"受入待ち","受入完了")))) | AB17: =IF($A17="","",COUNTIFS(現地作業!$A$3:$A$202,$A17,現地作業!$L$3:$L$202,"予定")) | AC17: =IF($A17="","",COUNTIFS(現地作業!$A$3:$A$202,$A17,現地作業!$L$3:$L$202,"完了")) | AD17: =IF(N($AB17)=0,"",IF(_xlfn.MINIFS(現地作業!$C$3:$C$202,現地作業!$A$3:$A$202,$A17,現地作業!$L$3:$L$202,"予定",現地作業!$C$3:$C$202,">="&TODAY())=0,"",_xlfn.MINIFS(現地作業!$C$3:$C$202,現地作業!$A$3:$A$202,$A17,現地作業!$L$3:$L$202,"予定",現地作業!$C$3:$C$202,">="&TODAY()))) | AF17: =IF($A17="","",SUM(月次工数計画!$G$22:$AD$22)) | AG17: =IF($A17="","",SUMIFS(工数明細!$G$3:$G$302,工数明細!$B$3:$B$302,$A17)) | AH17: =IF($AE17="","",$AE17-N($AG17)) | AI17: =IF(N($AE17)=0,"",$AG17/$AE17) | AJ17: =IF(N($AE17)=0,"",IF($AG17>$AE17,"超過",IF($AG17>=$AE17*0.9,"注意","適正")))
N18: =IF($J18="","",YEAR($J18)-IF(MONTH($J18)<マスタ!$B$4,1,0)) | O18: =IF($J18="","","Q"&(INT(MOD(MONTH($J18)-マスタ!$B$4+12,12)/3)+1)) | P18: =IF($L18="","",IF($M18<>"",$M18-$L18,IF(TODAY()>$L18,TODAY()-$L18,0))) | R18: =IF($Q18="","",$Q18*N($F18)) | T18: =IF($A18="","",SUMIFS(発注・納品!$H$3:$H$202,発注・納品!$B$3:$B$202,$A18)) | U18: =IF($Q18="","",N($S18)+N($T18)) | V18: =IF($Q18="","",$Q18-N($U18)) | W18: =IF(N($Q18)=0,"",$V18/$Q18) | X18: =IF($A18="","",COUNTIFS(発注・納品!$B$3:$B$202,$A18)) | Y18: =IF($A18="","",COUNTIFS(発注・納品!$B$3:$B$202,$A18,発注・納品!$M$3:$M$202,"")) | Z18: =IF(N($X18)=0,"",IF(_xlfn.MAXIFS(発注・納品!$M$3:$M$202,発注・納品!$B$3:$B$202,$A18)=0,"",_xlfn.MAXIFS(発注・納品!$M$3:$M$202,発注・納品!$B$3:$B$202,$A18))) | AA18: =IF($A18="","",IF(N($X18)=0,"機器なし",IF(N($Y18)>0,"入荷待ち",IF(COUNTIFS(発注・納品!$B$3:$B$202,$A18,発注・納品!$N$3:$N$202,"")>0,"受入待ち","受入完了")))) | AB18: =IF($A18="","",COUNTIFS(現地作業!$A$3:$A$202,$A18,現地作業!$L$3:$L$202,"予定")) | AC18: =IF($A18="","",COUNTIFS(現地作業!$A$3:$A$202,$A18,現地作業!$L$3:$L$202,"完了")) | AD18: =IF(N($AB18)=0,"",IF(_xlfn.MINIFS(現地作業!$C$3:$C$202,現地作業!$A$3:$A$202,$A18,現地作業!$L$3:$L$202,"予定",現地作業!$C$3:$C$202,">="&TODAY())=0,"",_xlfn.MINIFS(現地作業!$C$3:$C$202,現地作業!$A$3:$A$202,$A18,現地作業!$L$3:$L$202,"予定",現地作業!$C$3:$C$202,">="&TODAY()))) | AF18: =IF($A18="","",SUM(月次工数計画!$G$23:$AD$23)) | AG18: =IF($A18="","",SUMIFS(工数明細!$G$3:$G$302,工数明細!$B$3:$B$302,$A18)) | AH18: =IF($AE18="","",$AE18-N($AG18)) | AI18: =IF(N($AE18)=0,"",$AG18/$AE18) | AJ18: =IF(N($AE18)=0,"",IF($AG18>$AE18,"超過",IF($AG18>=$AE18*0.9,"注意","適正")))
N19: =IF($J19="","",YEAR($J19)-IF(MONTH($J19)<マスタ!$B$4,1,0)) | O19: =IF($J19="","","Q"&(INT(MOD(MONTH($J19)-マスタ!$B$4+12,12)/3)+1)) | P19: =IF($L19="","",IF($M19<>"",$M19-$L19,IF(TODAY()>$L19,TODAY()-$L19,0))) | R19: =IF($Q19="","",$Q19*N($F19)) | T19: =IF($A19="","",SUMIFS(発注・納品!$H$3:$H$202,発注・納品!$B$3:$B$202,$A19)) | U19: =IF($Q19="","",N($S19)+N($T19)) | V19: =IF($Q19="","",$Q19-N($U19)) | W19: =IF(N($Q19)=0,"",$V19/$Q19) | X19: =IF($A19="","",COUNTIFS(発注・納品!$B$3:$B$202,$A19)) | Y19: =IF($A19="","",COUNTIFS(発注・納品!$B$3:$B$202,$A19,発注・納品!$M$3:$M$202,"")) | Z19: =IF(N($X19)=0,"",IF(_xlfn.MAXIFS(発注・納品!$M$3:$M$202,発注・納品!$B$3:$B$202,$A19)=0,"",_xlfn.MAXIFS(発注・納品!$M$3:$M$202,発注・納品!$B$3:$B$202,$A19))) | AA19: =IF($A19="","",IF(N($X19)=0,"機器なし",IF(N($Y19)>0,"入荷待ち",IF(COUNTIFS(発注・納品!$B$3:$B$202,$A19,発注・納品!$N$3:$N$202,"")>0,"受入待ち","受入完了")))) | AB19: =IF($A19="","",COUNTIFS(現地作業!$A$3:$A$202,$A19,現地作業!$L$3:$L$202,"予定")) | AC19: =IF($A19="","",COUNTIFS(現地作業!$A$3:$A$202,$A19,現地作業!$L$3:$L$202,"完了")) | AD19: =IF(N($AB19)=0,"",IF(_xlfn.MINIFS(現地作業!$C$3:$C$202,現地作業!$A$3:$A$202,$A19,現地作業!$L$3:$L$202,"予定",現地作業!$C$3:$C$202,">="&TODAY())=0,"",_xlfn.MINIFS(現地作業!$C$3:$C$202,現地作業!$A$3:$A$202,$A19,現地作業!$L$3:$L$202,"予定",現地作業!$C$3:$C$202,">="&TODAY()))) | AF19: =IF($A19="","",SUM(月次工数計画!$G$24:$AD$24)) | AG19: =IF($A19="","",SUMIFS(工数明細!$G$3:$G$302,工数明細!$B$3:$B$302,$A19)) | AH19: =IF($AE19="","",$AE19-N($AG19)) | AI19: =IF(N($AE19)=0,"",$AG19/$AE19) | AJ19: =IF(N($AE19)=0,"",IF($AG19>$AE19,"超過",IF($AG19>=$AE19*0.9,"注意","適正")))
N20: =IF($J20="","",YEAR($J20)-IF(MONTH($J20)<マスタ!$B$4,1,0)) | O20: =IF($J20="","","Q"&(INT(MOD(MONTH($J20)-マスタ!$B$4+12,12)/3)+1)) | P20: =IF($L20="","",IF($M20<>"",$M20-$L20,IF(TODAY()>$L20,TODAY()-$L20,0))) | R20: =IF($Q20="","",$Q20*N($F20)) | T20: =IF($A20="","",SUMIFS(発注・納品!$H$3:$H$202,発注・納品!$B$3:$B$202,$A20)) | U20: =IF($Q20="","",N($S20)+N($T20)) | V20: =IF($Q20="","",$Q20-N($U20)) | W20: =IF(N($Q20)=0,"",$V20/$Q20) | X20: =IF($A20="","",COUNTIFS(発注・納品!$B$3:$B$202,$A20)) | Y20: =IF($A20="","",COUNTIFS(発注・納品!$B$3:$B$202,$A20,発注・納品!$M$3:$M$202,"")) | Z20: =IF(N($X20)=0,"",IF(_xlfn.MAXIFS(発注・納品!$M$3:$M$202,発注・納品!$B$3:$B$202,$A20)=0,"",_xlfn.MAXIFS(発注・納品!$M$3:$M$202,発注・納品!$B$3:$B$202,$A20))) | AA20: =IF($A20="","",IF(N($X20)=0,"機器なし",IF(N($Y20)>0,"入荷待ち",IF(COUNTIFS(発注・納品!$B$3:$B$202,$A20,発注・納品!$N$3:$N$202,"")>0,"受入待ち","受入完了")))) | AB20: =IF($A20="","",COUNTIFS(現地作業!$A$3:$A$202,$A20,現地作業!$L$3:$L$202,"予定")) | AC20: =IF($A20="","",COUNTIFS(現地作業!$A$3:$A$202,$A20,現地作業!$L$3:$L$202,"完了")) | AD20: =IF(N($AB20)=0,"",IF(_xlfn.MINIFS(現地作業!$C$3:$C$202,現地作業!$A$3:$A$202,$A20,現地作業!$L$3:$L$202,"予定",現地作業!$C$3:$C$202,">="&TODAY())=0,"",_xlfn.MINIFS(現地作業!$C$3:$C$202,現地作業!$A$3:$A$202,$A20,現地作業!$L$3:$L$202,"予定",現地作業!$C$3:$C$202,">="&TODAY()))) | AF20: =IF($A20="","",SUM(月次工数計画!$G$25:$AD$25)) | AG20: =IF($A20="","",SUMIFS(工数明細!$G$3:$G$302,工数明細!$B$3:$B$302,$A20)) | AH20: =IF($AE20="","",$AE20-N($AG20)) | AI20: =IF(N($AE20)=0,"",$AG20/$AE20) | AJ20: =IF(N($AE20)=0,"",IF($AG20>$AE20,"超過",IF($AG20>=$AE20*0.9,"注意","適正")))
N21: =IF($J21="","",YEAR($J21)-IF(MONTH($J21)<マスタ!$B$4,1,0)) | O21: =IF($J21="","","Q"&(INT(MOD(MONTH($J21)-マスタ!$B$4+12,12)/3)+1)) | P21: =IF($L21="","",IF($M21<>"",$M21-$L21,IF(TODAY()>$L21,TODAY()-$L21,0))) | R21: =IF($Q21="","",$Q21*N($F21)) | T21: =IF($A21="","",SUMIFS(発注・納品!$H$3:$H$202,発注・納品!$B$3:$B$202,$A21)) | U21: =IF($Q21="","",N($S21)+N($T21)) | V21: =IF($Q21="","",$Q21-N($U21)) | W21: =IF(N($Q21)=0,"",$V21/$Q21) | X21: =IF($A21="","",COUNTIFS(発注・納品!$B$3:$B$202,$A21)) | Y21: =IF($A21="","",COUNTIFS(発注・納品!$B$3:$B$202,$A21,発注・納品!$M$3:$M$202,"")) | Z21: =IF(N($X21)=0,"",IF(_xlfn.MAXIFS(発注・納品!$M$3:$M$202,発注・納品!$B$3:$B$202,$A21)=0,"",_xlfn.MAXIFS(発注・納品!$M$3:$M$202,発注・納品!$B$3:$B$202,$A21))) | AA21: =IF($A21="","",IF(N($X21)=0,"機器なし",IF(N($Y21)>0,"入荷待ち",IF(COUNTIFS(発注・納品!$B$3:$B$202,$A21,発注・納品!$N$3:$N$202,"")>0,"受入待ち","受入完了")))) | AB21: =IF($A21="","",COUNTIFS(現地作業!$A$3:$A$202,$A21,現地作業!$L$3:$L$202,"予定")) | AC21: =IF($A21="","",COUNTIFS(現地作業!$A$3:$A$202,$A21,現地作業!$L$3:$L$202,"完了")) | AD21: =IF(N($AB21)=0,"",IF(_xlfn.MINIFS(現地作業!$C$3:$C$202,現地作業!$A$3:$A$202,$A21,現地作業!$L$3:$L$202,"予定",現地作業!$C$3:$C$202,">="&TODAY())=0,"",_xlfn.MINIFS(現地作業!$C$3:$C$202,現地作業!$A$3:$A$202,$A21,現地作業!$L$3:$L$202,"予定",現地作業!$C$3:$C$202,">="&TODAY()))) | AF21: =IF($A21="","",SUM(月次工数計画!$G$26:$AD$26)) | AG21: =IF($A21="","",SUMIFS(工数明細!$G$3:$G$302,工数明細!$B$3:$B$302,$A21)) | AH21: =IF($AE21="","",$AE21-N($AG21)) | AI21: =IF(N($AE21)=0,"",$AG21/$AE21) | AJ21: =IF(N($AE21)=0,"",IF($AG21>$AE21,"超過",IF($AG21>=$AE21*0.9,"注意","適正")))
N22: =IF($J22="","",YEAR($J22)-IF(MONTH($J22)<マスタ!$B$4,1,0)) | O22: =IF($J22="","","Q"&(INT(MOD(MONTH($J22)-マスタ!$B$4+12,12)/3)+1)) | P22: =IF($L22="","",IF($M22<>"",$M22-$L22,IF(TODAY()>$L22,TODAY()-$L22,0))) | R22: =IF($Q22="","",$Q22*N($F22)) | T22: =IF($A22="","",SUMIFS(発注・納品!$H$3:$H$202,発注・納品!$B$3:$B$202,$A22)) | U22: =IF($Q22="","",N($S22)+N($T22)) | V22: =IF($Q22="","",$Q22-N($U22)) | W22: =IF(N($Q22)=0,"",$V22/$Q22) | X22: =IF($A22="","",COUNTIFS(発注・納品!$B$3:$B$202,$A22)) | Y22: =IF($A22="","",COUNTIFS(発注・納品!$B$3:$B$202,$A22,発注・納品!$M$3:$M$202,"")) | Z22: =IF(N($X22)=0,"",IF(_xlfn.MAXIFS(発注・納品!$M$3:$M$202,発注・納品!$B$3:$B$202,$A22)=0,"",_xlfn.MAXIFS(発注・納品!$M$3:$M$202,発注・納品!$B$3:$B$202,$A22))) | AA22: =IF($A22="","",IF(N($X22)=0,"機器なし",IF(N($Y22)>0,"入荷待ち",IF(COUNTIFS(発注・納品!$B$3:$B$202,$A22,発注・納品!$N$3:$N$202,"")>0,"受入待ち","受入完了")))) | AB22: =IF($A22="","",COUNTIFS(現地作業!$A$3:$A$202,$A22,現地作業!$L$3:$L$202,"予定")) | AC22: =IF($A22="","",COUNTIFS(現地作業!$A$3:$A$202,$A22,現地作業!$L$3:$L$202,"完了")) | AD22: =IF(N($AB22)=0,"",IF(_xlfn.MINIFS(現地作業!$C$3:$C$202,現地作業!$A$3:$A$202,$A22,現地作業!$L$3:$L$202,"予定",現地作業!$C$3:$C$202,">="&TODAY())=0,"",_xlfn.MINIFS(現地作業!$C$3:$C$202,現地作業!$A$3:$A$202,$A22,現地作業!$L$3:$L$202,"予定",現地作業!$C$3:$C$202,">="&TODAY()))) | AF22: =IF($A22="","",SUM(月次工数計画!$G$27:$AD$27)) | AG22: =IF($A22="","",SUMIFS(工数明細!$G$3:$G$302,工数明細!$B$3:$B$302,$A22)) | AH22: =IF($AE22="","",$AE22-N($AG22)) | AI22: =IF(N($AE22)=0,"",$AG22/$AE22) | AJ22: =IF(N($AE22)=0,"",IF($AG22>$AE22,"超過",IF($AG22>=$AE22*0.9,"注意","適正")))
N23: =IF($J23="","",YEAR($J23)-IF(MONTH($J23)<マスタ!$B$4,1,0)) | O23: =IF($J23="","","Q"&(INT(MOD(MONTH($J23)-マスタ!$B$4+12,12)/3)+1)) | P23: =IF($L23="","",IF($M23<>"",$M23-$L23,IF(TODAY()>$L23,TODAY()-$L23,0))) | R23: =IF($Q23="","",$Q23*N($F23)) | T23: =IF($A23="","",SUMIFS(発注・納品!$H$3:$H$202,発注・納品!$B$3:$B$202,$A23)) | U23: =IF($Q23="","",N($S23)+N($T23)) | V23: =IF($Q23="","",$Q23-N($U23)) | W23: =IF(N($Q23)=0,"",$V23/$Q23) | X23: =IF($A23="","",COUNTIFS(発注・納品!$B$3:$B$202,$A23)) | Y23: =IF($A23="","",COUNTIFS(発注・納品!$B$3:$B$202,$A23,発注・納品!$M$3:$M$202,"")) | Z23: =IF(N($X23)=0,"",IF(_xlfn.MAXIFS(発注・納品!$M$3:$M$202,発注・納品!$B$3:$B$202,$A23)=0,"",_xlfn.MAXIFS(発注・納品!$M$3:$M$202,発注・納品!$B$3:$B$202,$A23))) | AA23: =IF($A23="","",IF(N($X23)=0,"機器なし",IF(N($Y23)>0,"入荷待ち",IF(COUNTIFS(発注・納品!$B$3:$B$202,$A23,発注・納品!$N$3:$N$202,"")>0,"受入待ち","受入完了")))) | AB23: =IF($A23="","",COUNTIFS(現地作業!$A$3:$A$202,$A23,現地作業!$L$3:$L$202,"予定")) | AC23: =IF($A23="","",COUNTIFS(現地作業!$A$3:$A$202,$A23,現地作業!$L$3:$L$202,"完了")) | AD23: =IF(N($AB23)=0,"",IF(_xlfn.MINIFS(現地作業!$C$3:$C$202,現地作業!$A$3:$A$202,$A23,現地作業!$L$3:$L$202,"予定",現地作業!$C$3:$C$202,">="&TODAY())=0,"",_xlfn.MINIFS(現地作業!$C$3:$C$202,現地作業!$A$3:$A$202,$A23,現地作業!$L$3:$L$202,"予定",現地作業!$C$3:$C$202,">="&TODAY()))) | AF23: =IF($A23="","",SUM(月次工数計画!$G$28:$AD$28)) | AG23: =IF($A23="","",SUMIFS(工数明細!$G$3:$G$302,工数明細!$B$3:$B$302,$A23)) | AH23: =IF($AE23="","",$AE23-N($AG23)) | AI23: =IF(N($AE23)=0,"",$AG23/$AE23) | AJ23: =IF(N($AE23)=0,"",IF($AG23>$AE23,"超過",IF($AG23>=$AE23*0.9,"注意","適正")))
N24: =IF($J24="","",YEAR($J24)-IF(MONTH($J24)<マスタ!$B$4,1,0)) | O24: =IF($J24="","","Q"&(INT(MOD(MONTH($J24)-マスタ!$B$4+12,12)/3)+1)) | P24: =IF($L24="","",IF($M24<>"",$M24-$L24,IF(TODAY()>$L24,TODAY()-$L24,0))) | R24: =IF($Q24="","",$Q24*N($F24)) | T24: =IF($A24="","",SUMIFS(発注・納品!$H$3:$H$202,発注・納品!$B$3:$B$202,$A24)) | U24: =IF($Q24="","",N($S24)+N($T24)) | V24: =IF($Q24="","",$Q24-N($U24)) | W24: =IF(N($Q24)=0,"",$V24/$Q24) | X24: =IF($A24="","",COUNTIFS(発注・納品!$B$3:$B$202,$A24)) | Y24: =IF($A24="","",COUNTIFS(発注・納品!$B$3:$B$202,$A24,発注・納品!$M$3:$M$202,"")) | Z24: =IF(N($X24)=0,"",IF(_xlfn.MAXIFS(発注・納品!$M$3:$M$202,発注・納品!$B$3:$B$202,$A24)=0,"",_xlfn.MAXIFS(発注・納品!$M$3:$M$202,発注・納品!$B$3:$B$202,$A24))) | AA24: =IF($A24="","",IF(N($X24)=0,"機器なし",IF(N($Y24)>0,"入荷待ち",IF(COUNTIFS(発注・納品!$B$3:$B$202,$A24,発注・納品!$N$3:$N$202,"")>0,"受入待ち","受入完了")))) | AB24: =IF($A24="","",COUNTIFS(現地作業!$A$3:$A$202,$A24,現地作業!$L$3:$L$202,"予定")) | AC24: =IF($A24="","",COUNTIFS(現地作業!$A$3:$A$202,$A24,現地作業!$L$3:$L$202,"完了")) | AD24: =IF(N($AB24)=0,"",IF(_xlfn.MINIFS(現地作業!$C$3:$C$202,現地作業!$A$3:$A$202,$A24,現地作業!$L$3:$L$202,"予定",現地作業!$C$3:$C$202,">="&TODAY())=0,"",_xlfn.MINIFS(現地作業!$C$3:$C$202,現地作業!$A$3:$A$202,$A24,現地作業!$L$3:$L$202,"予定",現地作業!$C$3:$C$202,">="&TODAY()))) | AF24: =IF($A24="","",SUM(月次工数計画!$G$29:$AD$29)) | AG24: =IF($A24="","",SUMIFS(工数明細!$G$3:$G$302,工数明細!$B$3:$B$302,$A24)) | AH24: =IF($AE24="","",$AE24-N($AG24)) | AI24: =IF(N($AE24)=0,"",$AG24/$AE24) | AJ24: =IF(N($AE24)=0,"",IF($AG24>$AE24,"超過",IF($AG24>=$AE24*0.9,"注意","適正")))
N25: =IF($J25="","",YEAR($J25)-IF(MONTH($J25)<マスタ!$B$4,1,0)) | O25: =IF($J25="","","Q"&(INT(MOD(MONTH($J25)-マスタ!$B$4+12,12)/3)+1)) | P25: =IF($L25="","",IF($M25<>"",$M25-$L25,IF(TODAY()>$L25,TODAY()-$L25,0))) | R25: =IF($Q25="","",$Q25*N($F25)) | T25: =IF($A25="","",SUMIFS(発注・納品!$H$3:$H$202,発注・納品!$B$3:$B$202,$A25)) | U25: =IF($Q25="","",N($S25)+N($T25)) | V25: =IF($Q25="","",$Q25-N($U25)) | W25: =IF(N($Q25)=0,"",$V25/$Q25) | X25: =IF($A25="","",COUNTIFS(発注・納品!$B$3:$B$202,$A25)) | Y25: =IF($A25="","",COUNTIFS(発注・納品!$B$3:$B$202,$A25,発注・納品!$M$3:$M$202,"")) | Z25: =IF(N($X25)=0,"",IF(_xlfn.MAXIFS(発注・納品!$M$3:$M$202,発注・納品!$B$3:$B$202,$A25)=0,"",_xlfn.MAXIFS(発注・納品!$M$3:$M$202,発注・納品!$B$3:$B$202,$A25))) | AA25: =IF($A25="","",IF(N($X25)=0,"機器なし",IF(N($Y25)>0,"入荷待ち",IF(COUNTIFS(発注・納品!$B$3:$B$202,$A25,発注・納品!$N$3:$N$202,"")>0,"受入待ち","受入完了")))) | AB25: =IF($A25="","",COUNTIFS(現地作業!$A$3:$A$202,$A25,現地作業!$L$3:$L$202,"予定")) | AC25: =IF($A25="","",COUNTIFS(現地作業!$A$3:$A$202,$A25,現地作業!$L$3:$L$202,"完了")) | AD25: =IF(N($AB25)=0,"",IF(_xlfn.MINIFS(現地作業!$C$3:$C$202,現地作業!$A$3:$A$202,$A25,現地作業!$L$3:$L$202,"予定",現地作業!$C$3:$C$202,">="&TODAY())=0,"",_xlfn.MINIFS(現地作業!$C$3:$C$202,現地作業!$A$3:$A$202,$A25,現地作業!$L$3:$L$202,"予定",現地作業!$C$3:$C$202,">="&TODAY()))) | AF25: =IF($A25="","",SUM(月次工数計画!$G$30:$AD$30)) | AG25: =IF($A25="","",SUMIFS(工数明細!$G$3:$G$302,工数明細!$B$3:$B$302,$A25)) | AH25: =IF($AE25="","",$AE25-N($AG25)) | AI25: =IF(N($AE25)=0,"",$AG25/$AE25) | AJ25: =IF(N($AE25)=0,"",IF($AG25>$AE25,"超過",IF($AG25>=$AE25*0.9,"注意","適正")))
N26: =IF($J26="","",YEAR($J26)-IF(MONTH($J26)<マスタ!$B$4,1,0)) | O26: =IF($J26="","","Q"&(INT(MOD(MONTH($J26)-マスタ!$B$4+12,12)/3)+1)) | P26: =IF($L26="","",IF($M26<>"",$M26-$L26,IF(TODAY()>$L26,TODAY()-$L26,0))) | R26: =IF($Q26="","",$Q26*N($F26)) | T26: =IF($A26="","",SUMIFS(発注・納品!$H$3:$H$202,発注・納品!$B$3:$B$202,$A26)) | U26: =IF($Q26="","",N($S26)+N($T26)) | V26: =IF($Q26="","",$Q26-N($U26)) | W26: =IF(N($Q26)=0,"",$V26/$Q26) | X26: =IF($A26="","",COUNTIFS(発注・納品!$B$3:$B$202,$A26)) | Y26: =IF($A26="","",COUNTIFS(発注・納品!$B$3:$B$202,$A26,発注・納品!$M$3:$M$202,"")) | Z26: =IF(N($X26)=0,"",IF(_xlfn.MAXIFS(発注・納品!$M$3:$M$202,発注・納品!$B$3:$B$202,$A26)=0,"",_xlfn.MAXIFS(発注・納品!$M$3:$M$202,発注・納品!$B$3:$B$202,$A26))) | AA26: =IF($A26="","",IF(N($X26)=0,"機器なし",IF(N($Y26)>0,"入荷待ち",IF(COUNTIFS(発注・納品!$B$3:$B$202,$A26,発注・納品!$N$3:$N$202,"")>0,"受入待ち","受入完了")))) | AB26: =IF($A26="","",COUNTIFS(現地作業!$A$3:$A$202,$A26,現地作業!$L$3:$L$202,"予定")) | AC26: =IF($A26="","",COUNTIFS(現地作業!$A$3:$A$202,$A26,現地作業!$L$3:$L$202,"完了")) | AD26: =IF(N($AB26)=0,"",IF(_xlfn.MINIFS(現地作業!$C$3:$C$202,現地作業!$A$3:$A$202,$A26,現地作業!$L$3:$L$202,"予定",現地作業!$C$3:$C$202,">="&TODAY())=0,"",_xlfn.MINIFS(現地作業!$C$3:$C$202,現地作業!$A$3:$A$202,$A26,現地作業!$L$3:$L$202,"予定",現地作業!$C$3:$C$202,">="&TODAY()))) | AF26: =IF($A26="","",SUM(月次工数計画!$G$31:$AD$31)) | AG26: =IF($A26="","",SUMIFS(工数明細!$G$3:$G$302,工数明細!$B$3:$B$302,$A26)) | AH26: =IF($AE26="","",$AE26-N($AG26)) | AI26: =IF(N($AE26)=0,"",$AG26/$AE26) | AJ26: =IF(N($AE26)=0,"",IF($AG26>$AE26,"超過",IF($AG26>=$AE26*0.9,"注意","適正")))
N27: =IF($J27="","",YEAR($J27)-IF(MONTH($J27)<マスタ!$B$4,1,0)) | O27: =IF($J27="","","Q"&(INT(MOD(MONTH($J27)-マスタ!$B$4+12,12)/3)+1)) | P27: =IF($L27="","",IF($M27<>"",$M27-$L27,IF(TODAY()>$L27,TODAY()-$L27,0))) | R27: =IF($Q27="","",$Q27*N($F27)) | T27: =IF($A27="","",SUMIFS(発注・納品!$H$3:$H$202,発注・納品!$B$3:$B$202,$A27)) | U27: =IF($Q27="","",N($S27)+N($T27)) | V27: =IF($Q27="","",$Q27-N($U27)) | W27: =IF(N($Q27)=0,"",$V27/$Q27) | X27: =IF($A27="","",COUNTIFS(発注・納品!$B$3:$B$202,$A27)) | Y27: =IF($A27="","",COUNTIFS(発注・納品!$B$3:$B$202,$A27,発注・納品!$M$3:$M$202,"")) | Z27: =IF(N($X27)=0,"",IF(_xlfn.MAXIFS(発注・納品!$M$3:$M$202,発注・納品!$B$3:$B$202,$A27)=0,"",_xlfn.MAXIFS(発注・納品!$M$3:$M$202,発注・納品!$B$3:$B$202,$A27))) | AA27: =IF($A27="","",IF(N($X27)=0,"機器なし",IF(N($Y27)>0,"入荷待ち",IF(COUNTIFS(発注・納品!$B$3:$B$202,$A27,発注・納品!$N$3:$N$202,"")>0,"受入待ち","受入完了")))) | AB27: =IF($A27="","",COUNTIFS(現地作業!$A$3:$A$202,$A27,現地作業!$L$3:$L$202,"予定")) | AC27: =IF($A27="","",COUNTIFS(現地作業!$A$3:$A$202,$A27,現地作業!$L$3:$L$202,"完了")) | AD27: =IF(N($AB27)=0,"",IF(_xlfn.MINIFS(現地作業!$C$3:$C$202,現地作業!$A$3:$A$202,$A27,現地作業!$L$3:$L$202,"予定",現地作業!$C$3:$C$202,">="&TODAY())=0,"",_xlfn.MINIFS(現地作業!$C$3:$C$202,現地作業!$A$3:$A$202,$A27,現地作業!$L$3:$L$202,"予定",現地作業!$C$3:$C$202,">="&TODAY()))) | AF27: =IF($A27="","",SUM(月次工数計画!$G$32:$AD$32)) | AG27: =IF($A27="","",SUMIFS(工数明細!$G$3:$G$302,工数明細!$B$3:$B$302,$A27)) | AH27: =IF($AE27="","",$AE27-N($AG27)) | AI27: =IF(N($AE27)=0,"",$AG27/$AE27) | AJ27: =IF(N($AE27)=0,"",IF($AG27>$AE27,"超過",IF($AG27>=$AE27*0.9,"注意","適正")))
N28: =IF($J28="","",YEAR($J28)-IF(MONTH($J28)<マスタ!$B$4,1,0)) | O28: =IF($J28="","","Q"&(INT(MOD(MONTH($J28)-マスタ!$B$4+12,12)/3)+1)) | P28: =IF($L28="","",IF($M28<>"",$M28-$L28,IF(TODAY()>$L28,TODAY()-$L28,0))) | R28: =IF($Q28="","",$Q28*N($F28)) | T28: =IF($A28="","",SUMIFS(発注・納品!$H$3:$H$202,発注・納品!$B$3:$B$202,$A28)) | U28: =IF($Q28="","",N($S28)+N($T28)) | V28: =IF($Q28="","",$Q28-N($U28)) | W28: =IF(N($Q28)=0,"",$V28/$Q28) | X28: =IF($A28="","",COUNTIFS(発注・納品!$B$3:$B$202,$A28)) | Y28: =IF($A28="","",COUNTIFS(発注・納品!$B$3:$B$202,$A28,発注・納品!$M$3:$M$202,"")) | Z28: =IF(N($X28)=0,"",IF(_xlfn.MAXIFS(発注・納品!$M$3:$M$202,発注・納品!$B$3:$B$202,$A28)=0,"",_xlfn.MAXIFS(発注・納品!$M$3:$M$202,発注・納品!$B$3:$B$202,$A28))) | AA28: =IF($A28="","",IF(N($X28)=0,"機器なし",IF(N($Y28)>0,"入荷待ち",IF(COUNTIFS(発注・納品!$B$3:$B$202,$A28,発注・納品!$N$3:$N$202,"")>0,"受入待ち","受入完了")))) | AB28: =IF($A28="","",COUNTIFS(現地作業!$A$3:$A$202,$A28,現地作業!$L$3:$L$202,"予定")) | AC28: =IF($A28="","",COUNTIFS(現地作業!$A$3:$A$202,$A28,現地作業!$L$3:$L$202,"完了")) | AD28: =IF(N($AB28)=0,"",IF(_xlfn.MINIFS(現地作業!$C$3:$C$202,現地作業!$A$3:$A$202,$A28,現地作業!$L$3:$L$202,"予定",現地作業!$C$3:$C$202,">="&TODAY())=0,"",_xlfn.MINIFS(現地作業!$C$3:$C$202,現地作業!$A$3:$A$202,$A28,現地作業!$L$3:$L$202,"予定",現地作業!$C$3:$C$202,">="&TODAY()))) | AF28: =IF($A28="","",SUM(月次工数計画!$G$33:$AD$33)) | AG28: =IF($A28="","",SUMIFS(工数明細!$G$3:$G$302,工数明細!$B$3:$B$302,$A28)) | AH28: =IF($AE28="","",$AE28-N($AG28)) | AI28: =IF(N($AE28)=0,"",$AG28/$AE28) | AJ28: =IF(N($AE28)=0,"",IF($AG28>$AE28,"超過",IF($AG28>=$AE28*0.9,"注意","適正")))
N29: =IF($J29="","",YEAR($J29)-IF(MONTH($J29)<マスタ!$B$4,1,0)) | O29: =IF($J29="","","Q"&(INT(MOD(MONTH($J29)-マスタ!$B$4+12,12)/3)+1)) | P29: =IF($L29="","",IF($M29<>"",$M29-$L29,IF(TODAY()>$L29,TODAY()-$L29,0))) | R29: =IF($Q29="","",$Q29*N($F29)) | T29: =IF($A29="","",SUMIFS(発注・納品!$H$3:$H$202,発注・納品!$B$3:$B$202,$A29)) | U29: =IF($Q29="","",N($S29)+N($T29)) | V29: =IF($Q29="","",$Q29-N($U29)) | W29: =IF(N($Q29)=0,"",$V29/$Q29) | X29: =IF($A29="","",COUNTIFS(発注・納品!$B$3:$B$202,$A29)) | Y29: =IF($A29="","",COUNTIFS(発注・納品!$B$3:$B$202,$A29,発注・納品!$M$3:$M$202,"")) | Z29: =IF(N($X29)=0,"",IF(_xlfn.MAXIFS(発注・納品!$M$3:$M$202,発注・納品!$B$3:$B$202,$A29)=0,"",_xlfn.MAXIFS(発注・納品!$M$3:$M$202,発注・納品!$B$3:$B$202,$A29))) | AA29: =IF($A29="","",IF(N($X29)=0,"機器なし",IF(N($Y29)>0,"入荷待ち",IF(COUNTIFS(発注・納品!$B$3:$B$202,$A29,発注・納品!$N$3:$N$202,"")>0,"受入待ち","受入完了")))) | AB29: =IF($A29="","",COUNTIFS(現地作業!$A$3:$A$202,$A29,現地作業!$L$3:$L$202,"予定")) | AC29: =IF($A29="","",COUNTIFS(現地作業!$A$3:$A$202,$A29,現地作業!$L$3:$L$202,"完了")) | AD29: =IF(N($AB29)=0,"",IF(_xlfn.MINIFS(現地作業!$C$3:$C$202,現地作業!$A$3:$A$202,$A29,現地作業!$L$3:$L$202,"予定",現地作業!$C$3:$C$202,">="&TODAY())=0,"",_xlfn.MINIFS(現地作業!$C$3:$C$202,現地作業!$A$3:$A$202,$A29,現地作業!$L$3:$L$202,"予定",現地作業!$C$3:$C$202,">="&TODAY()))) | AF29: =IF($A29="","",SUM(月次工数計画!$G$34:$AD$34)) | AG29: =IF($A29="","",SUMIFS(工数明細!$G$3:$G$302,工数明細!$B$3:$B$302,$A29)) | AH29: =IF($AE29="","",$AE29-N($AG29)) | AI29: =IF(N($AE29)=0,"",$AG29/$AE29) | AJ29: =IF(N($AE29)=0,"",IF($AG29>$AE29,"超過",IF($AG29>=$AE29*0.9,"注意","適正")))
N30: =IF($J30="","",YEAR($J30)-IF(MONTH($J30)<マスタ!$B$4,1,0)) | O30: =IF($J30="","","Q"&(INT(MOD(MONTH($J30)-マスタ!$B$4+12,12)/3)+1)) | P30: =IF($L30="","",IF($M30<>"",$M30-$L30,IF(TODAY()>$L30,TODAY()-$L30,0))) | R30: =IF($Q30="","",$Q30*N($F30)) | T30: =IF($A30="","",SUMIFS(発注・納品!$H$3:$H$202,発注・納品!$B$3:$B$202,$A30)) | U30: =IF($Q30="","",N($S30)+N($T30)) | V30: =IF($Q30="","",$Q30-N($U30)) | W30: =IF(N($Q30)=0,"",$V30/$Q30) | X30: =IF($A30="","",COUNTIFS(発注・納品!$B$3:$B$202,$A30)) | Y30: =IF($A30="","",COUNTIFS(発注・納品!$B$3:$B$202,$A30,発注・納品!$M$3:$M$202,"")) | Z30: =IF(N($X30)=0,"",IF(_xlfn.MAXIFS(発注・納品!$M$3:$M$202,発注・納品!$B$3:$B$202,$A30)=0,"",_xlfn.MAXIFS(発注・納品!$M$3:$M$202,発注・納品!$B$3:$B$202,$A30))) | AA30: =IF($A30="","",IF(N($X30)=0,"機器なし",IF(N($Y30)>0,"入荷待ち",IF(COUNTIFS(発注・納品!$B$3:$B$202,$A30,発注・納品!$N$3:$N$202,"")>0,"受入待ち","受入完了")))) | AB30: =IF($A30="","",COUNTIFS(現地作業!$A$3:$A$202,$A30,現地作業!$L$3:$L$202,"予定")) | AC30: =IF($A30="","",COUNTIFS(現地作業!$A$3:$A$202,$A30,現地作業!$L$3:$L$202,"完了")) | AD30: =IF(N($AB30)=0,"",IF(_xlfn.MINIFS(現地作業!$C$3:$C$202,現地作業!$A$3:$A$202,$A30,現地作業!$L$3:$L$202,"予定",現地作業!$C$3:$C$202,">="&TODAY())=0,"",_xlfn.MINIFS(現地作業!$C$3:$C$202,現地作業!$A$3:$A$202,$A30,現地作業!$L$3:$L$202,"予定",現地作業!$C$3:$C$202,">="&TODAY()))) | AF30: =IF($A30="","",SUM(月次工数計画!$G$35:$AD$35)) | AG30: =IF($A30="","",SUMIFS(工数明細!$G$3:$G$302,工数明細!$B$3:$B$302,$A30)) | AH30: =IF($AE30="","",$AE30-N($AG30)) | AI30: =IF(N($AE30)=0,"",$AG30/$AE30) | AJ30: =IF(N($AE30)=0,"",IF($AG30>$AE30,"超過",IF($AG30>=$AE30*0.9,"注意","適正")))
N31: =IF($J31="","",YEAR($J31)-IF(MONTH($J31)<マスタ!$B$4,1,0)) | O31: =IF($J31="","","Q"&(INT(MOD(MONTH($J31)-マスタ!$B$4+12,12)/3)+1)) | P31: =IF($L31="","",IF($M31<>"",$M31-$L31,IF(TODAY()>$L31,TODAY()-$L31,0))) | R31: =IF($Q31="","",$Q31*N($F31)) | T31: =IF($A31="","",SUMIFS(発注・納品!$H$3:$H$202,発注・納品!$B$3:$B$202,$A31)) | U31: =IF($Q31="","",N($S31)+N($T31)) | V31: =IF($Q31="","",$Q31-N($U31)) | W31: =IF(N($Q31)=0,"",$V31/$Q31) | X31: =IF($A31="","",COUNTIFS(発注・納品!$B$3:$B$202,$A31)) | Y31: =IF($A31="","",COUNTIFS(発注・納品!$B$3:$B$202,$A31,発注・納品!$M$3:$M$202,"")) | Z31: =IF(N($X31)=0,"",IF(_xlfn.MAXIFS(発注・納品!$M$3:$M$202,発注・納品!$B$3:$B$202,$A31)=0,"",_xlfn.MAXIFS(発注・納品!$M$3:$M$202,発注・納品!$B$3:$B$202,$A31))) | AA31: =IF($A31="","",IF(N($X31)=0,"機器なし",IF(N($Y31)>0,"入荷待ち",IF(COUNTIFS(発注・納品!$B$3:$B$202,$A31,発注・納品!$N$3:$N$202,"")>0,"受入待ち","受入完了")))) | AB31: =IF($A31="","",COUNTIFS(現地作業!$A$3:$A$202,$A31,現地作業!$L$3:$L$202,"予定")) | AC31: =IF($A31="","",COUNTIFS(現地作業!$A$3:$A$202,$A31,現地作業!$L$3:$L$202,"完了")) | AD31: =IF(N($AB31)=0,"",IF(_xlfn.MINIFS(現地作業!$C$3:$C$202,現地作業!$A$3:$A$202,$A31,現地作業!$L$3:$L$202,"予定",現地作業!$C$3:$C$202,">="&TODAY())=0,"",_xlfn.MINIFS(現地作業!$C$3:$C$202,現地作業!$A$3:$A$202,$A31,現地作業!$L$3:$L$202,"予定",現地作業!$C$3:$C$202,">="&TODAY()))) | AF31: =IF($A31="","",SUM(月次工数計画!$G$36:$AD$36)) | AG31: =IF($A31="","",SUMIFS(工数明細!$G$3:$G$302,工数明細!$B$3:$B$302,$A31)) | AH31: =IF($AE31="","",$AE31-N($AG31)) | AI31: =IF(N($AE31)=0,"",$AG31/$AE31) | AJ31: =IF(N($AE31)=0,"",IF($AG31>$AE31,"超過",IF($AG31>=$AE31*0.9,"注意","適正")))
N32: =IF($J32="","",YEAR($J32)-IF(MONTH($J32)<マスタ!$B$4,1,0)) | O32: =IF($J32="","","Q"&(INT(MOD(MONTH($J32)-マスタ!$B$4+12,12)/3)+1)) | P32: =IF($L32="","",IF($M32<>"",$M32-$L32,IF(TODAY()>$L32,TODAY()-$L32,0))) | R32: =IF($Q32="","",$Q32*N($F32)) | T32: =IF($A32="","",SUMIFS(発注・納品!$H$3:$H$202,発注・納品!$B$3:$B$202,$A32)) | U32: =IF($Q32="","",N($S32)+N($T32)) | V32: =IF($Q32="","",$Q32-N($U32)) | W32: =IF(N($Q32)=0,"",$V32/$Q32) | X32: =IF($A32="","",COUNTIFS(発注・納品!$B$3:$B$202,$A32)) | Y32: =IF($A32="","",COUNTIFS(発注・納品!$B$3:$B$202,$A32,発注・納品!$M$3:$M$202,"")) | Z32: =IF(N($X32)=0,"",IF(_xlfn.MAXIFS(発注・納品!$M$3:$M$202,発注・納品!$B$3:$B$202,$A32)=0,"",_xlfn.MAXIFS(発注・納品!$M$3:$M$202,発注・納品!$B$3:$B$202,$A32))) | AA32: =IF($A32="","",IF(N($X32)=0,"機器なし",IF(N($Y32)>0,"入荷待ち",IF(COUNTIFS(発注・納品!$B$3:$B$202,$A32,発注・納品!$N$3:$N$202,"")>0,"受入待ち","受入完了")))) | AB32: =IF($A32="","",COUNTIFS(現地作業!$A$3:$A$202,$A32,現地作業!$L$3:$L$202,"予定")) | AC32: =IF($A32="","",COUNTIFS(現地作業!$A$3:$A$202,$A32,現地作業!$L$3:$L$202,"完了")) | AD32: =IF(N($AB32)=0,"",IF(_xlfn.MINIFS(現地作業!$C$3:$C$202,現地作業!$A$3:$A$202,$A32,現地作業!$L$3:$L$202,"予定",現地作業!$C$3:$C$202,">="&TODAY())=0,"",_xlfn.MINIFS(現地作業!$C$3:$C$202,現地作業!$A$3:$A$202,$A32,現地作業!$L$3:$L$202,"予定",現地作業!$C$3:$C$202,">="&TODAY()))) | AF32: =IF($A32="","",SUM(月次工数計画!$G$37:$AD$37)) | AG32: =IF($A32="","",SUMIFS(工数明細!$G$3:$G$302,工数明細!$B$3:$B$302,$A32)) | AH32: =IF($AE32="","",$AE32-N($AG32)) | AI32: =IF(N($AE32)=0,"",$AG32/$AE32) | AJ32: =IF(N($AE32)=0,"",IF($AG32>$AE32,"超過",IF($AG32>=$AE32*0.9,"注意","適正")))
N33: =IF($J33="","",YEAR($J33)-IF(MONTH($J33)<マスタ!$B$4,1,0)) | O33: =IF($J33="","","Q"&(INT(MOD(MONTH($J33)-マスタ!$B$4+12,12)/3)+1)) | P33: =IF($L33="","",IF($M33<>"",$M33-$L33,IF(TODAY()>$L33,TODAY()-$L33,0))) | R33: =IF($Q33="","",$Q33*N($F33)) | T33: =IF($A33="","",SUMIFS(発注・納品!$H$3:$H$202,発注・納品!$B$3:$B$202,$A33)) | U33: =IF($Q33="","",N($S33)+N($T33)) | V33: =IF($Q33="","",$Q33-N($U33)) | W33: =IF(N($Q33)=0,"",$V33/$Q33) | X33: =IF($A33="","",COUNTIFS(発注・納品!$B$3:$B$202,$A33)) | Y33: =IF($A33="","",COUNTIFS(発注・納品!$B$3:$B$202,$A33,発注・納品!$M$3:$M$202,"")) | Z33: =IF(N($X33)=0,"",IF(_xlfn.MAXIFS(発注・納品!$M$3:$M$202,発注・納品!$B$3:$B$202,$A33)=0,"",_xlfn.MAXIFS(発注・納品!$M$3:$M$202,発注・納品!$B$3:$B$202,$A33))) | AA33: =IF($A33="","",IF(N($X33)=0,"機器なし",IF(N($Y33)>0,"入荷待ち",IF(COUNTIFS(発注・納品!$B$3:$B$202,$A33,発注・納品!$N$3:$N$202,"")>0,"受入待ち","受入完了")))) | AB33: =IF($A33="","",COUNTIFS(現地作業!$A$3:$A$202,$A33,現地作業!$L$3:$L$202,"予定")) | AC33: =IF($A33="","",COUNTIFS(現地作業!$A$3:$A$202,$A33,現地作業!$L$3:$L$202,"完了")) | AD33: =IF(N($AB33)=0,"",IF(_xlfn.MINIFS(現地作業!$C$3:$C$202,現地作業!$A$3:$A$202,$A33,現地作業!$L$3:$L$202,"予定",現地作業!$C$3:$C$202,">="&TODAY())=0,"",_xlfn.MINIFS(現地作業!$C$3:$C$202,現地作業!$A$3:$A$202,$A33,現地作業!$L$3:$L$202,"予定",現地作業!$C$3:$C$202,">="&TODAY()))) | AF33: =IF($A33="","",SUM(月次工数計画!$G$38:$AD$38)) | AG33: =IF($A33="","",SUMIFS(工数明細!$G$3:$G$302,工数明細!$B$3:$B$302,$A33)) | AH33: =IF($AE33="","",$AE33-N($AG33)) | AI33: =IF(N($AE33)=0,"",$AG33/$AE33) | AJ33: =IF(N($AE33)=0,"",IF($AG33>$AE33,"超過",IF($AG33>=$AE33*0.9,"注意","適正")))
N34: =IF($J34="","",YEAR($J34)-IF(MONTH($J34)<マスタ!$B$4,1,0)) | O34: =IF($J34="","","Q"&(INT(MOD(MONTH($J34)-マスタ!$B$4+12,12)/3)+1)) | P34: =IF($L34="","",IF($M34<>"",$M34-$L34,IF(TODAY()>$L34,TODAY()-$L34,0))) | R34: =IF($Q34="","",$Q34*N($F34)) | T34: =IF($A34="","",SUMIFS(発注・納品!$H$3:$H$202,発注・納品!$B$3:$B$202,$A34)) | U34: =IF($Q34="","",N($S34)+N($T34)) | V34: =IF($Q34="","",$Q34-N($U34)) | W34: =IF(N($Q34)=0,"",$V34/$Q34) | X34: =IF($A34="","",COUNTIFS(発注・納品!$B$3:$B$202,$A34)) | Y34: =IF($A34="","",COUNTIFS(発注・納品!$B$3:$B$202,$A34,発注・納品!$M$3:$M$202,"")) | Z34: =IF(N($X34)=0,"",IF(_xlfn.MAXIFS(発注・納品!$M$3:$M$202,発注・納品!$B$3:$B$202,$A34)=0,"",_xlfn.MAXIFS(発注・納品!$M$3:$M$202,発注・納品!$B$3:$B$202,$A34))) | AA34: =IF($A34="","",IF(N($X34)=0,"機器なし",IF(N($Y34)>0,"入荷待ち",IF(COUNTIFS(発注・納品!$B$3:$B$202,$A34,発注・納品!$N$3:$N$202,"")>0,"受入待ち","受入完了")))) | AB34: =IF($A34="","",COUNTIFS(現地作業!$A$3:$A$202,$A34,現地作業!$L$3:$L$202,"予定")) | AC34: =IF($A34="","",COUNTIFS(現地作業!$A$3:$A$202,$A34,現地作業!$L$3:$L$202,"完了")) | AD34: =IF(N($AB34)=0,"",IF(_xlfn.MINIFS(現地作業!$C$3:$C$202,現地作業!$A$3:$A$202,$A34,現地作業!$L$3:$L$202,"予定",現地作業!$C$3:$C$202,">="&TODAY())=0,"",_xlfn.MINIFS(現地作業!$C$3:$C$202,現地作業!$A$3:$A$202,$A34,現地作業!$L$3:$L$202,"予定",現地作業!$C$3:$C$202,">="&TODAY()))) | AF34: =IF($A34="","",SUM(月次工数計画!$G$39:$AD$39)) | AG34: =IF($A34="","",SUMIFS(工数明細!$G$3:$G$302,工数明細!$B$3:$B$302,$A34)) | AH34: =IF($AE34="","",$AE34-N($AG34)) | AI34: =IF(N($AE34)=0,"",$AG34/$AE34) | AJ34: =IF(N($AE34)=0,"",IF($AG34>$AE34,"超過",IF($AG34>=$AE34*0.9,"注意","適正")))
N35: =IF($J35="","",YEAR($J35)-IF(MONTH($J35)<マスタ!$B$4,1,0)) | O35: =IF($J35="","","Q"&(INT(MOD(MONTH($J35)-マスタ!$B$4+12,12)/3)+1)) | P35: =IF($L35="","",IF($M35<>"",$M35-$L35,IF(TODAY()>$L35,TODAY()-$L35,0))) | R35: =IF($Q35="","",$Q35*N($F35)) | T35: =IF($A35="","",SUMIFS(発注・納品!$H$3:$H$202,発注・納品!$B$3:$B$202,$A35)) | U35: =IF($Q35="","",N($S35)+N($T35)) | V35: =IF($Q35="","",$Q35-N($U35)) | W35: =IF(N($Q35)=0,"",$V35/$Q35) | X35: =IF($A35="","",COUNTIFS(発注・納品!$B$3:$B$202,$A35)) | Y35: =IF($A35="","",COUNTIFS(発注・納品!$B$3:$B$202,$A35,発注・納品!$M$3:$M$202,"")) | Z35: =IF(N($X35)=0,"",IF(_xlfn.MAXIFS(発注・納品!$M$3:$M$202,発注・納品!$B$3:$B$202,$A35)=0,"",_xlfn.MAXIFS(発注・納品!$M$3:$M$202,発注・納品!$B$3:$B$202,$A35))) | AA35: =IF($A35="","",IF(N($X35)=0,"機器なし",IF(N($Y35)>0,"入荷待ち",IF(COUNTIFS(発注・納品!$B$3:$B$202,$A35,発注・納品!$N$3:$N$202,"")>0,"受入待ち","受入完了")))) | AB35: =IF($A35="","",COUNTIFS(現地作業!$A$3:$A$202,$A35,現地作業!$L$3:$L$202,"予定")) | AC35: =IF($A35="","",COUNTIFS(現地作業!$A$3:$A$202,$A35,現地作業!$L$3:$L$202,"完了")) | AD35: =IF(N($AB35)=0,"",IF(_xlfn.MINIFS(現地作業!$C$3:$C$202,現地作業!$A$3:$A$202,$A35,現地作業!$L$3:$L$202,"予定",現地作業!$C$3:$C$202,">="&TODAY())=0,"",_xlfn.MINIFS(現地作業!$C$3:$C$202,現地作業!$A$3:$A$202,$A35,現地作業!$L$3:$L$202,"予定",現地作業!$C$3:$C$202,">="&TODAY()))) | AF35: =IF($A35="","",SUM(月次工数計画!$G$40:$AD$40)) | AG35: =IF($A35="","",SUMIFS(工数明細!$G$3:$G$302,工数明細!$B$3:$B$302,$A35)) | AH35: =IF($AE35="","",$AE35-N($AG35)) | AI35: =IF(N($AE35)=0,"",$AG35/$AE35) | AJ35: =IF(N($AE35)=0,"",IF($AG35>$AE35,"超過",IF($AG35>=$AE35*0.9,"注意","適正")))
N36: =IF($J36="","",YEAR($J36)-IF(MONTH($J36)<マスタ!$B$4,1,0)) | O36: =IF($J36="","","Q"&(INT(MOD(MONTH($J36)-マスタ!$B$4+12,12)/3)+1)) | P36: =IF($L36="","",IF($M36<>"",$M36-$L36,IF(TODAY()>$L36,TODAY()-$L36,0))) | R36: =IF($Q36="","",$Q36*N($F36)) | T36: =IF($A36="","",SUMIFS(発注・納品!$H$3:$H$202,発注・納品!$B$3:$B$202,$A36)) | U36: =IF($Q36="","",N($S36)+N($T36)) | V36: =IF($Q36="","",$Q36-N($U36)) | W36: =IF(N($Q36)=0,"",$V36/$Q36) | X36: =IF($A36="","",COUNTIFS(発注・納品!$B$3:$B$202,$A36)) | Y36: =IF($A36="","",COUNTIFS(発注・納品!$B$3:$B$202,$A36,発注・納品!$M$3:$M$202,"")) | Z36: =IF(N($X36)=0,"",IF(_xlfn.MAXIFS(発注・納品!$M$3:$M$202,発注・納品!$B$3:$B$202,$A36)=0,"",_xlfn.MAXIFS(発注・納品!$M$3:$M$202,発注・納品!$B$3:$B$202,$A36))) | AA36: =IF($A36="","",IF(N($X36)=0,"機器なし",IF(N($Y36)>0,"入荷待ち",IF(COUNTIFS(発注・納品!$B$3:$B$202,$A36,発注・納品!$N$3:$N$202,"")>0,"受入待ち","受入完了")))) | AB36: =IF($A36="","",COUNTIFS(現地作業!$A$3:$A$202,$A36,現地作業!$L$3:$L$202,"予定")) | AC36: =IF($A36="","",COUNTIFS(現地作業!$A$3:$A$202,$A36,現地作業!$L$3:$L$202,"完了")) | AD36: =IF(N($AB36)=0,"",IF(_xlfn.MINIFS(現地作業!$C$3:$C$202,現地作業!$A$3:$A$202,$A36,現地作業!$L$3:$L$202,"予定",現地作業!$C$3:$C$202,">="&TODAY())=0,"",_xlfn.MINIFS(現地作業!$C$3:$C$202,現地作業!$A$3:$A$202,$A36,現地作業!$L$3:$L$202,"予定",現地作業!$C$3:$C$202,">="&TODAY()))) | AF36: =IF($A36="","",SUM(月次工数計画!$G$41:$AD$41)) | AG36: =IF($A36="","",SUMIFS(工数明細!$G$3:$G$302,工数明細!$B$3:$B$302,$A36)) | AH36: =IF($AE36="","",$AE36-N($AG36)) | AI36: =IF(N($AE36)=0,"",$AG36/$AE36) | AJ36: =IF(N($AE36)=0,"",IF($AG36>$AE36,"超過",IF($AG36>=$AE36*0.9,"注意","適正")))
N37: =IF($J37="","",YEAR($J37)-IF(MONTH($J37)<マスタ!$B$4,1,0)) | O37: =IF($J37="","","Q"&(INT(MOD(MONTH($J37)-マスタ!$B$4+12,12)/3)+1)) | P37: =IF($L37="","",IF($M37<>"",$M37-$L37,IF(TODAY()>$L37,TODAY()-$L37,0))) | R37: =IF($Q37="","",$Q37*N($F37)) | T37: =IF($A37="","",SUMIFS(発注・納品!$H$3:$H$202,発注・納品!$B$3:$B$202,$A37)) | U37: =IF($Q37="","",N($S37)+N($T37)) | V37: =IF($Q37="","",$Q37-N($U37)) | W37: =IF(N($Q37)=0,"",$V37/$Q37) | X37: =IF($A37="","",COUNTIFS(発注・納品!$B$3:$B$202,$A37)) | Y37: =IF($A37="","",COUNTIFS(発注・納品!$B$3:$B$202,$A37,発注・納品!$M$3:$M$202,"")) | Z37: =IF(N($X37)=0,"",IF(_xlfn.MAXIFS(発注・納品!$M$3:$M$202,発注・納品!$B$3:$B$202,$A37)=0,"",_xlfn.MAXIFS(発注・納品!$M$3:$M$202,発注・納品!$B$3:$B$202,$A37))) | AA37: =IF($A37="","",IF(N($X37)=0,"機器なし",IF(N($Y37)>0,"入荷待ち",IF(COUNTIFS(発注・納品!$B$3:$B$202,$A37,発注・納品!$N$3:$N$202,"")>0,"受入待ち","受入完了")))) | AB37: =IF($A37="","",COUNTIFS(現地作業!$A$3:$A$202,$A37,現地作業!$L$3:$L$202,"予定")) | AC37: =IF($A37="","",COUNTIFS(現地作業!$A$3:$A$202,$A37,現地作業!$L$3:$L$202,"完了")) | AD37: =IF(N($AB37)=0,"",IF(_xlfn.MINIFS(現地作業!$C$3:$C$202,現地作業!$A$3:$A$202,$A37,現地作業!$L$3:$L$202,"予定",現地作業!$C$3:$C$202,">="&TODAY())=0,"",_xlfn.MINIFS(現地作業!$C$3:$C$202,現地作業!$A$3:$A$202,$A37,現地作業!$L$3:$L$202,"予定",現地作業!$C$3:$C$202,">="&TODAY()))) | AF37: =IF($A37="","",SUM(月次工数計画!$G$42:$AD$42)) | AG37: =IF($A37="","",SUMIFS(工数明細!$G$3:$G$302,工数明細!$B$3:$B$302,$A37)) | AH37: =IF($AE37="","",$AE37-N($AG37)) | AI37: =IF(N($AE37)=0,"",$AG37/$AE37) | AJ37: =IF(N($AE37)=0,"",IF($AG37>$AE37,"超過",IF($AG37>=$AE37*0.9,"注意","適正")))
N38: =IF($J38="","",YEAR($J38)-IF(MONTH($J38)<マスタ!$B$4,1,0)) | O38: =IF($J38="","","Q"&(INT(MOD(MONTH($J38)-マスタ!$B$4+12,12)/3)+1)) | P38: =IF($L38="","",IF($M38<>"",$M38-$L38,IF(TODAY()>$L38,TODAY()-$L38,0))) | R38: =IF($Q38="","",$Q38*N($F38)) | T38: =IF($A38="","",SUMIFS(発注・納品!$H$3:$H$202,発注・納品!$B$3:$B$202,$A38)) | U38: =IF($Q38="","",N($S38)+N($T38)) | V38: =IF($Q38="","",$Q38-N($U38)) | W38: =IF(N($Q38)=0,"",$V38/$Q38) | X38: =IF($A38="","",COUNTIFS(発注・納品!$B$3:$B$202,$A38)) | Y38: =IF($A38="","",COUNTIFS(発注・納品!$B$3:$B$202,$A38,発注・納品!$M$3:$M$202,"")) | Z38: =IF(N($X38)=0,"",IF(_xlfn.MAXIFS(発注・納品!$M$3:$M$202,発注・納品!$B$3:$B$202,$A38)=0,"",_xlfn.MAXIFS(発注・納品!$M$3:$M$202,発注・納品!$B$3:$B$202,$A38))) | AA38: =IF($A38="","",IF(N($X38)=0,"機器なし",IF(N($Y38)>0,"入荷待ち",IF(COUNTIFS(発注・納品!$B$3:$B$202,$A38,発注・納品!$N$3:$N$202,"")>0,"受入待ち","受入完了")))) | AB38: =IF($A38="","",COUNTIFS(現地作業!$A$3:$A$202,$A38,現地作業!$L$3:$L$202,"予定")) | AC38: =IF($A38="","",COUNTIFS(現地作業!$A$3:$A$202,$A38,現地作業!$L$3:$L$202,"完了")) | AD38: =IF(N($AB38)=0,"",IF(_xlfn.MINIFS(現地作業!$C$3:$C$202,現地作業!$A$3:$A$202,$A38,現地作業!$L$3:$L$202,"予定",現地作業!$C$3:$C$202,">="&TODAY())=0,"",_xlfn.MINIFS(現地作業!$C$3:$C$202,現地作業!$A$3:$A$202,$A38,現地作業!$L$3:$L$202,"予定",現地作業!$C$3:$C$202,">="&TODAY()))) | AF38: =IF($A38="","",SUM(月次工数計画!$G$43:$AD$43)) | AG38: =IF($A38="","",SUMIFS(工数明細!$G$3:$G$302,工数明細!$B$3:$B$302,$A38)) | AH38: =IF($AE38="","",$AE38-N($AG38)) | AI38: =IF(N($AE38)=0,"",$AG38/$AE38) | AJ38: =IF(N($AE38)=0,"",IF($AG38>$AE38,"超過",IF($AG38>=$AE38*0.9,"注意","適正")))
N39: =IF($J39="","",YEAR($J39)-IF(MONTH($J39)<マスタ!$B$4,1,0)) | O39: =IF($J39="","","Q"&(INT(MOD(MONTH($J39)-マスタ!$B$4+12,12)/3)+1)) | P39: =IF($L39="","",IF($M39<>"",$M39-$L39,IF(TODAY()>$L39,TODAY()-$L39,0))) | R39: =IF($Q39="","",$Q39*N($F39)) | T39: =IF($A39="","",SUMIFS(発注・納品!$H$3:$H$202,発注・納品!$B$3:$B$202,$A39)) | U39: =IF($Q39="","",N($S39)+N($T39)) | V39: =IF($Q39="","",$Q39-N($U39)) | W39: =IF(N($Q39)=0,"",$V39/$Q39) | X39: =IF($A39="","",COUNTIFS(発注・納品!$B$3:$B$202,$A39)) | Y39: =IF($A39="","",COUNTIFS(発注・納品!$B$3:$B$202,$A39,発注・納品!$M$3:$M$202,"")) | Z39: =IF(N($X39)=0,"",IF(_xlfn.MAXIFS(発注・納品!$M$3:$M$202,発注・納品!$B$3:$B$202,$A39)=0,"",_xlfn.MAXIFS(発注・納品!$M$3:$M$202,発注・納品!$B$3:$B$202,$A39))) | AA39: =IF($A39="","",IF(N($X39)=0,"機器なし",IF(N($Y39)>0,"入荷待ち",IF(COUNTIFS(発注・納品!$B$3:$B$202,$A39,発注・納品!$N$3:$N$202,"")>0,"受入待ち","受入完了")))) | AB39: =IF($A39="","",COUNTIFS(現地作業!$A$3:$A$202,$A39,現地作業!$L$3:$L$202,"予定")) | AC39: =IF($A39="","",COUNTIFS(現地作業!$A$3:$A$202,$A39,現地作業!$L$3:$L$202,"完了")) | AD39: =IF(N($AB39)=0,"",IF(_xlfn.MINIFS(現地作業!$C$3:$C$202,現地作業!$A$3:$A$202,$A39,現地作業!$L$3:$L$202,"予定",現地作業!$C$3:$C$202,">="&TODAY())=0,"",_xlfn.MINIFS(現地作業!$C$3:$C$202,現地作業!$A$3:$A$202,$A39,現地作業!$L$3:$L$202,"予定",現地作業!$C$3:$C$202,">="&TODAY()))) | AF39: =IF($A39="","",SUM(月次工数計画!$G$44:$AD$44)) | AG39: =IF($A39="","",SUMIFS(工数明細!$G$3:$G$302,工数明細!$B$3:$B$302,$A39)) | AH39: =IF($AE39="","",$AE39-N($AG39)) | AI39: =IF(N($AE39)=0,"",$AG39/$AE39) | AJ39: =IF(N($AE39)=0,"",IF($AG39>$AE39,"超過",IF($AG39>=$AE39*0.9,"注意","適正")))
N40: =IF($J40="","",YEAR($J40)-IF(MONTH($J40)<マスタ!$B$4,1,0)) | O40: =IF($J40="","","Q"&(INT(MOD(MONTH($J40)-マスタ!$B$4+12,12)/3)+1)) | P40: =IF($L40="","",IF($M40<>"",$M40-$L40,IF(TODAY()>$L40,TODAY()-$L40,0))) | R40: =IF($Q40="","",$Q40*N($F40)) | T40: =IF($A40="","",SUMIFS(発注・納品!$H$3:$H$202,発注・納品!$B$3:$B$202,$A40)) | U40: =IF($Q40="","",N($S40)+N($T40)) | V40: =IF($Q40="","",$Q40-N($U40)) | W40: =IF(N($Q40)=0,"",$V40/$Q40) | X40: =IF($A40="","",COUNTIFS(発注・納品!$B$3:$B$202,$A40)) | Y40: =IF($A40="","",COUNTIFS(発注・納品!$B$3:$B$202,$A40,発注・納品!$M$3:$M$202,"")) | Z40: =IF(N($X40)=0,"",IF(_xlfn.MAXIFS(発注・納品!$M$3:$M$202,発注・納品!$B$3:$B$202,$A40)=0,"",_xlfn.MAXIFS(発注・納品!$M$3:$M$202,発注・納品!$B$3:$B$202,$A40))) | AA40: =IF($A40="","",IF(N($X40)=0,"機器なし",IF(N($Y40)>0,"入荷待ち",IF(COUNTIFS(発注・納品!$B$3:$B$202,$A40,発注・納品!$N$3:$N$202,"")>0,"受入待ち","受入完了")))) | AB40: =IF($A40="","",COUNTIFS(現地作業!$A$3:$A$202,$A40,現地作業!$L$3:$L$202,"予定")) | AC40: =IF($A40="","",COUNTIFS(現地作業!$A$3:$A$202,$A40,現地作業!$L$3:$L$202,"完了")) | AD40: =IF(N($AB40)=0,"",IF(_xlfn.MINIFS(現地作業!$C$3:$C$202,現地作業!$A$3:$A$202,$A40,現地作業!$L$3:$L$202,"予定",現地作業!$C$3:$C$202,">="&TODAY())=0,"",_xlfn.MINIFS(現地作業!$C$3:$C$202,現地作業!$A$3:$A$202,$A40,現地作業!$L$3:$L$202,"予定",現地作業!$C$3:$C$202,">="&TODAY()))) | AF40: =IF($A40="","",SUM(月次工数計画!$G$45:$AD$45)) | AG40: =IF($A40="","",SUMIFS(工数明細!$G$3:$G$302,工数明細!$B$3:$B$302,$A40)) | AH40: =IF($AE40="","",$AE40-N($AG40)) | AI40: =IF(N($AE40)=0,"",$AG40/$AE40) | AJ40: =IF(N($AE40)=0,"",IF($AG40>$AE40,"超過",IF($AG40>=$AE40*0.9,"注意","適正")))
N41: =IF($J41="","",YEAR($J41)-IF(MONTH($J41)<マスタ!$B$4,1,0)) | O41: =IF($J41="","","Q"&(INT(MOD(MONTH($J41)-マスタ!$B$4+12,12)/3)+1)) | P41: =IF($L41="","",IF($M41<>"",$M41-$L41,IF(TODAY()>$L41,TODAY()-$L41,0))) | R41: =IF($Q41="","",$Q41*N($F41)) | T41: =IF($A41="","",SUMIFS(発注・納品!$H$3:$H$202,発注・納品!$B$3:$B$202,$A41)) | U41: =IF($Q41="","",N($S41)+N($T41)) | V41: =IF($Q41="","",$Q41-N($U41)) | W41: =IF(N($Q41)=0,"",$V41/$Q41) | X41: =IF($A41="","",COUNTIFS(発注・納品!$B$3:$B$202,$A41)) | Y41: =IF($A41="","",COUNTIFS(発注・納品!$B$3:$B$202,$A41,発注・納品!$M$3:$M$202,"")) | Z41: =IF(N($X41)=0,"",IF(_xlfn.MAXIFS(発注・納品!$M$3:$M$202,発注・納品!$B$3:$B$202,$A41)=0,"",_xlfn.MAXIFS(発注・納品!$M$3:$M$202,発注・納品!$B$3:$B$202,$A41))) | AA41: =IF($A41="","",IF(N($X41)=0,"機器なし",IF(N($Y41)>0,"入荷待ち",IF(COUNTIFS(発注・納品!$B$3:$B$202,$A41,発注・納品!$N$3:$N$202,"")>0,"受入待ち","受入完了")))) | AB41: =IF($A41="","",COUNTIFS(現地作業!$A$3:$A$202,$A41,現地作業!$L$3:$L$202,"予定")) | AC41: =IF($A41="","",COUNTIFS(現地作業!$A$3:$A$202,$A41,現地作業!$L$3:$L$202,"完了")) | AD41: =IF(N($AB41)=0,"",IF(_xlfn.MINIFS(現地作業!$C$3:$C$202,現地作業!$A$3:$A$202,$A41,現地作業!$L$3:$L$202,"予定",現地作業!$C$3:$C$202,">="&TODAY())=0,"",_xlfn.MINIFS(現地作業!$C$3:$C$202,現地作業!$A$3:$A$202,$A41,現地作業!$L$3:$L$202,"予定",現地作業!$C$3:$C$202,">="&TODAY()))) | AF41: =IF($A41="","",SUM(月次工数計画!$G$46:$AD$46)) | AG41: =IF($A41="","",SUMIFS(工数明細!$G$3:$G$302,工数明細!$B$3:$B$302,$A41)) | AH41: =IF($AE41="","",$AE41-N($AG41)) | AI41: =IF(N($AE41)=0,"",$AG41/$AE41) | AJ41: =IF(N($AE41)=0,"",IF($AG41>$AE41,"超過",IF($AG41>=$AE41*0.9,"注意","適正")))
N42: =IF($J42="","",YEAR($J42)-IF(MONTH($J42)<マスタ!$B$4,1,0)) | O42: =IF($J42="","","Q"&(INT(MOD(MONTH($J42)-マスタ!$B$4+12,12)/3)+1)) | P42: =IF($L42="","",IF($M42<>"",$M42-$L42,IF(TODAY()>$L42,TODAY()-$L42,0))) | R42: =IF($Q42="","",$Q42*N($F42)) | T42: =IF($A42="","",SUMIFS(発注・納品!$H$3:$H$202,発注・納品!$B$3:$B$202,$A42)) | U42: =IF($Q42="","",N($S42)+N($T42)) | V42: =IF($Q42="","",$Q42-N($U42)) | W42: =IF(N($Q42)=0,"",$V42/$Q42) | X42: =IF($A42="","",COUNTIFS(発注・納品!$B$3:$B$202,$A42)) | Y42: =IF($A42="","",COUNTIFS(発注・納品!$B$3:$B$202,$A42,発注・納品!$M$3:$M$202,"")) | Z42: =IF(N($X42)=0,"",IF(_xlfn.MAXIFS(発注・納品!$M$3:$M$202,発注・納品!$B$3:$B$202,$A42)=0,"",_xlfn.MAXIFS(発注・納品!$M$3:$M$202,発注・納品!$B$3:$B$202,$A42))) | AA42: =IF($A42="","",IF(N($X42)=0,"機器なし",IF(N($Y42)>0,"入荷待ち",IF(COUNTIFS(発注・納品!$B$3:$B$202,$A42,発注・納品!$N$3:$N$202,"")>0,"受入待ち","受入完了")))) | AB42: =IF($A42="","",COUNTIFS(現地作業!$A$3:$A$202,$A42,現地作業!$L$3:$L$202,"予定")) | AC42: =IF($A42="","",COUNTIFS(現地作業!$A$3:$A$202,$A42,現地作業!$L$3:$L$202,"完了")) | AD42: =IF(N($AB42)=0,"",IF(_xlfn.MINIFS(現地作業!$C$3:$C$202,現地作業!$A$3:$A$202,$A42,現地作業!$L$3:$L$202,"予定",現地作業!$C$3:$C$202,">="&TODAY())=0,"",_xlfn.MINIFS(現地作業!$C$3:$C$202,現地作業!$A$3:$A$202,$A42,現地作業!$L$3:$L$202,"予定",現地作業!$C$3:$C$202,">="&TODAY()))) | AF42: =IF($A42="","",SUM(月次工数計画!$G$47:$AD$47)) | AG42: =IF($A42="","",SUMIFS(工数明細!$G$3:$G$302,工数明細!$B$3:$B$302,$A42)) | AH42: =IF($AE42="","",$AE42-N($AG42)) | AI42: =IF(N($AE42)=0,"",$AG42/$AE42) | AJ42: =IF(N($AE42)=0,"",IF($AG42>$AE42,"超過",IF($AG42>=$AE42*0.9,"注意","適正")))
N43: =IF($J43="","",YEAR($J43)-IF(MONTH($J43)<マスタ!$B$4,1,0)) | O43: =IF($J43="","","Q"&(INT(MOD(MONTH($J43)-マスタ!$B$4+12,12)/3)+1)) | P43: =IF($L43="","",IF($M43<>"",$M43-$L43,IF(TODAY()>$L43,TODAY()-$L43,0))) | R43: =IF($Q43="","",$Q43*N($F43)) | T43: =IF($A43="","",SUMIFS(発注・納品!$H$3:$H$202,発注・納品!$B$3:$B$202,$A43)) | U43: =IF($Q43="","",N($S43)+N($T43)) | V43: =IF($Q43="","",$Q43-N($U43)) | W43: =IF(N($Q43)=0,"",$V43/$Q43) | X43: =IF($A43="","",COUNTIFS(発注・納品!$B$3:$B$202,$A43)) | Y43: =IF($A43="","",COUNTIFS(発注・納品!$B$3:$B$202,$A43,発注・納品!$M$3:$M$202,"")) | Z43: =IF(N($X43)=0,"",IF(_xlfn.MAXIFS(発注・納品!$M$3:$M$202,発注・納品!$B$3:$B$202,$A43)=0,"",_xlfn.MAXIFS(発注・納品!$M$3:$M$202,発注・納品!$B$3:$B$202,$A43))) | AA43: =IF($A43="","",IF(N($X43)=0,"機器なし",IF(N($Y43)>0,"入荷待ち",IF(COUNTIFS(発注・納品!$B$3:$B$202,$A43,発注・納品!$N$3:$N$202,"")>0,"受入待ち","受入完了")))) | AB43: =IF($A43="","",COUNTIFS(現地作業!$A$3:$A$202,$A43,現地作業!$L$3:$L$202,"予定")) | AC43: =IF($A43="","",COUNTIFS(現地作業!$A$3:$A$202,$A43,現地作業!$L$3:$L$202,"完了")) | AD43: =IF(N($AB43)=0,"",IF(_xlfn.MINIFS(現地作業!$C$3:$C$202,現地作業!$A$3:$A$202,$A43,現地作業!$L$3:$L$202,"予定",現地作業!$C$3:$C$202,">="&TODAY())=0,"",_xlfn.MINIFS(現地作業!$C$3:$C$202,現地作業!$A$3:$A$202,$A43,現地作業!$L$3:$L$202,"予定",現地作業!$C$3:$C$202,">="&TODAY()))) | AF43: =IF($A43="","",SUM(月次工数計画!$G$48:$AD$48)) | AG43: =IF($A43="","",SUMIFS(工数明細!$G$3:$G$302,工数明細!$B$3:$B$302,$A43)) | AH43: =IF($AE43="","",$AE43-N($AG43)) | AI43: =IF(N($AE43)=0,"",$AG43/$AE43) | AJ43: =IF(N($AE43)=0,"",IF($AG43>$AE43,"超過",IF($AG43>=$AE43*0.9,"注意","適正")))
N44: =IF($J44="","",YEAR($J44)-IF(MONTH($J44)<マスタ!$B$4,1,0)) | O44: =IF($J44="","","Q"&(INT(MOD(MONTH($J44)-マスタ!$B$4+12,12)/3)+1)) | P44: =IF($L44="","",IF($M44<>"",$M44-$L44,IF(TODAY()>$L44,TODAY()-$L44,0))) | R44: =IF($Q44="","",$Q44*N($F44)) | T44: =IF($A44="","",SUMIFS(発注・納品!$H$3:$H$202,発注・納品!$B$3:$B$202,$A44)) | U44: =IF($Q44="","",N($S44)+N($T44)) | V44: =IF($Q44="","",$Q44-N($U44)) | W44: =IF(N($Q44)=0,"",$V44/$Q44) | X44: =IF($A44="","",COUNTIFS(発注・納品!$B$3:$B$202,$A44)) | Y44: =IF($A44="","",COUNTIFS(発注・納品!$B$3:$B$202,$A44,発注・納品!$M$3:$M$202,"")) | Z44: =IF(N($X44)=0,"",IF(_xlfn.MAXIFS(発注・納品!$M$3:$M$202,発注・納品!$B$3:$B$202,$A44)=0,"",_xlfn.MAXIFS(発注・納品!$M$3:$M$202,発注・納品!$B$3:$B$202,$A44))) | AA44: =IF($A44="","",IF(N($X44)=0,"機器なし",IF(N($Y44)>0,"入荷待ち",IF(COUNTIFS(発注・納品!$B$3:$B$202,$A44,発注・納品!$N$3:$N$202,"")>0,"受入待ち","受入完了")))) | AB44: =IF($A44="","",COUNTIFS(現地作業!$A$3:$A$202,$A44,現地作業!$L$3:$L$202,"予定")) | AC44: =IF($A44="","",COUNTIFS(現地作業!$A$3:$A$202,$A44,現地作業!$L$3:$L$202,"完了")) | AD44: =IF(N($AB44)=0,"",IF(_xlfn.MINIFS(現地作業!$C$3:$C$202,現地作業!$A$3:$A$202,$A44,現地作業!$L$3:$L$202,"予定",現地作業!$C$3:$C$202,">="&TODAY())=0,"",_xlfn.MINIFS(現地作業!$C$3:$C$202,現地作業!$A$3:$A$202,$A44,現地作業!$L$3:$L$202,"予定",現地作業!$C$3:$C$202,">="&TODAY()))) | AF44: =IF($A44="","",SUM(月次工数計画!$G$49:$AD$49)) | AG44: =IF($A44="","",SUMIFS(工数明細!$G$3:$G$302,工数明細!$B$3:$B$302,$A44)) | AH44: =IF($AE44="","",$AE44-N($AG44)) | AI44: =IF(N($AE44)=0,"",$AG44/$AE44) | AJ44: =IF(N($AE44)=0,"",IF($AG44>$AE44,"超過",IF($AG44>=$AE44*0.9,"注意","適正")))
N45: =IF($J45="","",YEAR($J45)-IF(MONTH($J45)<マスタ!$B$4,1,0)) | O45: =IF($J45="","","Q"&(INT(MOD(MONTH($J45)-マスタ!$B$4+12,12)/3)+1)) | P45: =IF($L45="","",IF($M45<>"",$M45-$L45,IF(TODAY()>$L45,TODAY()-$L45,0))) | R45: =IF($Q45="","",$Q45*N($F45)) | T45: =IF($A45="","",SUMIFS(発注・納品!$H$3:$H$202,発注・納品!$B$3:$B$202,$A45)) | U45: =IF($Q45="","",N($S45)+N($T45)) | V45: =IF($Q45="","",$Q45-N($U45)) | W45: =IF(N($Q45)=0,"",$V45/$Q45) | X45: =IF($A45="","",COUNTIFS(発注・納品!$B$3:$B$202,$A45)) | Y45: =IF($A45="","",COUNTIFS(発注・納品!$B$3:$B$202,$A45,発注・納品!$M$3:$M$202,"")) | Z45: =IF(N($X45)=0,"",IF(_xlfn.MAXIFS(発注・納品!$M$3:$M$202,発注・納品!$B$3:$B$202,$A45)=0,"",_xlfn.MAXIFS(発注・納品!$M$3:$M$202,発注・納品!$B$3:$B$202,$A45))) | AA45: =IF($A45="","",IF(N($X45)=0,"機器なし",IF(N($Y45)>0,"入荷待ち",IF(COUNTIFS(発注・納品!$B$3:$B$202,$A45,発注・納品!$N$3:$N$202,"")>0,"受入待ち","受入完了")))) | AB45: =IF($A45="","",COUNTIFS(現地作業!$A$3:$A$202,$A45,現地作業!$L$3:$L$202,"予定")) | AC45: =IF($A45="","",COUNTIFS(現地作業!$A$3:$A$202,$A45,現地作業!$L$3:$L$202,"完了")) | AD45: =IF(N($AB45)=0,"",IF(_xlfn.MINIFS(現地作業!$C$3:$C$202,現地作業!$A$3:$A$202,$A45,現地作業!$L$3:$L$202,"予定",現地作業!$C$3:$C$202,">="&TODAY())=0,"",_xlfn.MINIFS(現地作業!$C$3:$C$202,現地作業!$A$3:$A$202,$A45,現地作業!$L$3:$L$202,"予定",現地作業!$C$3:$C$202,">="&TODAY()))) | AF45: =IF($A45="","",SUM(月次工数計画!$G$50:$AD$50)) | AG45: =IF($A45="","",SUMIFS(工数明細!$G$3:$G$302,工数明細!$B$3:$B$302,$A45)) | AH45: =IF($AE45="","",$AE45-N($AG45)) | AI45: =IF(N($AE45)=0,"",$AG45/$AE45) | AJ45: =IF(N($AE45)=0,"",IF($AG45>$AE45,"超過",IF($AG45>=$AE45*0.9,"注意","適正")))
N46: =IF($J46="","",YEAR($J46)-IF(MONTH($J46)<マスタ!$B$4,1,0)) | O46: =IF($J46="","","Q"&(INT(MOD(MONTH($J46)-マスタ!$B$4+12,12)/3)+1)) | P46: =IF($L46="","",IF($M46<>"",$M46-$L46,IF(TODAY()>$L46,TODAY()-$L46,0))) | R46: =IF($Q46="","",$Q46*N($F46)) | T46: =IF($A46="","",SUMIFS(発注・納品!$H$3:$H$202,発注・納品!$B$3:$B$202,$A46)) | U46: =IF($Q46="","",N($S46)+N($T46)) | V46: =IF($Q46="","",$Q46-N($U46)) | W46: =IF(N($Q46)=0,"",$V46/$Q46) | X46: =IF($A46="","",COUNTIFS(発注・納品!$B$3:$B$202,$A46)) | Y46: =IF($A46="","",COUNTIFS(発注・納品!$B$3:$B$202,$A46,発注・納品!$M$3:$M$202,"")) | Z46: =IF(N($X46)=0,"",IF(_xlfn.MAXIFS(発注・納品!$M$3:$M$202,発注・納品!$B$3:$B$202,$A46)=0,"",_xlfn.MAXIFS(発注・納品!$M$3:$M$202,発注・納品!$B$3:$B$202,$A46))) | AA46: =IF($A46="","",IF(N($X46)=0,"機器なし",IF(N($Y46)>0,"入荷待ち",IF(COUNTIFS(発注・納品!$B$3:$B$202,$A46,発注・納品!$N$3:$N$202,"")>0,"受入待ち","受入完了")))) | AB46: =IF($A46="","",COUNTIFS(現地作業!$A$3:$A$202,$A46,現地作業!$L$3:$L$202,"予定")) | AC46: =IF($A46="","",COUNTIFS(現地作業!$A$3:$A$202,$A46,現地作業!$L$3:$L$202,"完了")) | AD46: =IF(N($AB46)=0,"",IF(_xlfn.MINIFS(現地作業!$C$3:$C$202,現地作業!$A$3:$A$202,$A46,現地作業!$L$3:$L$202,"予定",現地作業!$C$3:$C$202,">="&TODAY())=0,"",_xlfn.MINIFS(現地作業!$C$3:$C$202,現地作業!$A$3:$A$202,$A46,現地作業!$L$3:$L$202,"予定",現地作業!$C$3:$C$202,">="&TODAY()))) | AF46: =IF($A46="","",SUM(月次工数計画!$G$51:$AD$51)) | AG46: =IF($A46="","",SUMIFS(工数明細!$G$3:$G$302,工数明細!$B$3:$B$302,$A46)) | AH46: =IF($AE46="","",$AE46-N($AG46)) | AI46: =IF(N($AE46)=0,"",$AG46/$AE46) | AJ46: =IF(N($AE46)=0,"",IF($AG46>$AE46,"超過",IF($AG46>=$AE46*0.9,"注意","適正")))
N47: =IF($J47="","",YEAR($J47)-IF(MONTH($J47)<マスタ!$B$4,1,0)) | O47: =IF($J47="","","Q"&(INT(MOD(MONTH($J47)-マスタ!$B$4+12,12)/3)+1)) | P47: =IF($L47="","",IF($M47<>"",$M47-$L47,IF(TODAY()>$L47,TODAY()-$L47,0))) | R47: =IF($Q47="","",$Q47*N($F47)) | T47: =IF($A47="","",SUMIFS(発注・納品!$H$3:$H$202,発注・納品!$B$3:$B$202,$A47)) | U47: =IF($Q47="","",N($S47)+N($T47)) | V47: =IF($Q47="","",$Q47-N($U47)) | W47: =IF(N($Q47)=0,"",$V47/$Q47) | X47: =IF($A47="","",COUNTIFS(発注・納品!$B$3:$B$202,$A47)) | Y47: =IF($A47="","",COUNTIFS(発注・納品!$B$3:$B$202,$A47,発注・納品!$M$3:$M$202,"")) | Z47: =IF(N($X47)=0,"",IF(_xlfn.MAXIFS(発注・納品!$M$3:$M$202,発注・納品!$B$3:$B$202,$A47)=0,"",_xlfn.MAXIFS(発注・納品!$M$3:$M$202,発注・納品!$B$3:$B$202,$A47))) | AA47: =IF($A47="","",IF(N($X47)=0,"機器なし",IF(N($Y47)>0,"入荷待ち",IF(COUNTIFS(発注・納品!$B$3:$B$202,$A47,発注・納品!$N$3:$N$202,"")>0,"受入待ち","受入完了")))) | AB47: =IF($A47="","",COUNTIFS(現地作業!$A$3:$A$202,$A47,現地作業!$L$3:$L$202,"予定")) | AC47: =IF($A47="","",COUNTIFS(現地作業!$A$3:$A$202,$A47,現地作業!$L$3:$L$202,"完了")) | AD47: =IF(N($AB47)=0,"",IF(_xlfn.MINIFS(現地作業!$C$3:$C$202,現地作業!$A$3:$A$202,$A47,現地作業!$L$3:$L$202,"予定",現地作業!$C$3:$C$202,">="&TODAY())=0,"",_xlfn.MINIFS(現地作業!$C$3:$C$202,現地作業!$A$3:$A$202,$A47,現地作業!$L$3:$L$202,"予定",現地作業!$C$3:$C$202,">="&TODAY()))) | AF47: =IF($A47="","",SUM(月次工数計画!$G$52:$AD$52)) | AG47: =IF($A47="","",SUMIFS(工数明細!$G$3:$G$302,工数明細!$B$3:$B$302,$A47)) | AH47: =IF($AE47="","",$AE47-N($AG47)) | AI47: =IF(N($AE47)=0,"",$AG47/$AE47) | AJ47: =IF(N($AE47)=0,"",IF($AG47>$AE47,"超過",IF($AG47>=$AE47*0.9,"注意","適正")))
N48: =IF($J48="","",YEAR($J48)-IF(MONTH($J48)<マスタ!$B$4,1,0)) | O48: =IF($J48="","","Q"&(INT(MOD(MONTH($J48)-マスタ!$B$4+12,12)/3)+1)) | P48: =IF($L48="","",IF($M48<>"",$M48-$L48,IF(TODAY()>$L48,TODAY()-$L48,0))) | R48: =IF($Q48="","",$Q48*N($F48)) | T48: =IF($A48="","",SUMIFS(発注・納品!$H$3:$H$202,発注・納品!$B$3:$B$202,$A48)) | U48: =IF($Q48="","",N($S48)+N($T48)) | V48: =IF($Q48="","",$Q48-N($U48)) | W48: =IF(N($Q48)=0,"",$V48/$Q48) | X48: =IF($A48="","",COUNTIFS(発注・納品!$B$3:$B$202,$A48)) | Y48: =IF($A48="","",COUNTIFS(発注・納品!$B$3:$B$202,$A48,発注・納品!$M$3:$M$202,"")) | Z48: =IF(N($X48)=0,"",IF(_xlfn.MAXIFS(発注・納品!$M$3:$M$202,発注・納品!$B$3:$B$202,$A48)=0,"",_xlfn.MAXIFS(発注・納品!$M$3:$M$202,発注・納品!$B$3:$B$202,$A48))) | AA48: =IF($A48="","",IF(N($X48)=0,"機器なし",IF(N($Y48)>0,"入荷待ち",IF(COUNTIFS(発注・納品!$B$3:$B$202,$A48,発注・納品!$N$3:$N$202,"")>0,"受入待ち","受入完了")))) | AB48: =IF($A48="","",COUNTIFS(現地作業!$A$3:$A$202,$A48,現地作業!$L$3:$L$202,"予定")) | AC48: =IF($A48="","",COUNTIFS(現地作業!$A$3:$A$202,$A48,現地作業!$L$3:$L$202,"完了")) | AD48: =IF(N($AB48)=0,"",IF(_xlfn.MINIFS(現地作業!$C$3:$C$202,現地作業!$A$3:$A$202,$A48,現地作業!$L$3:$L$202,"予定",現地作業!$C$3:$C$202,">="&TODAY())=0,"",_xlfn.MINIFS(現地作業!$C$3:$C$202,現地作業!$A$3:$A$202,$A48,現地作業!$L$3:$L$202,"予定",現地作業!$C$3:$C$202,">="&TODAY()))) | AF48: =IF($A48="","",SUM(月次工数計画!$G$53:$AD$53)) | AG48: =IF($A48="","",SUMIFS(工数明細!$G$3:$G$302,工数明細!$B$3:$B$302,$A48)) | AH48: =IF($AE48="","",$AE48-N($AG48)) | AI48: =IF(N($AE48)=0,"",$AG48/$AE48) | AJ48: =IF(N($AE48)=0,"",IF($AG48>$AE48,"超過",IF($AG48>=$AE48*0.9,"注意","適正")))
N49: =IF($J49="","",YEAR($J49)-IF(MONTH($J49)<マスタ!$B$4,1,0)) | O49: =IF($J49="","","Q"&(INT(MOD(MONTH($J49)-マスタ!$B$4+12,12)/3)+1)) | P49: =IF($L49="","",IF($M49<>"",$M49-$L49,IF(TODAY()>$L49,TODAY()-$L49,0))) | R49: =IF($Q49="","",$Q49*N($F49)) | T49: =IF($A49="","",SUMIFS(発注・納品!$H$3:$H$202,発注・納品!$B$3:$B$202,$A49)) | U49: =IF($Q49="","",N($S49)+N($T49)) | V49: =IF($Q49="","",$Q49-N($U49)) | W49: =IF(N($Q49)=0,"",$V49/$Q49) | X49: =IF($A49="","",COUNTIFS(発注・納品!$B$3:$B$202,$A49)) | Y49: =IF($A49="","",COUNTIFS(発注・納品!$B$3:$B$202,$A49,発注・納品!$M$3:$M$202,"")) | Z49: =IF(N($X49)=0,"",IF(_xlfn.MAXIFS(発注・納品!$M$3:$M$202,発注・納品!$B$3:$B$202,$A49)=0,"",_xlfn.MAXIFS(発注・納品!$M$3:$M$202,発注・納品!$B$3:$B$202,$A49))) | AA49: =IF($A49="","",IF(N($X49)=0,"機器なし",IF(N($Y49)>0,"入荷待ち",IF(COUNTIFS(発注・納品!$B$3:$B$202,$A49,発注・納品!$N$3:$N$202,"")>0,"受入待ち","受入完了")))) | AB49: =IF($A49="","",COUNTIFS(現地作業!$A$3:$A$202,$A49,現地作業!$L$3:$L$202,"予定")) | AC49: =IF($A49="","",COUNTIFS(現地作業!$A$3:$A$202,$A49,現地作業!$L$3:$L$202,"完了")) | AD49: =IF(N($AB49)=0,"",IF(_xlfn.MINIFS(現地作業!$C$3:$C$202,現地作業!$A$3:$A$202,$A49,現地作業!$L$3:$L$202,"予定",現地作業!$C$3:$C$202,">="&TODAY())=0,"",_xlfn.MINIFS(現地作業!$C$3:$C$202,現地作業!$A$3:$A$202,$A49,現地作業!$L$3:$L$202,"予定",現地作業!$C$3:$C$202,">="&TODAY()))) | AF49: =IF($A49="","",SUM(月次工数計画!$G$54:$AD$54)) | AG49: =IF($A49="","",SUMIFS(工数明細!$G$3:$G$302,工数明細!$B$3:$B$302,$A49)) | AH49: =IF($AE49="","",$AE49-N($AG49)) | AI49: =IF(N($AE49)=0,"",$AG49/$AE49) | AJ49: =IF(N($AE49)=0,"",IF($AG49>$AE49,"超過",IF($AG49>=$AE49*0.9,"注意","適正")))
N50: =IF($J50="","",YEAR($J50)-IF(MONTH($J50)<マスタ!$B$4,1,0)) | O50: =IF($J50="","","Q"&(INT(MOD(MONTH($J50)-マスタ!$B$4+12,12)/3)+1)) | P50: =IF($L50="","",IF($M50<>"",$M50-$L50,IF(TODAY()>$L50,TODAY()-$L50,0))) | R50: =IF($Q50="","",$Q50*N($F50)) | T50: =IF($A50="","",SUMIFS(発注・納品!$H$3:$H$202,発注・納品!$B$3:$B$202,$A50)) | U50: =IF($Q50="","",N($S50)+N($T50)) | V50: =IF($Q50="","",$Q50-N($U50)) | W50: =IF(N($Q50)=0,"",$V50/$Q50) | X50: =IF($A50="","",COUNTIFS(発注・納品!$B$3:$B$202,$A50)) | Y50: =IF($A50="","",COUNTIFS(発注・納品!$B$3:$B$202,$A50,発注・納品!$M$3:$M$202,"")) | Z50: =IF(N($X50)=0,"",IF(_xlfn.MAXIFS(発注・納品!$M$3:$M$202,発注・納品!$B$3:$B$202,$A50)=0,"",_xlfn.MAXIFS(発注・納品!$M$3:$M$202,発注・納品!$B$3:$B$202,$A50))) | AA50: =IF($A50="","",IF(N($X50)=0,"機器なし",IF(N($Y50)>0,"入荷待ち",IF(COUNTIFS(発注・納品!$B$3:$B$202,$A50,発注・納品!$N$3:$N$202,"")>0,"受入待ち","受入完了")))) | AB50: =IF($A50="","",COUNTIFS(現地作業!$A$3:$A$202,$A50,現地作業!$L$3:$L$202,"予定")) | AC50: =IF($A50="","",COUNTIFS(現地作業!$A$3:$A$202,$A50,現地作業!$L$3:$L$202,"完了")) | AD50: =IF(N($AB50)=0,"",IF(_xlfn.MINIFS(現地作業!$C$3:$C$202,現地作業!$A$3:$A$202,$A50,現地作業!$L$3:$L$202,"予定",現地作業!$C$3:$C$202,">="&TODAY())=0,"",_xlfn.MINIFS(現地作業!$C$3:$C$202,現地作業!$A$3:$A$202,$A50,現地作業!$L$3:$L$202,"予定",現地作業!$C$3:$C$202,">="&TODAY()))) | AF50: =IF($A50="","",SUM(月次工数計画!$G$55:$AD$55)) | AG50: =IF($A50="","",SUMIFS(工数明細!$G$3:$G$302,工数明細!$B$3:$B$302,$A50)) | AH50: =IF($AE50="","",$AE50-N($AG50)) | AI50: =IF(N($AE50)=0,"",$AG50/$AE50) | AJ50: =IF(N($AE50)=0,"",IF($AG50>$AE50,"超過",IF($AG50>=$AE50*0.9,"注意","適正")))
N51: =IF($J51="","",YEAR($J51)-IF(MONTH($J51)<マスタ!$B$4,1,0)) | O51: =IF($J51="","","Q"&(INT(MOD(MONTH($J51)-マスタ!$B$4+12,12)/3)+1)) | P51: =IF($L51="","",IF($M51<>"",$M51-$L51,IF(TODAY()>$L51,TODAY()-$L51,0))) | R51: =IF($Q51="","",$Q51*N($F51)) | T51: =IF($A51="","",SUMIFS(発注・納品!$H$3:$H$202,発注・納品!$B$3:$B$202,$A51)) | U51: =IF($Q51="","",N($S51)+N($T51)) | V51: =IF($Q51="","",$Q51-N($U51)) | W51: =IF(N($Q51)=0,"",$V51/$Q51) | X51: =IF($A51="","",COUNTIFS(発注・納品!$B$3:$B$202,$A51)) | Y51: =IF($A51="","",COUNTIFS(発注・納品!$B$3:$B$202,$A51,発注・納品!$M$3:$M$202,"")) | Z51: =IF(N($X51)=0,"",IF(_xlfn.MAXIFS(発注・納品!$M$3:$M$202,発注・納品!$B$3:$B$202,$A51)=0,"",_xlfn.MAXIFS(発注・納品!$M$3:$M$202,発注・納品!$B$3:$B$202,$A51))) | AA51: =IF($A51="","",IF(N($X51)=0,"機器なし",IF(N($Y51)>0,"入荷待ち",IF(COUNTIFS(発注・納品!$B$3:$B$202,$A51,発注・納品!$N$3:$N$202,"")>0,"受入待ち","受入完了")))) | AB51: =IF($A51="","",COUNTIFS(現地作業!$A$3:$A$202,$A51,現地作業!$L$3:$L$202,"予定")) | AC51: =IF($A51="","",COUNTIFS(現地作業!$A$3:$A$202,$A51,現地作業!$L$3:$L$202,"完了")) | AD51: =IF(N($AB51)=0,"",IF(_xlfn.MINIFS(現地作業!$C$3:$C$202,現地作業!$A$3:$A$202,$A51,現地作業!$L$3:$L$202,"予定",現地作業!$C$3:$C$202,">="&TODAY())=0,"",_xlfn.MINIFS(現地作業!$C$3:$C$202,現地作業!$A$3:$A$202,$A51,現地作業!$L$3:$L$202,"予定",現地作業!$C$3:$C$202,">="&TODAY()))) | AF51: =IF($A51="","",SUM(月次工数計画!$G$56:$AD$56)) | AG51: =IF($A51="","",SUMIFS(工数明細!$G$3:$G$302,工数明細!$B$3:$B$302,$A51)) | AH51: =IF($AE51="","",$AE51-N($AG51)) | AI51: =IF(N($AE51)=0,"",$AG51/$AE51) | AJ51: =IF(N($AE51)=0,"",IF($AG51>$AE51,"超過",IF($AG51>=$AE51*0.9,"注意","適正")))
N52: =IF($J52="","",YEAR($J52)-IF(MONTH($J52)<マスタ!$B$4,1,0)) | O52: =IF($J52="","","Q"&(INT(MOD(MONTH($J52)-マスタ!$B$4+12,12)/3)+1)) | P52: =IF($L52="","",IF($M52<>"",$M52-$L52,IF(TODAY()>$L52,TODAY()-$L52,0))) | R52: =IF($Q52="","",$Q52*N($F52)) | T52: =IF($A52="","",SUMIFS(発注・納品!$H$3:$H$202,発注・納品!$B$3:$B$202,$A52)) | U52: =IF($Q52="","",N($S52)+N($T52)) | V52: =IF($Q52="","",$Q52-N($U52)) | W52: =IF(N($Q52)=0,"",$V52/$Q52) | X52: =IF($A52="","",COUNTIFS(発注・納品!$B$3:$B$202,$A52)) | Y52: =IF($A52="","",COUNTIFS(発注・納品!$B$3:$B$202,$A52,発注・納品!$M$3:$M$202,"")) | Z52: =IF(N($X52)=0,"",IF(_xlfn.MAXIFS(発注・納品!$M$3:$M$202,発注・納品!$B$3:$B$202,$A52)=0,"",_xlfn.MAXIFS(発注・納品!$M$3:$M$202,発注・納品!$B$3:$B$202,$A52))) | AA52: =IF($A52="","",IF(N($X52)=0,"機器なし",IF(N($Y52)>0,"入荷待ち",IF(COUNTIFS(発注・納品!$B$3:$B$202,$A52,発注・納品!$N$3:$N$202,"")>0,"受入待ち","受入完了")))) | AB52: =IF($A52="","",COUNTIFS(現地作業!$A$3:$A$202,$A52,現地作業!$L$3:$L$202,"予定")) | AC52: =IF($A52="","",COUNTIFS(現地作業!$A$3:$A$202,$A52,現地作業!$L$3:$L$202,"完了")) | AD52: =IF(N($AB52)=0,"",IF(_xlfn.MINIFS(現地作業!$C$3:$C$202,現地作業!$A$3:$A$202,$A52,現地作業!$L$3:$L$202,"予定",現地作業!$C$3:$C$202,">="&TODAY())=0,"",_xlfn.MINIFS(現地作業!$C$3:$C$202,現地作業!$A$3:$A$202,$A52,現地作業!$L$3:$L$202,"予定",現地作業!$C$3:$C$202,">="&TODAY()))) | AF52: =IF($A52="","",SUM(月次工数計画!$G$57:$AD$57)) | AG52: =IF($A52="","",SUMIFS(工数明細!$G$3:$G$302,工数明細!$B$3:$B$302,$A52)) | AH52: =IF($AE52="","",$AE52-N($AG52)) | AI52: =IF(N($AE52)=0,"",$AG52/$AE52) | AJ52: =IF(N($AE52)=0,"",IF($AG52>$AE52,"超過",IF($AG52>=$AE52*0.9,"注意","適正")))
N53: =IF($J53="","",YEAR($J53)-IF(MONTH($J53)<マスタ!$B$4,1,0)) | O53: =IF($J53="","","Q"&(INT(MOD(MONTH($J53)-マスタ!$B$4+12,12)/3)+1)) | P53: =IF($L53="","",IF($M53<>"",$M53-$L53,IF(TODAY()>$L53,TODAY()-$L53,0))) | R53: =IF($Q53="","",$Q53*N($F53)) | T53: =IF($A53="","",SUMIFS(発注・納品!$H$3:$H$202,発注・納品!$B$3:$B$202,$A53)) | U53: =IF($Q53="","",N($S53)+N($T53)) | V53: =IF($Q53="","",$Q53-N($U53)) | W53: =IF(N($Q53)=0,"",$V53/$Q53) | X53: =IF($A53="","",COUNTIFS(発注・納品!$B$3:$B$202,$A53)) | Y53: =IF($A53="","",COUNTIFS(発注・納品!$B$3:$B$202,$A53,発注・納品!$M$3:$M$202,"")) | Z53: =IF(N($X53)=0,"",IF(_xlfn.MAXIFS(発注・納品!$M$3:$M$202,発注・納品!$B$3:$B$202,$A53)=0,"",_xlfn.MAXIFS(発注・納品!$M$3:$M$202,発注・納品!$B$3:$B$202,$A53))) | AA53: =IF($A53="","",IF(N($X53)=0,"機器なし",IF(N($Y53)>0,"入荷待ち",IF(COUNTIFS(発注・納品!$B$3:$B$202,$A53,発注・納品!$N$3:$N$202,"")>0,"受入待ち","受入完了")))) | AB53: =IF($A53="","",COUNTIFS(現地作業!$A$3:$A$202,$A53,現地作業!$L$3:$L$202,"予定")) | AC53: =IF($A53="","",COUNTIFS(現地作業!$A$3:$A$202,$A53,現地作業!$L$3:$L$202,"完了")) | AD53: =IF(N($AB53)=0,"",IF(_xlfn.MINIFS(現地作業!$C$3:$C$202,現地作業!$A$3:$A$202,$A53,現地作業!$L$3:$L$202,"予定",現地作業!$C$3:$C$202,">="&TODAY())=0,"",_xlfn.MINIFS(現地作業!$C$3:$C$202,現地作業!$A$3:$A$202,$A53,現地作業!$L$3:$L$202,"予定",現地作業!$C$3:$C$202,">="&TODAY()))) | AF53: =IF($A53="","",SUM(月次工数計画!$G$58:$AD$58)) | AG53: =IF($A53="","",SUMIFS(工数明細!$G$3:$G$302,工数明細!$B$3:$B$302,$A53)) | AH53: =IF($AE53="","",$AE53-N($AG53)) | AI53: =IF(N($AE53)=0,"",$AG53/$AE53) | AJ53: =IF(N($AE53)=0,"",IF($AG53>$AE53,"超過",IF($AG53>=$AE53*0.9,"注意","適正")))
N54: =IF($J54="","",YEAR($J54)-IF(MONTH($J54)<マスタ!$B$4,1,0)) | O54: =IF($J54="","","Q"&(INT(MOD(MONTH($J54)-マスタ!$B$4+12,12)/3)+1)) | P54: =IF($L54="","",IF($M54<>"",$M54-$L54,IF(TODAY()>$L54,TODAY()-$L54,0))) | R54: =IF($Q54="","",$Q54*N($F54)) | T54: =IF($A54="","",SUMIFS(発注・納品!$H$3:$H$202,発注・納品!$B$3:$B$202,$A54)) | U54: =IF($Q54="","",N($S54)+N($T54)) | V54: =IF($Q54="","",$Q54-N($U54)) | W54: =IF(N($Q54)=0,"",$V54/$Q54) | X54: =IF($A54="","",COUNTIFS(発注・納品!$B$3:$B$202,$A54)) | Y54: =IF($A54="","",COUNTIFS(発注・納品!$B$3:$B$202,$A54,発注・納品!$M$3:$M$202,"")) | Z54: =IF(N($X54)=0,"",IF(_xlfn.MAXIFS(発注・納品!$M$3:$M$202,発注・納品!$B$3:$B$202,$A54)=0,"",_xlfn.MAXIFS(発注・納品!$M$3:$M$202,発注・納品!$B$3:$B$202,$A54))) | AA54: =IF($A54="","",IF(N($X54)=0,"機器なし",IF(N($Y54)>0,"入荷待ち",IF(COUNTIFS(発注・納品!$B$3:$B$202,$A54,発注・納品!$N$3:$N$202,"")>0,"受入待ち","受入完了")))) | AB54: =IF($A54="","",COUNTIFS(現地作業!$A$3:$A$202,$A54,現地作業!$L$3:$L$202,"予定")) | AC54: =IF($A54="","",COUNTIFS(現地作業!$A$3:$A$202,$A54,現地作業!$L$3:$L$202,"完了")) | AD54: =IF(N($AB54)=0,"",IF(_xlfn.MINIFS(現地作業!$C$3:$C$202,現地作業!$A$3:$A$202,$A54,現地作業!$L$3:$L$202,"予定",現地作業!$C$3:$C$202,">="&TODAY())=0,"",_xlfn.MINIFS(現地作業!$C$3:$C$202,現地作業!$A$3:$A$202,$A54,現地作業!$L$3:$L$202,"予定",現地作業!$C$3:$C$202,">="&TODAY()))) | AF54: =IF($A54="","",SUM(月次工数計画!$G$59:$AD$59)) | AG54: =IF($A54="","",SUMIFS(工数明細!$G$3:$G$302,工数明細!$B$3:$B$302,$A54)) | AH54: =IF($AE54="","",$AE54-N($AG54)) | AI54: =IF(N($AE54)=0,"",$AG54/$AE54) | AJ54: =IF(N($AE54)=0,"",IF($AG54>$AE54,"超過",IF($AG54>=$AE54*0.9,"注意","適正")))
N55: =IF($J55="","",YEAR($J55)-IF(MONTH($J55)<マスタ!$B$4,1,0)) | O55: =IF($J55="","","Q"&(INT(MOD(MONTH($J55)-マスタ!$B$4+12,12)/3)+1)) | P55: =IF($L55="","",IF($M55<>"",$M55-$L55,IF(TODAY()>$L55,TODAY()-$L55,0))) | R55: =IF($Q55="","",$Q55*N($F55)) | T55: =IF($A55="","",SUMIFS(発注・納品!$H$3:$H$202,発注・納品!$B$3:$B$202,$A55)) | U55: =IF($Q55="","",N($S55)+N($T55)) | V55: =IF($Q55="","",$Q55-N($U55)) | W55: =IF(N($Q55)=0,"",$V55/$Q55) | X55: =IF($A55="","",COUNTIFS(発注・納品!$B$3:$B$202,$A55)) | Y55: =IF($A55="","",COUNTIFS(発注・納品!$B$3:$B$202,$A55,発注・納品!$M$3:$M$202,"")) | Z55: =IF(N($X55)=0,"",IF(_xlfn.MAXIFS(発注・納品!$M$3:$M$202,発注・納品!$B$3:$B$202,$A55)=0,"",_xlfn.MAXIFS(発注・納品!$M$3:$M$202,発注・納品!$B$3:$B$202,$A55))) | AA55: =IF($A55="","",IF(N($X55)=0,"機器なし",IF(N($Y55)>0,"入荷待ち",IF(COUNTIFS(発注・納品!$B$3:$B$202,$A55,発注・納品!$N$3:$N$202,"")>0,"受入待ち","受入完了")))) | AB55: =IF($A55="","",COUNTIFS(現地作業!$A$3:$A$202,$A55,現地作業!$L$3:$L$202,"予定")) | AC55: =IF($A55="","",COUNTIFS(現地作業!$A$3:$A$202,$A55,現地作業!$L$3:$L$202,"完了")) | AD55: =IF(N($AB55)=0,"",IF(_xlfn.MINIFS(現地作業!$C$3:$C$202,現地作業!$A$3:$A$202,$A55,現地作業!$L$3:$L$202,"予定",現地作業!$C$3:$C$202,">="&TODAY())=0,"",_xlfn.MINIFS(現地作業!$C$3:$C$202,現地作業!$A$3:$A$202,$A55,現地作業!$L$3:$L$202,"予定",現地作業!$C$3:$C$202,">="&TODAY()))) | AF55: =IF($A55="","",SUM(月次工数計画!$G$60:$AD$60)) | AG55: =IF($A55="","",SUMIFS(工数明細!$G$3:$G$302,工数明細!$B$3:$B$302,$A55)) | AH55: =IF($AE55="","",$AE55-N($AG55)) | AI55: =IF(N($AE55)=0,"",$AG55/$AE55) | AJ55: =IF(N($AE55)=0,"",IF($AG55>$AE55,"超過",IF($AG55>=$AE55*0.9,"注意","適正")))
N56: =IF($J56="","",YEAR($J56)-IF(MONTH($J56)<マスタ!$B$4,1,0)) | O56: =IF($J56="","","Q"&(INT(MOD(MONTH($J56)-マスタ!$B$4+12,12)/3)+1)) | P56: =IF($L56="","",IF($M56<>"",$M56-$L56,IF(TODAY()>$L56,TODAY()-$L56,0))) | R56: =IF($Q56="","",$Q56*N($F56)) | T56: =IF($A56="","",SUMIFS(発注・納品!$H$3:$H$202,発注・納品!$B$3:$B$202,$A56)) | U56: =IF($Q56="","",N($S56)+N($T56)) | V56: =IF($Q56="","",$Q56-N($U56)) | W56: =IF(N($Q56)=0,"",$V56/$Q56) | X56: =IF($A56="","",COUNTIFS(発注・納品!$B$3:$B$202,$A56)) | Y56: =IF($A56="","",COUNTIFS(発注・納品!$B$3:$B$202,$A56,発注・納品!$M$3:$M$202,"")) | Z56: =IF(N($X56)=0,"",IF(_xlfn.MAXIFS(発注・納品!$M$3:$M$202,発注・納品!$B$3:$B$202,$A56)=0,"",_xlfn.MAXIFS(発注・納品!$M$3:$M$202,発注・納品!$B$3:$B$202,$A56))) | AA56: =IF($A56="","",IF(N($X56)=0,"機器なし",IF(N($Y56)>0,"入荷待ち",IF(COUNTIFS(発注・納品!$B$3:$B$202,$A56,発注・納品!$N$3:$N$202,"")>0,"受入待ち","受入完了")))) | AB56: =IF($A56="","",COUNTIFS(現地作業!$A$3:$A$202,$A56,現地作業!$L$3:$L$202,"予定")) | AC56: =IF($A56="","",COUNTIFS(現地作業!$A$3:$A$202,$A56,現地作業!$L$3:$L$202,"完了")) | AD56: =IF(N($AB56)=0,"",IF(_xlfn.MINIFS(現地作業!$C$3:$C$202,現地作業!$A$3:$A$202,$A56,現地作業!$L$3:$L$202,"予定",現地作業!$C$3:$C$202,">="&TODAY())=0,"",_xlfn.MINIFS(現地作業!$C$3:$C$202,現地作業!$A$3:$A$202,$A56,現地作業!$L$3:$L$202,"予定",現地作業!$C$3:$C$202,">="&TODAY()))) | AF56: =IF($A56="","",SUM(月次工数計画!$G$61:$AD$61)) | AG56: =IF($A56="","",SUMIFS(工数明細!$G$3:$G$302,工数明細!$B$3:$B$302,$A56)) | AH56: =IF($AE56="","",$AE56-N($AG56)) | AI56: =IF(N($AE56)=0,"",$AG56/$AE56) | AJ56: =IF(N($AE56)=0,"",IF($AG56>$AE56,"超過",IF($AG56>=$AE56*0.9,"注意","適正")))
N57: =IF($J57="","",YEAR($J57)-IF(MONTH($J57)<マスタ!$B$4,1,0)) | O57: =IF($J57="","","Q"&(INT(MOD(MONTH($J57)-マスタ!$B$4+12,12)/3)+1)) | P57: =IF($L57="","",IF($M57<>"",$M57-$L57,IF(TODAY()>$L57,TODAY()-$L57,0))) | R57: =IF($Q57="","",$Q57*N($F57)) | T57: =IF($A57="","",SUMIFS(発注・納品!$H$3:$H$202,発注・納品!$B$3:$B$202,$A57)) | U57: =IF($Q57="","",N($S57)+N($T57)) | V57: =IF($Q57="","",$Q57-N($U57)) | W57: =IF(N($Q57)=0,"",$V57/$Q57) | X57: =IF($A57="","",COUNTIFS(発注・納品!$B$3:$B$202,$A57)) | Y57: =IF($A57="","",COUNTIFS(発注・納品!$B$3:$B$202,$A57,発注・納品!$M$3:$M$202,"")) | Z57: =IF(N($X57)=0,"",IF(_xlfn.MAXIFS(発注・納品!$M$3:$M$202,発注・納品!$B$3:$B$202,$A57)=0,"",_xlfn.MAXIFS(発注・納品!$M$3:$M$202,発注・納品!$B$3:$B$202,$A57))) | AA57: =IF($A57="","",IF(N($X57)=0,"機器なし",IF(N($Y57)>0,"入荷待ち",IF(COUNTIFS(発注・納品!$B$3:$B$202,$A57,発注・納品!$N$3:$N$202,"")>0,"受入待ち","受入完了")))) | AB57: =IF($A57="","",COUNTIFS(現地作業!$A$3:$A$202,$A57,現地作業!$L$3:$L$202,"予定")) | AC57: =IF($A57="","",COUNTIFS(現地作業!$A$3:$A$202,$A57,現地作業!$L$3:$L$202,"完了")) | AD57: =IF(N($AB57)=0,"",IF(_xlfn.MINIFS(現地作業!$C$3:$C$202,現地作業!$A$3:$A$202,$A57,現地作業!$L$3:$L$202,"予定",現地作業!$C$3:$C$202,">="&TODAY())=0,"",_xlfn.MINIFS(現地作業!$C$3:$C$202,現地作業!$A$3:$A$202,$A57,現地作業!$L$3:$L$202,"予定",現地作業!$C$3:$C$202,">="&TODAY()))) | AF57: =IF($A57="","",SUM(月次工数計画!$G$62:$AD$62)) | AG57: =IF($A57="","",SUMIFS(工数明細!$G$3:$G$302,工数明細!$B$3:$B$302,$A57)) | AH57: =IF($AE57="","",$AE57-N($AG57)) | AI57: =IF(N($AE57)=0,"",$AG57/$AE57) | AJ57: =IF(N($AE57)=0,"",IF($AG57>$AE57,"超過",IF($AG57>=$AE57*0.9,"注意","適正")))
N58: =IF($J58="","",YEAR($J58)-IF(MONTH($J58)<マスタ!$B$4,1,0)) | O58: =IF($J58="","","Q"&(INT(MOD(MONTH($J58)-マスタ!$B$4+12,12)/3)+1)) | P58: =IF($L58="","",IF($M58<>"",$M58-$L58,IF(TODAY()>$L58,TODAY()-$L58,0))) | R58: =IF($Q58="","",$Q58*N($F58)) | T58: =IF($A58="","",SUMIFS(発注・納品!$H$3:$H$202,発注・納品!$B$3:$B$202,$A58)) | U58: =IF($Q58="","",N($S58)+N($T58)) | V58: =IF($Q58="","",$Q58-N($U58)) | W58: =IF(N($Q58)=0,"",$V58/$Q58) | X58: =IF($A58="","",COUNTIFS(発注・納品!$B$3:$B$202,$A58)) | Y58: =IF($A58="","",COUNTIFS(発注・納品!$B$3:$B$202,$A58,発注・納品!$M$3:$M$202,"")) | Z58: =IF(N($X58)=0,"",IF(_xlfn.MAXIFS(発注・納品!$M$3:$M$202,発注・納品!$B$3:$B$202,$A58)=0,"",_xlfn.MAXIFS(発注・納品!$M$3:$M$202,発注・納品!$B$3:$B$202,$A58))) | AA58: =IF($A58="","",IF(N($X58)=0,"機器なし",IF(N($Y58)>0,"入荷待ち",IF(COUNTIFS(発注・納品!$B$3:$B$202,$A58,発注・納品!$N$3:$N$202,"")>0,"受入待ち","受入完了")))) | AB58: =IF($A58="","",COUNTIFS(現地作業!$A$3:$A$202,$A58,現地作業!$L$3:$L$202,"予定")) | AC58: =IF($A58="","",COUNTIFS(現地作業!$A$3:$A$202,$A58,現地作業!$L$3:$L$202,"完了")) | AD58: =IF(N($AB58)=0,"",IF(_xlfn.MINIFS(現地作業!$C$3:$C$202,現地作業!$A$3:$A$202,$A58,現地作業!$L$3:$L$202,"予定",現地作業!$C$3:$C$202,">="&TODAY())=0,"",_xlfn.MINIFS(現地作業!$C$3:$C$202,現地作業!$A$3:$A$202,$A58,現地作業!$L$3:$L$202,"予定",現地作業!$C$3:$C$202,">="&TODAY()))) | AF58: =IF($A58="","",SUM(月次工数計画!$G$63:$AD$63)) | AG58: =IF($A58="","",SUMIFS(工数明細!$G$3:$G$302,工数明細!$B$3:$B$302,$A58)) | AH58: =IF($AE58="","",$AE58-N($AG58)) | AI58: =IF(N($AE58)=0,"",$AG58/$AE58) | AJ58: =IF(N($AE58)=0,"",IF($AG58>$AE58,"超過",IF($AG58>=$AE58*0.9,"注意","適正")))
N59: =IF($J59="","",YEAR($J59)-IF(MONTH($J59)<マスタ!$B$4,1,0)) | O59: =IF($J59="","","Q"&(INT(MOD(MONTH($J59)-マスタ!$B$4+12,12)/3)+1)) | P59: =IF($L59="","",IF($M59<>"",$M59-$L59,IF(TODAY()>$L59,TODAY()-$L59,0))) | R59: =IF($Q59="","",$Q59*N($F59)) | T59: =IF($A59="","",SUMIFS(発注・納品!$H$3:$H$202,発注・納品!$B$3:$B$202,$A59)) | U59: =IF($Q59="","",N($S59)+N($T59)) | V59: =IF($Q59="","",$Q59-N($U59)) | W59: =IF(N($Q59)=0,"",$V59/$Q59) | X59: =IF($A59="","",COUNTIFS(発注・納品!$B$3:$B$202,$A59)) | Y59: =IF($A59="","",COUNTIFS(発注・納品!$B$3:$B$202,$A59,発注・納品!$M$3:$M$202,"")) | Z59: =IF(N($X59)=0,"",IF(_xlfn.MAXIFS(発注・納品!$M$3:$M$202,発注・納品!$B$3:$B$202,$A59)=0,"",_xlfn.MAXIFS(発注・納品!$M$3:$M$202,発注・納品!$B$3:$B$202,$A59))) | AA59: =IF($A59="","",IF(N($X59)=0,"機器なし",IF(N($Y59)>0,"入荷待ち",IF(COUNTIFS(発注・納品!$B$3:$B$202,$A59,発注・納品!$N$3:$N$202,"")>0,"受入待ち","受入完了")))) | AB59: =IF($A59="","",COUNTIFS(現地作業!$A$3:$A$202,$A59,現地作業!$L$3:$L$202,"予定")) | AC59: =IF($A59="","",COUNTIFS(現地作業!$A$3:$A$202,$A59,現地作業!$L$3:$L$202,"完了")) | AD59: =IF(N($AB59)=0,"",IF(_xlfn.MINIFS(現地作業!$C$3:$C$202,現地作業!$A$3:$A$202,$A59,現地作業!$L$3:$L$202,"予定",現地作業!$C$3:$C$202,">="&TODAY())=0,"",_xlfn.MINIFS(現地作業!$C$3:$C$202,現地作業!$A$3:$A$202,$A59,現地作業!$L$3:$L$202,"予定",現地作業!$C$3:$C$202,">="&TODAY()))) | AF59: =IF($A59="","",SUM(月次工数計画!$G$64:$AD$64)) | AG59: =IF($A59="","",SUMIFS(工数明細!$G$3:$G$302,工数明細!$B$3:$B$302,$A59)) | AH59: =IF($AE59="","",$AE59-N($AG59)) | AI59: =IF(N($AE59)=0,"",$AG59/$AE59) | AJ59: =IF(N($AE59)=0,"",IF($AG59>$AE59,"超過",IF($AG59>=$AE59*0.9,"注意","適正")))
N60: =IF($J60="","",YEAR($J60)-IF(MONTH($J60)<マスタ!$B$4,1,0)) | O60: =IF($J60="","","Q"&(INT(MOD(MONTH($J60)-マスタ!$B$4+12,12)/3)+1)) | P60: =IF($L60="","",IF($M60<>"",$M60-$L60,IF(TODAY()>$L60,TODAY()-$L60,0))) | R60: =IF($Q60="","",$Q60*N($F60)) | T60: =IF($A60="","",SUMIFS(発注・納品!$H$3:$H$202,発注・納品!$B$3:$B$202,$A60)) | U60: =IF($Q60="","",N($S60)+N($T60)) | V60: =IF($Q60="","",$Q60-N($U60)) | W60: =IF(N($Q60)=0,"",$V60/$Q60) | X60: =IF($A60="","",COUNTIFS(発注・納品!$B$3:$B$202,$A60)) | Y60: =IF($A60="","",COUNTIFS(発注・納品!$B$3:$B$202,$A60,発注・納品!$M$3:$M$202,"")) | Z60: =IF(N($X60)=0,"",IF(_xlfn.MAXIFS(発注・納品!$M$3:$M$202,発注・納品!$B$3:$B$202,$A60)=0,"",_xlfn.MAXIFS(発注・納品!$M$3:$M$202,発注・納品!$B$3:$B$202,$A60))) | AA60: =IF($A60="","",IF(N($X60)=0,"機器なし",IF(N($Y60)>0,"入荷待ち",IF(COUNTIFS(発注・納品!$B$3:$B$202,$A60,発注・納品!$N$3:$N$202,"")>0,"受入待ち","受入完了")))) | AB60: =IF($A60="","",COUNTIFS(現地作業!$A$3:$A$202,$A60,現地作業!$L$3:$L$202,"予定")) | AC60: =IF($A60="","",COUNTIFS(現地作業!$A$3:$A$202,$A60,現地作業!$L$3:$L$202,"完了")) | AD60: =IF(N($AB60)=0,"",IF(_xlfn.MINIFS(現地作業!$C$3:$C$202,現地作業!$A$3:$A$202,$A60,現地作業!$L$3:$L$202,"予定",現地作業!$C$3:$C$202,">="&TODAY())=0,"",_xlfn.MINIFS(現地作業!$C$3:$C$202,現地作業!$A$3:$A$202,$A60,現地作業!$L$3:$L$202,"予定",現地作業!$C$3:$C$202,">="&TODAY()))) | AF60: =IF($A60="","",SUM(月次工数計画!$G$65:$AD$65)) | AG60: =IF($A60="","",SUMIFS(工数明細!$G$3:$G$302,工数明細!$B$3:$B$302,$A60)) | AH60: =IF($AE60="","",$AE60-N($AG60)) | AI60: =IF(N($AE60)=0,"",$AG60/$AE60) | AJ60: =IF(N($AE60)=0,"",IF($AG60>$AE60,"超過",IF($AG60>=$AE60*0.9,"注意","適正")))
N61: =IF($J61="","",YEAR($J61)-IF(MONTH($J61)<マスタ!$B$4,1,0)) | O61: =IF($J61="","","Q"&(INT(MOD(MONTH($J61)-マスタ!$B$4+12,12)/3)+1)) | P61: =IF($L61="","",IF($M61<>"",$M61-$L61,IF(TODAY()>$L61,TODAY()-$L61,0))) | R61: =IF($Q61="","",$Q61*N($F61)) | T61: =IF($A61="","",SUMIFS(発注・納品!$H$3:$H$202,発注・納品!$B$3:$B$202,$A61)) | U61: =IF($Q61="","",N($S61)+N($T61)) | V61: =IF($Q61="","",$Q61-N($U61)) | W61: =IF(N($Q61)=0,"",$V61/$Q61) | X61: =IF($A61="","",COUNTIFS(発注・納品!$B$3:$B$202,$A61)) | Y61: =IF($A61="","",COUNTIFS(発注・納品!$B$3:$B$202,$A61,発注・納品!$M$3:$M$202,"")) | Z61: =IF(N($X61)=0,"",IF(_xlfn.MAXIFS(発注・納品!$M$3:$M$202,発注・納品!$B$3:$B$202,$A61)=0,"",_xlfn.MAXIFS(発注・納品!$M$3:$M$202,発注・納品!$B$3:$B$202,$A61))) | AA61: =IF($A61="","",IF(N($X61)=0,"機器なし",IF(N($Y61)>0,"入荷待ち",IF(COUNTIFS(発注・納品!$B$3:$B$202,$A61,発注・納品!$N$3:$N$202,"")>0,"受入待ち","受入完了")))) | AB61: =IF($A61="","",COUNTIFS(現地作業!$A$3:$A$202,$A61,現地作業!$L$3:$L$202,"予定")) | AC61: =IF($A61="","",COUNTIFS(現地作業!$A$3:$A$202,$A61,現地作業!$L$3:$L$202,"完了")) | AD61: =IF(N($AB61)=0,"",IF(_xlfn.MINIFS(現地作業!$C$3:$C$202,現地作業!$A$3:$A$202,$A61,現地作業!$L$3:$L$202,"予定",現地作業!$C$3:$C$202,">="&TODAY())=0,"",_xlfn.MINIFS(現地作業!$C$3:$C$202,現地作業!$A$3:$A$202,$A61,現地作業!$L$3:$L$202,"予定",現地作業!$C$3:$C$202,">="&TODAY()))) | AF61: =IF($A61="","",SUM(月次工数計画!$G$66:$AD$66)) | AG61: =IF($A61="","",SUMIFS(工数明細!$G$3:$G$302,工数明細!$B$3:$B$302,$A61)) | AH61: =IF($AE61="","",$AE61-N($AG61)) | AI61: =IF(N($AE61)=0,"",$AG61/$AE61) | AJ61: =IF(N($AE61)=0,"",IF($AG61>$AE61,"超過",IF($AG61>=$AE61*0.9,"注意","適正")))
N62: =IF($J62="","",YEAR($J62)-IF(MONTH($J62)<マスタ!$B$4,1,0)) | O62: =IF($J62="","","Q"&(INT(MOD(MONTH($J62)-マスタ!$B$4+12,12)/3)+1)) | P62: =IF($L62="","",IF($M62<>"",$M62-$L62,IF(TODAY()>$L62,TODAY()-$L62,0))) | R62: =IF($Q62="","",$Q62*N($F62)) | T62: =IF($A62="","",SUMIFS(発注・納品!$H$3:$H$202,発注・納品!$B$3:$B$202,$A62)) | U62: =IF($Q62="","",N($S62)+N($T62)) | V62: =IF($Q62="","",$Q62-N($U62)) | W62: =IF(N($Q62)=0,"",$V62/$Q62) | X62: =IF($A62="","",COUNTIFS(発注・納品!$B$3:$B$202,$A62)) | Y62: =IF($A62="","",COUNTIFS(発注・納品!$B$3:$B$202,$A62,発注・納品!$M$3:$M$202,"")) | Z62: =IF(N($X62)=0,"",IF(_xlfn.MAXIFS(発注・納品!$M$3:$M$202,発注・納品!$B$3:$B$202,$A62)=0,"",_xlfn.MAXIFS(発注・納品!$M$3:$M$202,発注・納品!$B$3:$B$202,$A62))) | AA62: =IF($A62="","",IF(N($X62)=0,"機器なし",IF(N($Y62)>0,"入荷待ち",IF(COUNTIFS(発注・納品!$B$3:$B$202,$A62,発注・納品!$N$3:$N$202,"")>0,"受入待ち","受入完了")))) | AB62: =IF($A62="","",COUNTIFS(現地作業!$A$3:$A$202,$A62,現地作業!$L$3:$L$202,"予定")) | AC62: =IF($A62="","",COUNTIFS(現地作業!$A$3:$A$202,$A62,現地作業!$L$3:$L$202,"完了")) | AD62: =IF(N($AB62)=0,"",IF(_xlfn.MINIFS(現地作業!$C$3:$C$202,現地作業!$A$3:$A$202,$A62,現地作業!$L$3:$L$202,"予定",現地作業!$C$3:$C$202,">="&TODAY())=0,"",_xlfn.MINIFS(現地作業!$C$3:$C$202,現地作業!$A$3:$A$202,$A62,現地作業!$L$3:$L$202,"予定",現地作業!$C$3:$C$202,">="&TODAY()))) | AF62: =IF($A62="","",SUM(月次工数計画!$G$67:$AD$67)) | AG62: =IF($A62="","",SUMIFS(工数明細!$G$3:$G$302,工数明細!$B$3:$B$302,$A62)) | AH62: =IF($AE62="","",$AE62-N($AG62)) | AI62: =IF(N($AE62)=0,"",$AG62/$AE62) | AJ62: =IF(N($AE62)=0,"",IF($AG62>$AE62,"超過",IF($AG62>=$AE62*0.9,"注意","適正")))
N63: =IF($J63="","",YEAR($J63)-IF(MONTH($J63)<マスタ!$B$4,1,0)) | O63: =IF($J63="","","Q"&(INT(MOD(MONTH($J63)-マスタ!$B$4+12,12)/3)+1)) | P63: =IF($L63="","",IF($M63<>"",$M63-$L63,IF(TODAY()>$L63,TODAY()-$L63,0))) | R63: =IF($Q63="","",$Q63*N($F63)) | T63: =IF($A63="","",SUMIFS(発注・納品!$H$3:$H$202,発注・納品!$B$3:$B$202,$A63)) | U63: =IF($Q63="","",N($S63)+N($T63)) | V63: =IF($Q63="","",$Q63-N($U63)) | W63: =IF(N($Q63)=0,"",$V63/$Q63) | X63: =IF($A63="","",COUNTIFS(発注・納品!$B$3:$B$202,$A63)) | Y63: =IF($A63="","",COUNTIFS(発注・納品!$B$3:$B$202,$A63,発注・納品!$M$3:$M$202,"")) | Z63: =IF(N($X63)=0,"",IF(_xlfn.MAXIFS(発注・納品!$M$3:$M$202,発注・納品!$B$3:$B$202,$A63)=0,"",_xlfn.MAXIFS(発注・納品!$M$3:$M$202,発注・納品!$B$3:$B$202,$A63))) | AA63: =IF($A63="","",IF(N($X63)=0,"機器なし",IF(N($Y63)>0,"入荷待ち",IF(COUNTIFS(発注・納品!$B$3:$B$202,$A63,発注・納品!$N$3:$N$202,"")>0,"受入待ち","受入完了")))) | AB63: =IF($A63="","",COUNTIFS(現地作業!$A$3:$A$202,$A63,現地作業!$L$3:$L$202,"予定")) | AC63: =IF($A63="","",COUNTIFS(現地作業!$A$3:$A$202,$A63,現地作業!$L$3:$L$202,"完了")) | AD63: =IF(N($AB63)=0,"",IF(_xlfn.MINIFS(現地作業!$C$3:$C$202,現地作業!$A$3:$A$202,$A63,現地作業!$L$3:$L$202,"予定",現地作業!$C$3:$C$202,">="&TODAY())=0,"",_xlfn.MINIFS(現地作業!$C$3:$C$202,現地作業!$A$3:$A$202,$A63,現地作業!$L$3:$L$202,"予定",現地作業!$C$3:$C$202,">="&TODAY()))) | AF63: =IF($A63="","",SUM(月次工数計画!$G$68:$AD$68)) | AG63: =IF($A63="","",SUMIFS(工数明細!$G$3:$G$302,工数明細!$B$3:$B$302,$A63)) | AH63: =IF($AE63="","",$AE63-N($AG63)) | AI63: =IF(N($AE63)=0,"",$AG63/$AE63) | AJ63: =IF(N($AE63)=0,"",IF($AG63>$AE63,"超過",IF($AG63>=$AE63*0.9,"注意","適正")))
N64: =IF($J64="","",YEAR($J64)-IF(MONTH($J64)<マスタ!$B$4,1,0)) | O64: =IF($J64="","","Q"&(INT(MOD(MONTH($J64)-マスタ!$B$4+12,12)/3)+1)) | P64: =IF($L64="","",IF($M64<>"",$M64-$L64,IF(TODAY()>$L64,TODAY()-$L64,0))) | R64: =IF($Q64="","",$Q64*N($F64)) | T64: =IF($A64="","",SUMIFS(発注・納品!$H$3:$H$202,発注・納品!$B$3:$B$202,$A64)) | U64: =IF($Q64="","",N($S64)+N($T64)) | V64: =IF($Q64="","",$Q64-N($U64)) | W64: =IF(N($Q64)=0,"",$V64/$Q64) | X64: =IF($A64="","",COUNTIFS(発注・納品!$B$3:$B$202,$A64)) | Y64: =IF($A64="","",COUNTIFS(発注・納品!$B$3:$B$202,$A64,発注・納品!$M$3:$M$202,"")) | Z64: =IF(N($X64)=0,"",IF(_xlfn.MAXIFS(発注・納品!$M$3:$M$202,発注・納品!$B$3:$B$202,$A64)=0,"",_xlfn.MAXIFS(発注・納品!$M$3:$M$202,発注・納品!$B$3:$B$202,$A64))) | AA64: =IF($A64="","",IF(N($X64)=0,"機器なし",IF(N($Y64)>0,"入荷待ち",IF(COUNTIFS(発注・納品!$B$3:$B$202,$A64,発注・納品!$N$3:$N$202,"")>0,"受入待ち","受入完了")))) | AB64: =IF($A64="","",COUNTIFS(現地作業!$A$3:$A$202,$A64,現地作業!$L$3:$L$202,"予定")) | AC64: =IF($A64="","",COUNTIFS(現地作業!$A$3:$A$202,$A64,現地作業!$L$3:$L$202,"完了")) | AD64: =IF(N($AB64)=0,"",IF(_xlfn.MINIFS(現地作業!$C$3:$C$202,現地作業!$A$3:$A$202,$A64,現地作業!$L$3:$L$202,"予定",現地作業!$C$3:$C$202,">="&TODAY())=0,"",_xlfn.MINIFS(現地作業!$C$3:$C$202,現地作業!$A$3:$A$202,$A64,現地作業!$L$3:$L$202,"予定",現地作業!$C$3:$C$202,">="&TODAY()))) | AF64: =IF($A64="","",SUM(月次工数計画!$G$69:$AD$69)) | AG64: =IF($A64="","",SUMIFS(工数明細!$G$3:$G$302,工数明細!$B$3:$B$302,$A64)) | AH64: =IF($AE64="","",$AE64-N($AG64)) | AI64: =IF(N($AE64)=0,"",$AG64/$AE64) | AJ64: =IF(N($AE64)=0,"",IF($AG64>$AE64,"超過",IF($AG64>=$AE64*0.9,"注意","適正")))
N65: =IF($J65="","",YEAR($J65)-IF(MONTH($J65)<マスタ!$B$4,1,0)) | O65: =IF($J65="","","Q"&(INT(MOD(MONTH($J65)-マスタ!$B$4+12,12)/3)+1)) | P65: =IF($L65="","",IF($M65<>"",$M65-$L65,IF(TODAY()>$L65,TODAY()-$L65,0))) | R65: =IF($Q65="","",$Q65*N($F65)) | T65: =IF($A65="","",SUMIFS(発注・納品!$H$3:$H$202,発注・納品!$B$3:$B$202,$A65)) | U65: =IF($Q65="","",N($S65)+N($T65)) | V65: =IF($Q65="","",$Q65-N($U65)) | W65: =IF(N($Q65)=0,"",$V65/$Q65) | X65: =IF($A65="","",COUNTIFS(発注・納品!$B$3:$B$202,$A65)) | Y65: =IF($A65="","",COUNTIFS(発注・納品!$B$3:$B$202,$A65,発注・納品!$M$3:$M$202,"")) | Z65: =IF(N($X65)=0,"",IF(_xlfn.MAXIFS(発注・納品!$M$3:$M$202,発注・納品!$B$3:$B$202,$A65)=0,"",_xlfn.MAXIFS(発注・納品!$M$3:$M$202,発注・納品!$B$3:$B$202,$A65))) | AA65: =IF($A65="","",IF(N($X65)=0,"機器なし",IF(N($Y65)>0,"入荷待ち",IF(COUNTIFS(発注・納品!$B$3:$B$202,$A65,発注・納品!$N$3:$N$202,"")>0,"受入待ち","受入完了")))) | AB65: =IF($A65="","",COUNTIFS(現地作業!$A$3:$A$202,$A65,現地作業!$L$3:$L$202,"予定")) | AC65: =IF($A65="","",COUNTIFS(現地作業!$A$3:$A$202,$A65,現地作業!$L$3:$L$202,"完了")) | AD65: =IF(N($AB65)=0,"",IF(_xlfn.MINIFS(現地作業!$C$3:$C$202,現地作業!$A$3:$A$202,$A65,現地作業!$L$3:$L$202,"予定",現地作業!$C$3:$C$202,">="&TODAY())=0,"",_xlfn.MINIFS(現地作業!$C$3:$C$202,現地作業!$A$3:$A$202,$A65,現地作業!$L$3:$L$202,"予定",現地作業!$C$3:$C$202,">="&TODAY()))) | AF65: =IF($A65="","",SUM(月次工数計画!$G$70:$AD$70)) | AG65: =IF($A65="","",SUMIFS(工数明細!$G$3:$G$302,工数明細!$B$3:$B$302,$A65)) | AH65: =IF($AE65="","",$AE65-N($AG65)) | AI65: =IF(N($AE65)=0,"",$AG65/$AE65) | AJ65: =IF(N($AE65)=0,"",IF($AG65>$AE65,"超過",IF($AG65>=$AE65*0.9,"注意","適正")))
N66: =IF($J66="","",YEAR($J66)-IF(MONTH($J66)<マスタ!$B$4,1,0)) | O66: =IF($J66="","","Q"&(INT(MOD(MONTH($J66)-マスタ!$B$4+12,12)/3)+1)) | P66: =IF($L66="","",IF($M66<>"",$M66-$L66,IF(TODAY()>$L66,TODAY()-$L66,0))) | R66: =IF($Q66="","",$Q66*N($F66)) | T66: =IF($A66="","",SUMIFS(発注・納品!$H$3:$H$202,発注・納品!$B$3:$B$202,$A66)) | U66: =IF($Q66="","",N($S66)+N($T66)) | V66: =IF($Q66="","",$Q66-N($U66)) | W66: =IF(N($Q66)=0,"",$V66/$Q66) | X66: =IF($A66="","",COUNTIFS(発注・納品!$B$3:$B$202,$A66)) | Y66: =IF($A66="","",COUNTIFS(発注・納品!$B$3:$B$202,$A66,発注・納品!$M$3:$M$202,"")) | Z66: =IF(N($X66)=0,"",IF(_xlfn.MAXIFS(発注・納品!$M$3:$M$202,発注・納品!$B$3:$B$202,$A66)=0,"",_xlfn.MAXIFS(発注・納品!$M$3:$M$202,発注・納品!$B$3:$B$202,$A66))) | AA66: =IF($A66="","",IF(N($X66)=0,"機器なし",IF(N($Y66)>0,"入荷待ち",IF(COUNTIFS(発注・納品!$B$3:$B$202,$A66,発注・納品!$N$3:$N$202,"")>0,"受入待ち","受入完了")))) | AB66: =IF($A66="","",COUNTIFS(現地作業!$A$3:$A$202,$A66,現地作業!$L$3:$L$202,"予定")) | AC66: =IF($A66="","",COUNTIFS(現地作業!$A$3:$A$202,$A66,現地作業!$L$3:$L$202,"完了")) | AD66: =IF(N($AB66)=0,"",IF(_xlfn.MINIFS(現地作業!$C$3:$C$202,現地作業!$A$3:$A$202,$A66,現地作業!$L$3:$L$202,"予定",現地作業!$C$3:$C$202,">="&TODAY())=0,"",_xlfn.MINIFS(現地作業!$C$3:$C$202,現地作業!$A$3:$A$202,$A66,現地作業!$L$3:$L$202,"予定",現地作業!$C$3:$C$202,">="&TODAY()))) | AF66: =IF($A66="","",SUM(月次工数計画!$G$71:$AD$71)) | AG66: =IF($A66="","",SUMIFS(工数明細!$G$3:$G$302,工数明細!$B$3:$B$302,$A66)) | AH66: =IF($AE66="","",$AE66-N($AG66)) | AI66: =IF(N($AE66)=0,"",$AG66/$AE66) | AJ66: =IF(N($AE66)=0,"",IF($AG66>$AE66,"超過",IF($AG66>=$AE66*0.9,"注意","適正")))
N67: =IF($J67="","",YEAR($J67)-IF(MONTH($J67)<マスタ!$B$4,1,0)) | O67: =IF($J67="","","Q"&(INT(MOD(MONTH($J67)-マスタ!$B$4+12,12)/3)+1)) | P67: =IF($L67="","",IF($M67<>"",$M67-$L67,IF(TODAY()>$L67,TODAY()-$L67,0))) | R67: =IF($Q67="","",$Q67*N($F67)) | T67: =IF($A67="","",SUMIFS(発注・納品!$H$3:$H$202,発注・納品!$B$3:$B$202,$A67)) | U67: =IF($Q67="","",N($S67)+N($T67)) | V67: =IF($Q67="","",$Q67-N($U67)) | W67: =IF(N($Q67)=0,"",$V67/$Q67) | X67: =IF($A67="","",COUNTIFS(発注・納品!$B$3:$B$202,$A67)) | Y67: =IF($A67="","",COUNTIFS(発注・納品!$B$3:$B$202,$A67,発注・納品!$M$3:$M$202,"")) | Z67: =IF(N($X67)=0,"",IF(_xlfn.MAXIFS(発注・納品!$M$3:$M$202,発注・納品!$B$3:$B$202,$A67)=0,"",_xlfn.MAXIFS(発注・納品!$M$3:$M$202,発注・納品!$B$3:$B$202,$A67))) | AA67: =IF($A67="","",IF(N($X67)=0,"機器なし",IF(N($Y67)>0,"入荷待ち",IF(COUNTIFS(発注・納品!$B$3:$B$202,$A67,発注・納品!$N$3:$N$202,"")>0,"受入待ち","受入完了")))) | AB67: =IF($A67="","",COUNTIFS(現地作業!$A$3:$A$202,$A67,現地作業!$L$3:$L$202,"予定")) | AC67: =IF($A67="","",COUNTIFS(現地作業!$A$3:$A$202,$A67,現地作業!$L$3:$L$202,"完了")) | AD67: =IF(N($AB67)=0,"",IF(_xlfn.MINIFS(現地作業!$C$3:$C$202,現地作業!$A$3:$A$202,$A67,現地作業!$L$3:$L$202,"予定",現地作業!$C$3:$C$202,">="&TODAY())=0,"",_xlfn.MINIFS(現地作業!$C$3:$C$202,現地作業!$A$3:$A$202,$A67,現地作業!$L$3:$L$202,"予定",現地作業!$C$3:$C$202,">="&TODAY()))) | AF67: =IF($A67="","",SUM(月次工数計画!$G$72:$AD$72)) | AG67: =IF($A67="","",SUMIFS(工数明細!$G$3:$G$302,工数明細!$B$3:$B$302,$A67)) | AH67: =IF($AE67="","",$AE67-N($AG67)) | AI67: =IF(N($AE67)=0,"",$AG67/$AE67) | AJ67: =IF(N($AE67)=0,"",IF($AG67>$AE67,"超過",IF($AG67>=$AE67*0.9,"注意","適正")))
N68: =IF($J68="","",YEAR($J68)-IF(MONTH($J68)<マスタ!$B$4,1,0)) | O68: =IF($J68="","","Q"&(INT(MOD(MONTH($J68)-マスタ!$B$4+12,12)/3)+1)) | P68: =IF($L68="","",IF($M68<>"",$M68-$L68,IF(TODAY()>$L68,TODAY()-$L68,0))) | R68: =IF($Q68="","",$Q68*N($F68)) | T68: =IF($A68="","",SUMIFS(発注・納品!$H$3:$H$202,発注・納品!$B$3:$B$202,$A68)) | U68: =IF($Q68="","",N($S68)+N($T68)) | V68: =IF($Q68="","",$Q68-N($U68)) | W68: =IF(N($Q68)=0,"",$V68/$Q68) | X68: =IF($A68="","",COUNTIFS(発注・納品!$B$3:$B$202,$A68)) | Y68: =IF($A68="","",COUNTIFS(発注・納品!$B$3:$B$202,$A68,発注・納品!$M$3:$M$202,"")) | Z68: =IF(N($X68)=0,"",IF(_xlfn.MAXIFS(発注・納品!$M$3:$M$202,発注・納品!$B$3:$B$202,$A68)=0,"",_xlfn.MAXIFS(発注・納品!$M$3:$M$202,発注・納品!$B$3:$B$202,$A68))) | AA68: =IF($A68="","",IF(N($X68)=0,"機器なし",IF(N($Y68)>0,"入荷待ち",IF(COUNTIFS(発注・納品!$B$3:$B$202,$A68,発注・納品!$N$3:$N$202,"")>0,"受入待ち","受入完了")))) | AB68: =IF($A68="","",COUNTIFS(現地作業!$A$3:$A$202,$A68,現地作業!$L$3:$L$202,"予定")) | AC68: =IF($A68="","",COUNTIFS(現地作業!$A$3:$A$202,$A68,現地作業!$L$3:$L$202,"完了")) | AD68: =IF(N($AB68)=0,"",IF(_xlfn.MINIFS(現地作業!$C$3:$C$202,現地作業!$A$3:$A$202,$A68,現地作業!$L$3:$L$202,"予定",現地作業!$C$3:$C$202,">="&TODAY())=0,"",_xlfn.MINIFS(現地作業!$C$3:$C$202,現地作業!$A$3:$A$202,$A68,現地作業!$L$3:$L$202,"予定",現地作業!$C$3:$C$202,">="&TODAY()))) | AF68: =IF($A68="","",SUM(月次工数計画!$G$73:$AD$73)) | AG68: =IF($A68="","",SUMIFS(工数明細!$G$3:$G$302,工数明細!$B$3:$B$302,$A68)) | AH68: =IF($AE68="","",$AE68-N($AG68)) | AI68: =IF(N($AE68)=0,"",$AG68/$AE68) | AJ68: =IF(N($AE68)=0,"",IF($AG68>$AE68,"超過",IF($AG68>=$AE68*0.9,"注意","適正")))
N69: =IF($J69="","",YEAR($J69)-IF(MONTH($J69)<マスタ!$B$4,1,0)) | O69: =IF($J69="","","Q"&(INT(MOD(MONTH($J69)-マスタ!$B$4+12,12)/3)+1)) | P69: =IF($L69="","",IF($M69<>"",$M69-$L69,IF(TODAY()>$L69,TODAY()-$L69,0))) | R69: =IF($Q69="","",$Q69*N($F69)) | T69: =IF($A69="","",SUMIFS(発注・納品!$H$3:$H$202,発注・納品!$B$3:$B$202,$A69)) | U69: =IF($Q69="","",N($S69)+N($T69)) | V69: =IF($Q69="","",$Q69-N($U69)) | W69: =IF(N($Q69)=0,"",$V69/$Q69) | X69: =IF($A69="","",COUNTIFS(発注・納品!$B$3:$B$202,$A69)) | Y69: =IF($A69="","",COUNTIFS(発注・納品!$B$3:$B$202,$A69,発注・納品!$M$3:$M$202,"")) | Z69: =IF(N($X69)=0,"",IF(_xlfn.MAXIFS(発注・納品!$M$3:$M$202,発注・納品!$B$3:$B$202,$A69)=0,"",_xlfn.MAXIFS(発注・納品!$M$3:$M$202,発注・納品!$B$3:$B$202,$A69))) | AA69: =IF($A69="","",IF(N($X69)=0,"機器なし",IF(N($Y69)>0,"入荷待ち",IF(COUNTIFS(発注・納品!$B$3:$B$202,$A69,発注・納品!$N$3:$N$202,"")>0,"受入待ち","受入完了")))) | AB69: =IF($A69="","",COUNTIFS(現地作業!$A$3:$A$202,$A69,現地作業!$L$3:$L$202,"予定")) | AC69: =IF($A69="","",COUNTIFS(現地作業!$A$3:$A$202,$A69,現地作業!$L$3:$L$202,"完了")) | AD69: =IF(N($AB69)=0,"",IF(_xlfn.MINIFS(現地作業!$C$3:$C$202,現地作業!$A$3:$A$202,$A69,現地作業!$L$3:$L$202,"予定",現地作業!$C$3:$C$202,">="&TODAY())=0,"",_xlfn.MINIFS(現地作業!$C$3:$C$202,現地作業!$A$3:$A$202,$A69,現地作業!$L$3:$L$202,"予定",現地作業!$C$3:$C$202,">="&TODAY()))) | AF69: =IF($A69="","",SUM(月次工数計画!$G$74:$AD$74)) | AG69: =IF($A69="","",SUMIFS(工数明細!$G$3:$G$302,工数明細!$B$3:$B$302,$A69)) | AH69: =IF($AE69="","",$AE69-N($AG69)) | AI69: =IF(N($AE69)=0,"",$AG69/$AE69) | AJ69: =IF(N($AE69)=0,"",IF($AG69>$AE69,"超過",IF($AG69>=$AE69*0.9,"注意","適正")))
N70: =IF($J70="","",YEAR($J70)-IF(MONTH($J70)<マスタ!$B$4,1,0)) | O70: =IF($J70="","","Q"&(INT(MOD(MONTH($J70)-マスタ!$B$4+12,12)/3)+1)) | P70: =IF($L70="","",IF($M70<>"",$M70-$L70,IF(TODAY()>$L70,TODAY()-$L70,0))) | R70: =IF($Q70="","",$Q70*N($F70)) | T70: =IF($A70="","",SUMIFS(発注・納品!$H$3:$H$202,発注・納品!$B$3:$B$202,$A70)) | U70: =IF($Q70="","",N($S70)+N($T70)) | V70: =IF($Q70="","",$Q70-N($U70)) | W70: =IF(N($Q70)=0,"",$V70/$Q70) | X70: =IF($A70="","",COUNTIFS(発注・納品!$B$3:$B$202,$A70)) | Y70: =IF($A70="","",COUNTIFS(発注・納品!$B$3:$B$202,$A70,発注・納品!$M$3:$M$202,"")) | Z70: =IF(N($X70)=0,"",IF(_xlfn.MAXIFS(発注・納品!$M$3:$M$202,発注・納品!$B$3:$B$202,$A70)=0,"",_xlfn.MAXIFS(発注・納品!$M$3:$M$202,発注・納品!$B$3:$B$202,$A70))) | AA70: =IF($A70="","",IF(N($X70)=0,"機器なし",IF(N($Y70)>0,"入荷待ち",IF(COUNTIFS(発注・納品!$B$3:$B$202,$A70,発注・納品!$N$3:$N$202,"")>0,"受入待ち","受入完了")))) | AB70: =IF($A70="","",COUNTIFS(現地作業!$A$3:$A$202,$A70,現地作業!$L$3:$L$202,"予定")) | AC70: =IF($A70="","",COUNTIFS(現地作業!$A$3:$A$202,$A70,現地作業!$L$3:$L$202,"完了")) | AD70: =IF(N($AB70)=0,"",IF(_xlfn.MINIFS(現地作業!$C$3:$C$202,現地作業!$A$3:$A$202,$A70,現地作業!$L$3:$L$202,"予定",現地作業!$C$3:$C$202,">="&TODAY())=0,"",_xlfn.MINIFS(現地作業!$C$3:$C$202,現地作業!$A$3:$A$202,$A70,現地作業!$L$3:$L$202,"予定",現地作業!$C$3:$C$202,">="&TODAY()))) | AF70: =IF($A70="","",SUM(月次工数計画!$G$75:$AD$75)) | AG70: =IF($A70="","",SUMIFS(工数明細!$G$3:$G$302,工数明細!$B$3:$B$302,$A70)) | AH70: =IF($AE70="","",$AE70-N($AG70)) | AI70: =IF(N($AE70)=0,"",$AG70/$AE70) | AJ70: =IF(N($AE70)=0,"",IF($AG70>$AE70,"超過",IF($AG70>=$AE70*0.9,"注意","適正")))
N71: =IF($J71="","",YEAR($J71)-IF(MONTH($J71)<マスタ!$B$4,1,0)) | O71: =IF($J71="","","Q"&(INT(MOD(MONTH($J71)-マスタ!$B$4+12,12)/3)+1)) | P71: =IF($L71="","",IF($M71<>"",$M71-$L71,IF(TODAY()>$L71,TODAY()-$L71,0))) | R71: =IF($Q71="","",$Q71*N($F71)) | T71: =IF($A71="","",SUMIFS(発注・納品!$H$3:$H$202,発注・納品!$B$3:$B$202,$A71)) | U71: =IF($Q71="","",N($S71)+N($T71)) | V71: =IF($Q71="","",$Q71-N($U71)) | W71: =IF(N($Q71)=0,"",$V71/$Q71) | X71: =IF($A71="","",COUNTIFS(発注・納品!$B$3:$B$202,$A71)) | Y71: =IF($A71="","",COUNTIFS(発注・納品!$B$3:$B$202,$A71,発注・納品!$M$3:$M$202,"")) | Z71: =IF(N($X71)=0,"",IF(_xlfn.MAXIFS(発注・納品!$M$3:$M$202,発注・納品!$B$3:$B$202,$A71)=0,"",_xlfn.MAXIFS(発注・納品!$M$3:$M$202,発注・納品!$B$3:$B$202,$A71))) | AA71: =IF($A71="","",IF(N($X71)=0,"機器なし",IF(N($Y71)>0,"入荷待ち",IF(COUNTIFS(発注・納品!$B$3:$B$202,$A71,発注・納品!$N$3:$N$202,"")>0,"受入待ち","受入完了")))) | AB71: =IF($A71="","",COUNTIFS(現地作業!$A$3:$A$202,$A71,現地作業!$L$3:$L$202,"予定")) | AC71: =IF($A71="","",COUNTIFS(現地作業!$A$3:$A$202,$A71,現地作業!$L$3:$L$202,"完了")) | AD71: =IF(N($AB71)=0,"",IF(_xlfn.MINIFS(現地作業!$C$3:$C$202,現地作業!$A$3:$A$202,$A71,現地作業!$L$3:$L$202,"予定",現地作業!$C$3:$C$202,">="&TODAY())=0,"",_xlfn.MINIFS(現地作業!$C$3:$C$202,現地作業!$A$3:$A$202,$A71,現地作業!$L$3:$L$202,"予定",現地作業!$C$3:$C$202,">="&TODAY()))) | AF71: =IF($A71="","",SUM(月次工数計画!$G$76:$AD$76)) | AG71: =IF($A71="","",SUMIFS(工数明細!$G$3:$G$302,工数明細!$B$3:$B$302,$A71)) | AH71: =IF($AE71="","",$AE71-N($AG71)) | AI71: =IF(N($AE71)=0,"",$AG71/$AE71) | AJ71: =IF(N($AE71)=0,"",IF($AG71>$AE71,"超過",IF($AG71>=$AE71*0.9,"注意","適正")))
N72: =IF($J72="","",YEAR($J72)-IF(MONTH($J72)<マスタ!$B$4,1,0)) | O72: =IF($J72="","","Q"&(INT(MOD(MONTH($J72)-マスタ!$B$4+12,12)/3)+1)) | P72: =IF($L72="","",IF($M72<>"",$M72-$L72,IF(TODAY()>$L72,TODAY()-$L72,0))) | R72: =IF($Q72="","",$Q72*N($F72)) | T72: =IF($A72="","",SUMIFS(発注・納品!$H$3:$H$202,発注・納品!$B$3:$B$202,$A72)) | U72: =IF($Q72="","",N($S72)+N($T72)) | V72: =IF($Q72="","",$Q72-N($U72)) | W72: =IF(N($Q72)=0,"",$V72/$Q72) | X72: =IF($A72="","",COUNTIFS(発注・納品!$B$3:$B$202,$A72)) | Y72: =IF($A72="","",COUNTIFS(発注・納品!$B$3:$B$202,$A72,発注・納品!$M$3:$M$202,"")) | Z72: =IF(N($X72)=0,"",IF(_xlfn.MAXIFS(発注・納品!$M$3:$M$202,発注・納品!$B$3:$B$202,$A72)=0,"",_xlfn.MAXIFS(発注・納品!$M$3:$M$202,発注・納品!$B$3:$B$202,$A72))) | AA72: =IF($A72="","",IF(N($X72)=0,"機器なし",IF(N($Y72)>0,"入荷待ち",IF(COUNTIFS(発注・納品!$B$3:$B$202,$A72,発注・納品!$N$3:$N$202,"")>0,"受入待ち","受入完了")))) | AB72: =IF($A72="","",COUNTIFS(現地作業!$A$3:$A$202,$A72,現地作業!$L$3:$L$202,"予定")) | AC72: =IF($A72="","",COUNTIFS(現地作業!$A$3:$A$202,$A72,現地作業!$L$3:$L$202,"完了")) | AD72: =IF(N($AB72)=0,"",IF(_xlfn.MINIFS(現地作業!$C$3:$C$202,現地作業!$A$3:$A$202,$A72,現地作業!$L$3:$L$202,"予定",現地作業!$C$3:$C$202,">="&TODAY())=0,"",_xlfn.MINIFS(現地作業!$C$3:$C$202,現地作業!$A$3:$A$202,$A72,現地作業!$L$3:$L$202,"予定",現地作業!$C$3:$C$202,">="&TODAY()))) | AF72: =IF($A72="","",SUM(月次工数計画!$G$77:$AD$77)) | AG72: =IF($A72="","",SUMIFS(工数明細!$G$3:$G$302,工数明細!$B$3:$B$302,$A72)) | AH72: =IF($AE72="","",$AE72-N($AG72)) | AI72: =IF(N($AE72)=0,"",$AG72/$AE72) | AJ72: =IF(N($AE72)=0,"",IF($AG72>$AE72,"超過",IF($AG72>=$AE72*0.9,"注意","適正")))
N73: =IF($J73="","",YEAR($J73)-IF(MONTH($J73)<マスタ!$B$4,1,0)) | O73: =IF($J73="","","Q"&(INT(MOD(MONTH($J73)-マスタ!$B$4+12,12)/3)+1)) | P73: =IF($L73="","",IF($M73<>"",$M73-$L73,IF(TODAY()>$L73,TODAY()-$L73,0))) | R73: =IF($Q73="","",$Q73*N($F73)) | T73: =IF($A73="","",SUMIFS(発注・納品!$H$3:$H$202,発注・納品!$B$3:$B$202,$A73)) | U73: =IF($Q73="","",N($S73)+N($T73)) | V73: =IF($Q73="","",$Q73-N($U73)) | W73: =IF(N($Q73)=0,"",$V73/$Q73) | X73: =IF($A73="","",COUNTIFS(発注・納品!$B$3:$B$202,$A73)) | Y73: =IF($A73="","",COUNTIFS(発注・納品!$B$3:$B$202,$A73,発注・納品!$M$3:$M$202,"")) | Z73: =IF(N($X73)=0,"",IF(_xlfn.MAXIFS(発注・納品!$M$3:$M$202,発注・納品!$B$3:$B$202,$A73)=0,"",_xlfn.MAXIFS(発注・納品!$M$3:$M$202,発注・納品!$B$3:$B$202,$A73))) | AA73: =IF($A73="","",IF(N($X73)=0,"機器なし",IF(N($Y73)>0,"入荷待ち",IF(COUNTIFS(発注・納品!$B$3:$B$202,$A73,発注・納品!$N$3:$N$202,"")>0,"受入待ち","受入完了")))) | AB73: =IF($A73="","",COUNTIFS(現地作業!$A$3:$A$202,$A73,現地作業!$L$3:$L$202,"予定")) | AC73: =IF($A73="","",COUNTIFS(現地作業!$A$3:$A$202,$A73,現地作業!$L$3:$L$202,"完了")) | AD73: =IF(N($AB73)=0,"",IF(_xlfn.MINIFS(現地作業!$C$3:$C$202,現地作業!$A$3:$A$202,$A73,現地作業!$L$3:$L$202,"予定",現地作業!$C$3:$C$202,">="&TODAY())=0,"",_xlfn.MINIFS(現地作業!$C$3:$C$202,現地作業!$A$3:$A$202,$A73,現地作業!$L$3:$L$202,"予定",現地作業!$C$3:$C$202,">="&TODAY()))) | AF73: =IF($A73="","",SUM(月次工数計画!$G$78:$AD$78)) | AG73: =IF($A73="","",SUMIFS(工数明細!$G$3:$G$302,工数明細!$B$3:$B$302,$A73)) | AH73: =IF($AE73="","",$AE73-N($AG73)) | AI73: =IF(N($AE73)=0,"",$AG73/$AE73) | AJ73: =IF(N($AE73)=0,"",IF($AG73>$AE73,"超過",IF($AG73>=$AE73*0.9,"注意","適正")))
N74: =IF($J74="","",YEAR($J74)-IF(MONTH($J74)<マスタ!$B$4,1,0)) | O74: =IF($J74="","","Q"&(INT(MOD(MONTH($J74)-マスタ!$B$4+12,12)/3)+1)) | P74: =IF($L74="","",IF($M74<>"",$M74-$L74,IF(TODAY()>$L74,TODAY()-$L74,0))) | R74: =IF($Q74="","",$Q74*N($F74)) | T74: =IF($A74="","",SUMIFS(発注・納品!$H$3:$H$202,発注・納品!$B$3:$B$202,$A74)) | U74: =IF($Q74="","",N($S74)+N($T74)) | V74: =IF($Q74="","",$Q74-N($U74)) | W74: =IF(N($Q74)=0,"",$V74/$Q74) | X74: =IF($A74="","",COUNTIFS(発注・納品!$B$3:$B$202,$A74)) | Y74: =IF($A74="","",COUNTIFS(発注・納品!$B$3:$B$202,$A74,発注・納品!$M$3:$M$202,"")) | Z74: =IF(N($X74)=0,"",IF(_xlfn.MAXIFS(発注・納品!$M$3:$M$202,発注・納品!$B$3:$B$202,$A74)=0,"",_xlfn.MAXIFS(発注・納品!$M$3:$M$202,発注・納品!$B$3:$B$202,$A74))) | AA74: =IF($A74="","",IF(N($X74)=0,"機器なし",IF(N($Y74)>0,"入荷待ち",IF(COUNTIFS(発注・納品!$B$3:$B$202,$A74,発注・納品!$N$3:$N$202,"")>0,"受入待ち","受入完了")))) | AB74: =IF($A74="","",COUNTIFS(現地作業!$A$3:$A$202,$A74,現地作業!$L$3:$L$202,"予定")) | AC74: =IF($A74="","",COUNTIFS(現地作業!$A$3:$A$202,$A74,現地作業!$L$3:$L$202,"完了")) | AD74: =IF(N($AB74)=0,"",IF(_xlfn.MINIFS(現地作業!$C$3:$C$202,現地作業!$A$3:$A$202,$A74,現地作業!$L$3:$L$202,"予定",現地作業!$C$3:$C$202,">="&TODAY())=0,"",_xlfn.MINIFS(現地作業!$C$3:$C$202,現地作業!$A$3:$A$202,$A74,現地作業!$L$3:$L$202,"予定",現地作業!$C$3:$C$202,">="&TODAY()))) | AF74: =IF($A74="","",SUM(月次工数計画!$G$79:$AD$79)) | AG74: =IF($A74="","",SUMIFS(工数明細!$G$3:$G$302,工数明細!$B$3:$B$302,$A74)) | AH74: =IF($AE74="","",$AE74-N($AG74)) | AI74: =IF(N($AE74)=0,"",$AG74/$AE74) | AJ74: =IF(N($AE74)=0,"",IF($AG74>$AE74,"超過",IF($AG74>=$AE74*0.9,"注意","適正")))
N75: =IF($J75="","",YEAR($J75)-IF(MONTH($J75)<マスタ!$B$4,1,0)) | O75: =IF($J75="","","Q"&(INT(MOD(MONTH($J75)-マスタ!$B$4+12,12)/3)+1)) | P75: =IF($L75="","",IF($M75<>"",$M75-$L75,IF(TODAY()>$L75,TODAY()-$L75,0))) | R75: =IF($Q75="","",$Q75*N($F75)) | T75: =IF($A75="","",SUMIFS(発注・納品!$H$3:$H$202,発注・納品!$B$3:$B$202,$A75)) | U75: =IF($Q75="","",N($S75)+N($T75)) | V75: =IF($Q75="","",$Q75-N($U75)) | W75: =IF(N($Q75)=0,"",$V75/$Q75) | X75: =IF($A75="","",COUNTIFS(発注・納品!$B$3:$B$202,$A75)) | Y75: =IF($A75="","",COUNTIFS(発注・納品!$B$3:$B$202,$A75,発注・納品!$M$3:$M$202,"")) | Z75: =IF(N($X75)=0,"",IF(_xlfn.MAXIFS(発注・納品!$M$3:$M$202,発注・納品!$B$3:$B$202,$A75)=0,"",_xlfn.MAXIFS(発注・納品!$M$3:$M$202,発注・納品!$B$3:$B$202,$A75))) | AA75: =IF($A75="","",IF(N($X75)=0,"機器なし",IF(N($Y75)>0,"入荷待ち",IF(COUNTIFS(発注・納品!$B$3:$B$202,$A75,発注・納品!$N$3:$N$202,"")>0,"受入待ち","受入完了")))) | AB75: =IF($A75="","",COUNTIFS(現地作業!$A$3:$A$202,$A75,現地作業!$L$3:$L$202,"予定")) | AC75: =IF($A75="","",COUNTIFS(現地作業!$A$3:$A$202,$A75,現地作業!$L$3:$L$202,"完了")) | AD75: =IF(N($AB75)=0,"",IF(_xlfn.MINIFS(現地作業!$C$3:$C$202,現地作業!$A$3:$A$202,$A75,現地作業!$L$3:$L$202,"予定",現地作業!$C$3:$C$202,">="&TODAY())=0,"",_xlfn.MINIFS(現地作業!$C$3:$C$202,現地作業!$A$3:$A$202,$A75,現地作業!$L$3:$L$202,"予定",現地作業!$C$3:$C$202,">="&TODAY()))) | AF75: =IF($A75="","",SUM(月次工数計画!$G$80:$AD$80)) | AG75: =IF($A75="","",SUMIFS(工数明細!$G$3:$G$302,工数明細!$B$3:$B$302,$A75)) | AH75: =IF($AE75="","",$AE75-N($AG75)) | AI75: =IF(N($AE75)=0,"",$AG75/$AE75) | AJ75: =IF(N($AE75)=0,"",IF($AG75>$AE75,"超過",IF($AG75>=$AE75*0.9,"注意","適正")))
N76: =IF($J76="","",YEAR($J76)-IF(MONTH($J76)<マスタ!$B$4,1,0)) | O76: =IF($J76="","","Q"&(INT(MOD(MONTH($J76)-マスタ!$B$4+12,12)/3)+1)) | P76: =IF($L76="","",IF($M76<>"",$M76-$L76,IF(TODAY()>$L76,TODAY()-$L76,0))) | R76: =IF($Q76="","",$Q76*N($F76)) | T76: =IF($A76="","",SUMIFS(発注・納品!$H$3:$H$202,発注・納品!$B$3:$B$202,$A76)) | U76: =IF($Q76="","",N($S76)+N($T76)) | V76: =IF($Q76="","",$Q76-N($U76)) | W76: =IF(N($Q76)=0,"",$V76/$Q76) | X76: =IF($A76="","",COUNTIFS(発注・納品!$B$3:$B$202,$A76)) | Y76: =IF($A76="","",COUNTIFS(発注・納品!$B$3:$B$202,$A76,発注・納品!$M$3:$M$202,"")) | Z76: =IF(N($X76)=0,"",IF(_xlfn.MAXIFS(発注・納品!$M$3:$M$202,発注・納品!$B$3:$B$202,$A76)=0,"",_xlfn.MAXIFS(発注・納品!$M$3:$M$202,発注・納品!$B$3:$B$202,$A76))) | AA76: =IF($A76="","",IF(N($X76)=0,"機器なし",IF(N($Y76)>0,"入荷待ち",IF(COUNTIFS(発注・納品!$B$3:$B$202,$A76,発注・納品!$N$3:$N$202,"")>0,"受入待ち","受入完了")))) | AB76: =IF($A76="","",COUNTIFS(現地作業!$A$3:$A$202,$A76,現地作業!$L$3:$L$202,"予定")) | AC76: =IF($A76="","",COUNTIFS(現地作業!$A$3:$A$202,$A76,現地作業!$L$3:$L$202,"完了")) | AD76: =IF(N($AB76)=0,"",IF(_xlfn.MINIFS(現地作業!$C$3:$C$202,現地作業!$A$3:$A$202,$A76,現地作業!$L$3:$L$202,"予定",現地作業!$C$3:$C$202,">="&TODAY())=0,"",_xlfn.MINIFS(現地作業!$C$3:$C$202,現地作業!$A$3:$A$202,$A76,現地作業!$L$3:$L$202,"予定",現地作業!$C$3:$C$202,">="&TODAY()))) | AF76: =IF($A76="","",SUM(月次工数計画!$G$81:$AD$81)) | AG76: =IF($A76="","",SUMIFS(工数明細!$G$3:$G$302,工数明細!$B$3:$B$302,$A76)) | AH76: =IF($AE76="","",$AE76-N($AG76)) | AI76: =IF(N($AE76)=0,"",$AG76/$AE76) | AJ76: =IF(N($AE76)=0,"",IF($AG76>$AE76,"超過",IF($AG76>=$AE76*0.9,"注意","適正")))
N77: =IF($J77="","",YEAR($J77)-IF(MONTH($J77)<マスタ!$B$4,1,0)) | O77: =IF($J77="","","Q"&(INT(MOD(MONTH($J77)-マスタ!$B$4+12,12)/3)+1)) | P77: =IF($L77="","",IF($M77<>"",$M77-$L77,IF(TODAY()>$L77,TODAY()-$L77,0))) | R77: =IF($Q77="","",$Q77*N($F77)) | T77: =IF($A77="","",SUMIFS(発注・納品!$H$3:$H$202,発注・納品!$B$3:$B$202,$A77)) | U77: =IF($Q77="","",N($S77)+N($T77)) | V77: =IF($Q77="","",$Q77-N($U77)) | W77: =IF(N($Q77)=0,"",$V77/$Q77) | X77: =IF($A77="","",COUNTIFS(発注・納品!$B$3:$B$202,$A77)) | Y77: =IF($A77="","",COUNTIFS(発注・納品!$B$3:$B$202,$A77,発注・納品!$M$3:$M$202,"")) | Z77: =IF(N($X77)=0,"",IF(_xlfn.MAXIFS(発注・納品!$M$3:$M$202,発注・納品!$B$3:$B$202,$A77)=0,"",_xlfn.MAXIFS(発注・納品!$M$3:$M$202,発注・納品!$B$3:$B$202,$A77))) | AA77: =IF($A77="","",IF(N($X77)=0,"機器なし",IF(N($Y77)>0,"入荷待ち",IF(COUNTIFS(発注・納品!$B$3:$B$202,$A77,発注・納品!$N$3:$N$202,"")>0,"受入待ち","受入完了")))) | AB77: =IF($A77="","",COUNTIFS(現地作業!$A$3:$A$202,$A77,現地作業!$L$3:$L$202,"予定")) | AC77: =IF($A77="","",COUNTIFS(現地作業!$A$3:$A$202,$A77,現地作業!$L$3:$L$202,"完了")) | AD77: =IF(N($AB77)=0,"",IF(_xlfn.MINIFS(現地作業!$C$3:$C$202,現地作業!$A$3:$A$202,$A77,現地作業!$L$3:$L$202,"予定",現地作業!$C$3:$C$202,">="&TODAY())=0,"",_xlfn.MINIFS(現地作業!$C$3:$C$202,現地作業!$A$3:$A$202,$A77,現地作業!$L$3:$L$202,"予定",現地作業!$C$3:$C$202,">="&TODAY()))) | AF77: =IF($A77="","",SUM(月次工数計画!$G$82:$AD$82)) | AG77: =IF($A77="","",SUMIFS(工数明細!$G$3:$G$302,工数明細!$B$3:$B$302,$A77)) | AH77: =IF($AE77="","",$AE77-N($AG77)) | AI77: =IF(N($AE77)=0,"",$AG77/$AE77) | AJ77: =IF(N($AE77)=0,"",IF($AG77>$AE77,"超過",IF($AG77>=$AE77*0.9,"注意","適正")))
N78: =IF($J78="","",YEAR($J78)-IF(MONTH($J78)<マスタ!$B$4,1,0)) | O78: =IF($J78="","","Q"&(INT(MOD(MONTH($J78)-マスタ!$B$4+12,12)/3)+1)) | P78: =IF($L78="","",IF($M78<>"",$M78-$L78,IF(TODAY()>$L78,TODAY()-$L78,0))) | R78: =IF($Q78="","",$Q78*N($F78)) | T78: =IF($A78="","",SUMIFS(発注・納品!$H$3:$H$202,発注・納品!$B$3:$B$202,$A78)) | U78: =IF($Q78="","",N($S78)+N($T78)) | V78: =IF($Q78="","",$Q78-N($U78)) | W78: =IF(N($Q78)=0,"",$V78/$Q78) | X78: =IF($A78="","",COUNTIFS(発注・納品!$B$3:$B$202,$A78)) | Y78: =IF($A78="","",COUNTIFS(発注・納品!$B$3:$B$202,$A78,発注・納品!$M$3:$M$202,"")) | Z78: =IF(N($X78)=0,"",IF(_xlfn.MAXIFS(発注・納品!$M$3:$M$202,発注・納品!$B$3:$B$202,$A78)=0,"",_xlfn.MAXIFS(発注・納品!$M$3:$M$202,発注・納品!$B$3:$B$202,$A78))) | AA78: =IF($A78="","",IF(N($X78)=0,"機器なし",IF(N($Y78)>0,"入荷待ち",IF(COUNTIFS(発注・納品!$B$3:$B$202,$A78,発注・納品!$N$3:$N$202,"")>0,"受入待ち","受入完了")))) | AB78: =IF($A78="","",COUNTIFS(現地作業!$A$3:$A$202,$A78,現地作業!$L$3:$L$202,"予定")) | AC78: =IF($A78="","",COUNTIFS(現地作業!$A$3:$A$202,$A78,現地作業!$L$3:$L$202,"完了")) | AD78: =IF(N($AB78)=0,"",IF(_xlfn.MINIFS(現地作業!$C$3:$C$202,現地作業!$A$3:$A$202,$A78,現地作業!$L$3:$L$202,"予定",現地作業!$C$3:$C$202,">="&TODAY())=0,"",_xlfn.MINIFS(現地作業!$C$3:$C$202,現地作業!$A$3:$A$202,$A78,現地作業!$L$3:$L$202,"予定",現地作業!$C$3:$C$202,">="&TODAY()))) | AF78: =IF($A78="","",SUM(月次工数計画!$G$83:$AD$83)) | AG78: =IF($A78="","",SUMIFS(工数明細!$G$3:$G$302,工数明細!$B$3:$B$302,$A78)) | AH78: =IF($AE78="","",$AE78-N($AG78)) | AI78: =IF(N($AE78)=0,"",$AG78/$AE78) | AJ78: =IF(N($AE78)=0,"",IF($AG78>$AE78,"超過",IF($AG78>=$AE78*0.9,"注意","適正")))
N79: =IF($J79="","",YEAR($J79)-IF(MONTH($J79)<マスタ!$B$4,1,0)) | O79: =IF($J79="","","Q"&(INT(MOD(MONTH($J79)-マスタ!$B$4+12,12)/3)+1)) | P79: =IF($L79="","",IF($M79<>"",$M79-$L79,IF(TODAY()>$L79,TODAY()-$L79,0))) | R79: =IF($Q79="","",$Q79*N($F79)) | T79: =IF($A79="","",SUMIFS(発注・納品!$H$3:$H$202,発注・納品!$B$3:$B$202,$A79)) | U79: =IF($Q79="","",N($S79)+N($T79)) | V79: =IF($Q79="","",$Q79-N($U79)) | W79: =IF(N($Q79)=0,"",$V79/$Q79) | X79: =IF($A79="","",COUNTIFS(発注・納品!$B$3:$B$202,$A79)) | Y79: =IF($A79="","",COUNTIFS(発注・納品!$B$3:$B$202,$A79,発注・納品!$M$3:$M$202,"")) | Z79: =IF(N($X79)=0,"",IF(_xlfn.MAXIFS(発注・納品!$M$3:$M$202,発注・納品!$B$3:$B$202,$A79)=0,"",_xlfn.MAXIFS(発注・納品!$M$3:$M$202,発注・納品!$B$3:$B$202,$A79))) | AA79: =IF($A79="","",IF(N($X79)=0,"機器なし",IF(N($Y79)>0,"入荷待ち",IF(COUNTIFS(発注・納品!$B$3:$B$202,$A79,発注・納品!$N$3:$N$202,"")>0,"受入待ち","受入完了")))) | AB79: =IF($A79="","",COUNTIFS(現地作業!$A$3:$A$202,$A79,現地作業!$L$3:$L$202,"予定")) | AC79: =IF($A79="","",COUNTIFS(現地作業!$A$3:$A$202,$A79,現地作業!$L$3:$L$202,"完了")) | AD79: =IF(N($AB79)=0,"",IF(_xlfn.MINIFS(現地作業!$C$3:$C$202,現地作業!$A$3:$A$202,$A79,現地作業!$L$3:$L$202,"予定",現地作業!$C$3:$C$202,">="&TODAY())=0,"",_xlfn.MINIFS(現地作業!$C$3:$C$202,現地作業!$A$3:$A$202,$A79,現地作業!$L$3:$L$202,"予定",現地作業!$C$3:$C$202,">="&TODAY()))) | AF79: =IF($A79="","",SUM(月次工数計画!$G$84:$AD$84)) | AG79: =IF($A79="","",SUMIFS(工数明細!$G$3:$G$302,工数明細!$B$3:$B$302,$A79)) | AH79: =IF($AE79="","",$AE79-N($AG79)) | AI79: =IF(N($AE79)=0,"",$AG79/$AE79) | AJ79: =IF(N($AE79)=0,"",IF($AG79>$AE79,"超過",IF($AG79>=$AE79*0.9,"注意","適正")))
N80: =IF($J80="","",YEAR($J80)-IF(MONTH($J80)<マスタ!$B$4,1,0)) | O80: =IF($J80="","","Q"&(INT(MOD(MONTH($J80)-マスタ!$B$4+12,12)/3)+1)) | P80: =IF($L80="","",IF($M80<>"",$M80-$L80,IF(TODAY()>$L80,TODAY()-$L80,0))) | R80: =IF($Q80="","",$Q80*N($F80)) | T80: =IF($A80="","",SUMIFS(発注・納品!$H$3:$H$202,発注・納品!$B$3:$B$202,$A80)) | U80: =IF($Q80="","",N($S80)+N($T80)) | V80: =IF($Q80="","",$Q80-N($U80)) | W80: =IF(N($Q80)=0,"",$V80/$Q80) | X80: =IF($A80="","",COUNTIFS(発注・納品!$B$3:$B$202,$A80)) | Y80: =IF($A80="","",COUNTIFS(発注・納品!$B$3:$B$202,$A80,発注・納品!$M$3:$M$202,"")) | Z80: =IF(N($X80)=0,"",IF(_xlfn.MAXIFS(発注・納品!$M$3:$M$202,発注・納品!$B$3:$B$202,$A80)=0,"",_xlfn.MAXIFS(発注・納品!$M$3:$M$202,発注・納品!$B$3:$B$202,$A80))) | AA80: =IF($A80="","",IF(N($X80)=0,"機器なし",IF(N($Y80)>0,"入荷待ち",IF(COUNTIFS(発注・納品!$B$3:$B$202,$A80,発注・納品!$N$3:$N$202,"")>0,"受入待ち","受入完了")))) | AB80: =IF($A80="","",COUNTIFS(現地作業!$A$3:$A$202,$A80,現地作業!$L$3:$L$202,"予定")) | AC80: =IF($A80="","",COUNTIFS(現地作業!$A$3:$A$202,$A80,現地作業!$L$3:$L$202,"完了")) | AD80: =IF(N($AB80)=0,"",IF(_xlfn.MINIFS(現地作業!$C$3:$C$202,現地作業!$A$3:$A$202,$A80,現地作業!$L$3:$L$202,"予定",現地作業!$C$3:$C$202,">="&TODAY())=0,"",_xlfn.MINIFS(現地作業!$C$3:$C$202,現地作業!$A$3:$A$202,$A80,現地作業!$L$3:$L$202,"予定",現地作業!$C$3:$C$202,">="&TODAY()))) | AF80: =IF($A80="","",SUM(月次工数計画!$G$85:$AD$85)) | AG80: =IF($A80="","",SUMIFS(工数明細!$G$3:$G$302,工数明細!$B$3:$B$302,$A80)) | AH80: =IF($AE80="","",$AE80-N($AG80)) | AI80: =IF(N($AE80)=0,"",$AG80/$AE80) | AJ80: =IF(N($AE80)=0,"",IF($AG80>$AE80,"超過",IF($AG80>=$AE80*0.9,"注意","適正")))
N81: =IF($J81="","",YEAR($J81)-IF(MONTH($J81)<マスタ!$B$4,1,0)) | O81: =IF($J81="","","Q"&(INT(MOD(MONTH($J81)-マスタ!$B$4+12,12)/3)+1)) | P81: =IF($L81="","",IF($M81<>"",$M81-$L81,IF(TODAY()>$L81,TODAY()-$L81,0))) | R81: =IF($Q81="","",$Q81*N($F81)) | T81: =IF($A81="","",SUMIFS(発注・納品!$H$3:$H$202,発注・納品!$B$3:$B$202,$A81)) | U81: =IF($Q81="","",N($S81)+N($T81)) | V81: =IF($Q81="","",$Q81-N($U81)) | W81: =IF(N($Q81)=0,"",$V81/$Q81) | X81: =IF($A81="","",COUNTIFS(発注・納品!$B$3:$B$202,$A81)) | Y81: =IF($A81="","",COUNTIFS(発注・納品!$B$3:$B$202,$A81,発注・納品!$M$3:$M$202,"")) | Z81: =IF(N($X81)=0,"",IF(_xlfn.MAXIFS(発注・納品!$M$3:$M$202,発注・納品!$B$3:$B$202,$A81)=0,"",_xlfn.MAXIFS(発注・納品!$M$3:$M$202,発注・納品!$B$3:$B$202,$A81))) | AA81: =IF($A81="","",IF(N($X81)=0,"機器なし",IF(N($Y81)>0,"入荷待ち",IF(COUNTIFS(発注・納品!$B$3:$B$202,$A81,発注・納品!$N$3:$N$202,"")>0,"受入待ち","受入完了")))) | AB81: =IF($A81="","",COUNTIFS(現地作業!$A$3:$A$202,$A81,現地作業!$L$3:$L$202,"予定")) | AC81: =IF($A81="","",COUNTIFS(現地作業!$A$3:$A$202,$A81,現地作業!$L$3:$L$202,"完了")) | AD81: =IF(N($AB81)=0,"",IF(_xlfn.MINIFS(現地作業!$C$3:$C$202,現地作業!$A$3:$A$202,$A81,現地作業!$L$3:$L$202,"予定",現地作業!$C$3:$C$202,">="&TODAY())=0,"",_xlfn.MINIFS(現地作業!$C$3:$C$202,現地作業!$A$3:$A$202,$A81,現地作業!$L$3:$L$202,"予定",現地作業!$C$3:$C$202,">="&TODAY()))) | AF81: =IF($A81="","",SUM(月次工数計画!$G$86:$AD$86)) | AG81: =IF($A81="","",SUMIFS(工数明細!$G$3:$G$302,工数明細!$B$3:$B$302,$A81)) | AH81: =IF($AE81="","",$AE81-N($AG81)) | AI81: =IF(N($AE81)=0,"",$AG81/$AE81) | AJ81: =IF(N($AE81)=0,"",IF($AG81>$AE81,"超過",IF($AG81>=$AE81*0.9,"注意","適正")))
N82: =IF($J82="","",YEAR($J82)-IF(MONTH($J82)<マスタ!$B$4,1,0)) | O82: =IF($J82="","","Q"&(INT(MOD(MONTH($J82)-マスタ!$B$4+12,12)/3)+1)) | P82: =IF($L82="","",IF($M82<>"",$M82-$L82,IF(TODAY()>$L82,TODAY()-$L82,0))) | R82: =IF($Q82="","",$Q82*N($F82)) | T82: =IF($A82="","",SUMIFS(発注・納品!$H$3:$H$202,発注・納品!$B$3:$B$202,$A82)) | U82: =IF($Q82="","",N($S82)+N($T82)) | V82: =IF($Q82="","",$Q82-N($U82)) | W82: =IF(N($Q82)=0,"",$V82/$Q82) | X82: =IF($A82="","",COUNTIFS(発注・納品!$B$3:$B$202,$A82)) | Y82: =IF($A82="","",COUNTIFS(発注・納品!$B$3:$B$202,$A82,発注・納品!$M$3:$M$202,"")) | Z82: =IF(N($X82)=0,"",IF(_xlfn.MAXIFS(発注・納品!$M$3:$M$202,発注・納品!$B$3:$B$202,$A82)=0,"",_xlfn.MAXIFS(発注・納品!$M$3:$M$202,発注・納品!$B$3:$B$202,$A82))) | AA82: =IF($A82="","",IF(N($X82)=0,"機器なし",IF(N($Y82)>0,"入荷待ち",IF(COUNTIFS(発注・納品!$B$3:$B$202,$A82,発注・納品!$N$3:$N$202,"")>0,"受入待ち","受入完了")))) | AB82: =IF($A82="","",COUNTIFS(現地作業!$A$3:$A$202,$A82,現地作業!$L$3:$L$202,"予定")) | AC82: =IF($A82="","",COUNTIFS(現地作業!$A$3:$A$202,$A82,現地作業!$L$3:$L$202,"完了")) | AD82: =IF(N($AB82)=0,"",IF(_xlfn.MINIFS(現地作業!$C$3:$C$202,現地作業!$A$3:$A$202,$A82,現地作業!$L$3:$L$202,"予定",現地作業!$C$3:$C$202,">="&TODAY())=0,"",_xlfn.MINIFS(現地作業!$C$3:$C$202,現地作業!$A$3:$A$202,$A82,現地作業!$L$3:$L$202,"予定",現地作業!$C$3:$C$202,">="&TODAY()))) | AF82: =IF($A82="","",SUM(月次工数計画!$G$87:$AD$87)) | AG82: =IF($A82="","",SUMIFS(工数明細!$G$3:$G$302,工数明細!$B$3:$B$302,$A82)) | AH82: =IF($AE82="","",$AE82-N($AG82)) | AI82: =IF(N($AE82)=0,"",$AG82/$AE82) | AJ82: =IF(N($AE82)=0,"",IF($AG82>$AE82,"超過",IF($AG82>=$AE82*0.9,"注意","適正")))
N83: =IF($J83="","",YEAR($J83)-IF(MONTH($J83)<マスタ!$B$4,1,0)) | O83: =IF($J83="","","Q"&(INT(MOD(MONTH($J83)-マスタ!$B$4+12,12)/3)+1)) | P83: =IF($L83="","",IF($M83<>"",$M83-$L83,IF(TODAY()>$L83,TODAY()-$L83,0))) | R83: =IF($Q83="","",$Q83*N($F83)) | T83: =IF($A83="","",SUMIFS(発注・納品!$H$3:$H$202,発注・納品!$B$3:$B$202,$A83)) | U83: =IF($Q83="","",N($S83)+N($T83)) | V83: =IF($Q83="","",$Q83-N($U83)) | W83: =IF(N($Q83)=0,"",$V83/$Q83) | X83: =IF($A83="","",COUNTIFS(発注・納品!$B$3:$B$202,$A83)) | Y83: =IF($A83="","",COUNTIFS(発注・納品!$B$3:$B$202,$A83,発注・納品!$M$3:$M$202,"")) | Z83: =IF(N($X83)=0,"",IF(_xlfn.MAXIFS(発注・納品!$M$3:$M$202,発注・納品!$B$3:$B$202,$A83)=0,"",_xlfn.MAXIFS(発注・納品!$M$3:$M$202,発注・納品!$B$3:$B$202,$A83))) | AA83: =IF($A83="","",IF(N($X83)=0,"機器なし",IF(N($Y83)>0,"入荷待ち",IF(COUNTIFS(発注・納品!$B$3:$B$202,$A83,発注・納品!$N$3:$N$202,"")>0,"受入待ち","受入完了")))) | AB83: =IF($A83="","",COUNTIFS(現地作業!$A$3:$A$202,$A83,現地作業!$L$3:$L$202,"予定")) | AC83: =IF($A83="","",COUNTIFS(現地作業!$A$3:$A$202,$A83,現地作業!$L$3:$L$202,"完了")) | AD83: =IF(N($AB83)=0,"",IF(_xlfn.MINIFS(現地作業!$C$3:$C$202,現地作業!$A$3:$A$202,$A83,現地作業!$L$3:$L$202,"予定",現地作業!$C$3:$C$202,">="&TODAY())=0,"",_xlfn.MINIFS(現地作業!$C$3:$C$202,現地作業!$A$3:$A$202,$A83,現地作業!$L$3:$L$202,"予定",現地作業!$C$3:$C$202,">="&TODAY()))) | AF83: =IF($A83="","",SUM(月次工数計画!$G$88:$AD$88)) | AG83: =IF($A83="","",SUMIFS(工数明細!$G$3:$G$302,工数明細!$B$3:$B$302,$A83)) | AH83: =IF($AE83="","",$AE83-N($AG83)) | AI83: =IF(N($AE83)=0,"",$AG83/$AE83) | AJ83: =IF(N($AE83)=0,"",IF($AG83>$AE83,"超過",IF($AG83>=$AE83*0.9,"注意","適正")))
N84: =IF($J84="","",YEAR($J84)-IF(MONTH($J84)<マスタ!$B$4,1,0)) | O84: =IF($J84="","","Q"&(INT(MOD(MONTH($J84)-マスタ!$B$4+12,12)/3)+1)) | P84: =IF($L84="","",IF($M84<>"",$M84-$L84,IF(TODAY()>$L84,TODAY()-$L84,0))) | R84: =IF($Q84="","",$Q84*N($F84)) | T84: =IF($A84="","",SUMIFS(発注・納品!$H$3:$H$202,発注・納品!$B$3:$B$202,$A84)) | U84: =IF($Q84="","",N($S84)+N($T84)) | V84: =IF($Q84="","",$Q84-N($U84)) | W84: =IF(N($Q84)=0,"",$V84/$Q84) | X84: =IF($A84="","",COUNTIFS(発注・納品!$B$3:$B$202,$A84)) | Y84: =IF($A84="","",COUNTIFS(発注・納品!$B$3:$B$202,$A84,発注・納品!$M$3:$M$202,"")) | Z84: =IF(N($X84)=0,"",IF(_xlfn.MAXIFS(発注・納品!$M$3:$M$202,発注・納品!$B$3:$B$202,$A84)=0,"",_xlfn.MAXIFS(発注・納品!$M$3:$M$202,発注・納品!$B$3:$B$202,$A84))) | AA84: =IF($A84="","",IF(N($X84)=0,"機器なし",IF(N($Y84)>0,"入荷待ち",IF(COUNTIFS(発注・納品!$B$3:$B$202,$A84,発注・納品!$N$3:$N$202,"")>0,"受入待ち","受入完了")))) | AB84: =IF($A84="","",COUNTIFS(現地作業!$A$3:$A$202,$A84,現地作業!$L$3:$L$202,"予定")) | AC84: =IF($A84="","",COUNTIFS(現地作業!$A$3:$A$202,$A84,現地作業!$L$3:$L$202,"完了")) | AD84: =IF(N($AB84)=0,"",IF(_xlfn.MINIFS(現地作業!$C$3:$C$202,現地作業!$A$3:$A$202,$A84,現地作業!$L$3:$L$202,"予定",現地作業!$C$3:$C$202,">="&TODAY())=0,"",_xlfn.MINIFS(現地作業!$C$3:$C$202,現地作業!$A$3:$A$202,$A84,現地作業!$L$3:$L$202,"予定",現地作業!$C$3:$C$202,">="&TODAY()))) | AF84: =IF($A84="","",SUM(月次工数計画!$G$89:$AD$89)) | AG84: =IF($A84="","",SUMIFS(工数明細!$G$3:$G$302,工数明細!$B$3:$B$302,$A84)) | AH84: =IF($AE84="","",$AE84-N($AG84)) | AI84: =IF(N($AE84)=0,"",$AG84/$AE84) | AJ84: =IF(N($AE84)=0,"",IF($AG84>$AE84,"超過",IF($AG84>=$AE84*0.9,"注意","適正")))
N85: =IF($J85="","",YEAR($J85)-IF(MONTH($J85)<マスタ!$B$4,1,0)) | O85: =IF($J85="","","Q"&(INT(MOD(MONTH($J85)-マスタ!$B$4+12,12)/3)+1)) | P85: =IF($L85="","",IF($M85<>"",$M85-$L85,IF(TODAY()>$L85,TODAY()-$L85,0))) | R85: =IF($Q85="","",$Q85*N($F85)) | T85: =IF($A85="","",SUMIFS(発注・納品!$H$3:$H$202,発注・納品!$B$3:$B$202,$A85)) | U85: =IF($Q85="","",N($S85)+N($T85)) | V85: =IF($Q85="","",$Q85-N($U85)) | W85: =IF(N($Q85)=0,"",$V85/$Q85) | X85: =IF($A85="","",COUNTIFS(発注・納品!$B$3:$B$202,$A85)) | Y85: =IF($A85="","",COUNTIFS(発注・納品!$B$3:$B$202,$A85,発注・納品!$M$3:$M$202,"")) | Z85: =IF(N($X85)=0,"",IF(_xlfn.MAXIFS(発注・納品!$M$3:$M$202,発注・納品!$B$3:$B$202,$A85)=0,"",_xlfn.MAXIFS(発注・納品!$M$3:$M$202,発注・納品!$B$3:$B$202,$A85))) | AA85: =IF($A85="","",IF(N($X85)=0,"機器なし",IF(N($Y85)>0,"入荷待ち",IF(COUNTIFS(発注・納品!$B$3:$B$202,$A85,発注・納品!$N$3:$N$202,"")>0,"受入待ち","受入完了")))) | AB85: =IF($A85="","",COUNTIFS(現地作業!$A$3:$A$202,$A85,現地作業!$L$3:$L$202,"予定")) | AC85: =IF($A85="","",COUNTIFS(現地作業!$A$3:$A$202,$A85,現地作業!$L$3:$L$202,"完了")) | AD85: =IF(N($AB85)=0,"",IF(_xlfn.MINIFS(現地作業!$C$3:$C$202,現地作業!$A$3:$A$202,$A85,現地作業!$L$3:$L$202,"予定",現地作業!$C$3:$C$202,">="&TODAY())=0,"",_xlfn.MINIFS(現地作業!$C$3:$C$202,現地作業!$A$3:$A$202,$A85,現地作業!$L$3:$L$202,"予定",現地作業!$C$3:$C$202,">="&TODAY()))) | AF85: =IF($A85="","",SUM(月次工数計画!$G$90:$AD$90)) | AG85: =IF($A85="","",SUMIFS(工数明細!$G$3:$G$302,工数明細!$B$3:$B$302,$A85)) | AH85: =IF($AE85="","",$AE85-N($AG85)) | AI85: =IF(N($AE85)=0,"",$AG85/$AE85) | AJ85: =IF(N($AE85)=0,"",IF($AG85>$AE85,"超過",IF($AG85>=$AE85*0.9,"注意","適正")))
N86: =IF($J86="","",YEAR($J86)-IF(MONTH($J86)<マスタ!$B$4,1,0)) | O86: =IF($J86="","","Q"&(INT(MOD(MONTH($J86)-マスタ!$B$4+12,12)/3)+1)) | P86: =IF($L86="","",IF($M86<>"",$M86-$L86,IF(TODAY()>$L86,TODAY()-$L86,0))) | R86: =IF($Q86="","",$Q86*N($F86)) | T86: =IF($A86="","",SUMIFS(発注・納品!$H$3:$H$202,発注・納品!$B$3:$B$202,$A86)) | U86: =IF($Q86="","",N($S86)+N($T86)) | V86: =IF($Q86="","",$Q86-N($U86)) | W86: =IF(N($Q86)=0,"",$V86/$Q86) | X86: =IF($A86="","",COUNTIFS(発注・納品!$B$3:$B$202,$A86)) | Y86: =IF($A86="","",COUNTIFS(発注・納品!$B$3:$B$202,$A86,発注・納品!$M$3:$M$202,"")) | Z86: =IF(N($X86)=0,"",IF(_xlfn.MAXIFS(発注・納品!$M$3:$M$202,発注・納品!$B$3:$B$202,$A86)=0,"",_xlfn.MAXIFS(発注・納品!$M$3:$M$202,発注・納品!$B$3:$B$202,$A86))) | AA86: =IF($A86="","",IF(N($X86)=0,"機器なし",IF(N($Y86)>0,"入荷待ち",IF(COUNTIFS(発注・納品!$B$3:$B$202,$A86,発注・納品!$N$3:$N$202,"")>0,"受入待ち","受入完了")))) | AB86: =IF($A86="","",COUNTIFS(現地作業!$A$3:$A$202,$A86,現地作業!$L$3:$L$202,"予定")) | AC86: =IF($A86="","",COUNTIFS(現地作業!$A$3:$A$202,$A86,現地作業!$L$3:$L$202,"完了")) | AD86: =IF(N($AB86)=0,"",IF(_xlfn.MINIFS(現地作業!$C$3:$C$202,現地作業!$A$3:$A$202,$A86,現地作業!$L$3:$L$202,"予定",現地作業!$C$3:$C$202,">="&TODAY())=0,"",_xlfn.MINIFS(現地作業!$C$3:$C$202,現地作業!$A$3:$A$202,$A86,現地作業!$L$3:$L$202,"予定",現地作業!$C$3:$C$202,">="&TODAY()))) | AF86: =IF($A86="","",SUM(月次工数計画!$G$91:$AD$91)) | AG86: =IF($A86="","",SUMIFS(工数明細!$G$3:$G$302,工数明細!$B$3:$B$302,$A86)) | AH86: =IF($AE86="","",$AE86-N($AG86)) | AI86: =IF(N($AE86)=0,"",$AG86/$AE86) | AJ86: =IF(N($AE86)=0,"",IF($AG86>$AE86,"超過",IF($AG86>=$AE86*0.9,"注意","適正")))
N87: =IF($J87="","",YEAR($J87)-IF(MONTH($J87)<マスタ!$B$4,1,0)) | O87: =IF($J87="","","Q"&(INT(MOD(MONTH($J87)-マスタ!$B$4+12,12)/3)+1)) | P87: =IF($L87="","",IF($M87<>"",$M87-$L87,IF(TODAY()>$L87,TODAY()-$L87,0))) | R87: =IF($Q87="","",$Q87*N($F87)) | T87: =IF($A87="","",SUMIFS(発注・納品!$H$3:$H$202,発注・納品!$B$3:$B$202,$A87)) | U87: =IF($Q87="","",N($S87)+N($T87)) | V87: =IF($Q87="","",$Q87-N($U87)) | W87: =IF(N($Q87)=0,"",$V87/$Q87) | X87: =IF($A87="","",COUNTIFS(発注・納品!$B$3:$B$202,$A87)) | Y87: =IF($A87="","",COUNTIFS(発注・納品!$B$3:$B$202,$A87,発注・納品!$M$3:$M$202,"")) | Z87: =IF(N($X87)=0,"",IF(_xlfn.MAXIFS(発注・納品!$M$3:$M$202,発注・納品!$B$3:$B$202,$A87)=0,"",_xlfn.MAXIFS(発注・納品!$M$3:$M$202,発注・納品!$B$3:$B$202,$A87))) | AA87: =IF($A87="","",IF(N($X87)=0,"機器なし",IF(N($Y87)>0,"入荷待ち",IF(COUNTIFS(発注・納品!$B$3:$B$202,$A87,発注・納品!$N$3:$N$202,"")>0,"受入待ち","受入完了")))) | AB87: =IF($A87="","",COUNTIFS(現地作業!$A$3:$A$202,$A87,現地作業!$L$3:$L$202,"予定")) | AC87: =IF($A87="","",COUNTIFS(現地作業!$A$3:$A$202,$A87,現地作業!$L$3:$L$202,"完了")) | AD87: =IF(N($AB87)=0,"",IF(_xlfn.MINIFS(現地作業!$C$3:$C$202,現地作業!$A$3:$A$202,$A87,現地作業!$L$3:$L$202,"予定",現地作業!$C$3:$C$202,">="&TODAY())=0,"",_xlfn.MINIFS(現地作業!$C$3:$C$202,現地作業!$A$3:$A$202,$A87,現地作業!$L$3:$L$202,"予定",現地作業!$C$3:$C$202,">="&TODAY()))) | AF87: =IF($A87="","",SUM(月次工数計画!$G$92:$AD$92)) | AG87: =IF($A87="","",SUMIFS(工数明細!$G$3:$G$302,工数明細!$B$3:$B$302,$A87)) | AH87: =IF($AE87="","",$AE87-N($AG87)) | AI87: =IF(N($AE87)=0,"",$AG87/$AE87) | AJ87: =IF(N($AE87)=0,"",IF($AG87>$AE87,"超過",IF($AG87>=$AE87*0.9,"注意","適正")))
N88: =IF($J88="","",YEAR($J88)-IF(MONTH($J88)<マスタ!$B$4,1,0)) | O88: =IF($J88="","","Q"&(INT(MOD(MONTH($J88)-マスタ!$B$4+12,12)/3)+1)) | P88: =IF($L88="","",IF($M88<>"",$M88-$L88,IF(TODAY()>$L88,TODAY()-$L88,0))) | R88: =IF($Q88="","",$Q88*N($F88)) | T88: =IF($A88="","",SUMIFS(発注・納品!$H$3:$H$202,発注・納品!$B$3:$B$202,$A88)) | U88: =IF($Q88="","",N($S88)+N($T88)) | V88: =IF($Q88="","",$Q88-N($U88)) | W88: =IF(N($Q88)=0,"",$V88/$Q88) | X88: =IF($A88="","",COUNTIFS(発注・納品!$B$3:$B$202,$A88)) | Y88: =IF($A88="","",COUNTIFS(発注・納品!$B$3:$B$202,$A88,発注・納品!$M$3:$M$202,"")) | Z88: =IF(N($X88)=0,"",IF(_xlfn.MAXIFS(発注・納品!$M$3:$M$202,発注・納品!$B$3:$B$202,$A88)=0,"",_xlfn.MAXIFS(発注・納品!$M$3:$M$202,発注・納品!$B$3:$B$202,$A88))) | AA88: =IF($A88="","",IF(N($X88)=0,"機器なし",IF(N($Y88)>0,"入荷待ち",IF(COUNTIFS(発注・納品!$B$3:$B$202,$A88,発注・納品!$N$3:$N$202,"")>0,"受入待ち","受入完了")))) | AB88: =IF($A88="","",COUNTIFS(現地作業!$A$3:$A$202,$A88,現地作業!$L$3:$L$202,"予定")) | AC88: =IF($A88="","",COUNTIFS(現地作業!$A$3:$A$202,$A88,現地作業!$L$3:$L$202,"完了")) | AD88: =IF(N($AB88)=0,"",IF(_xlfn.MINIFS(現地作業!$C$3:$C$202,現地作業!$A$3:$A$202,$A88,現地作業!$L$3:$L$202,"予定",現地作業!$C$3:$C$202,">="&TODAY())=0,"",_xlfn.MINIFS(現地作業!$C$3:$C$202,現地作業!$A$3:$A$202,$A88,現地作業!$L$3:$L$202,"予定",現地作業!$C$3:$C$202,">="&TODAY()))) | AF88: =IF($A88="","",SUM(月次工数計画!$G$93:$AD$93)) | AG88: =IF($A88="","",SUMIFS(工数明細!$G$3:$G$302,工数明細!$B$3:$B$302,$A88)) | AH88: =IF($AE88="","",$AE88-N($AG88)) | AI88: =IF(N($AE88)=0,"",$AG88/$AE88) | AJ88: =IF(N($AE88)=0,"",IF($AG88>$AE88,"超過",IF($AG88>=$AE88*0.9,"注意","適正")))
N89: =IF($J89="","",YEAR($J89)-IF(MONTH($J89)<マスタ!$B$4,1,0)) | O89: =IF($J89="","","Q"&(INT(MOD(MONTH($J89)-マスタ!$B$4+12,12)/3)+1)) | P89: =IF($L89="","",IF($M89<>"",$M89-$L89,IF(TODAY()>$L89,TODAY()-$L89,0))) | R89: =IF($Q89="","",$Q89*N($F89)) | T89: =IF($A89="","",SUMIFS(発注・納品!$H$3:$H$202,発注・納品!$B$3:$B$202,$A89)) | U89: =IF($Q89="","",N($S89)+N($T89)) | V89: =IF($Q89="","",$Q89-N($U89)) | W89: =IF(N($Q89)=0,"",$V89/$Q89) | X89: =IF($A89="","",COUNTIFS(発注・納品!$B$3:$B$202,$A89)) | Y89: =IF($A89="","",COUNTIFS(発注・納品!$B$3:$B$202,$A89,発注・納品!$M$3:$M$202,"")) | Z89: =IF(N($X89)=0,"",IF(_xlfn.MAXIFS(発注・納品!$M$3:$M$202,発注・納品!$B$3:$B$202,$A89)=0,"",_xlfn.MAXIFS(発注・納品!$M$3:$M$202,発注・納品!$B$3:$B$202,$A89))) | AA89: =IF($A89="","",IF(N($X89)=0,"機器なし",IF(N($Y89)>0,"入荷待ち",IF(COUNTIFS(発注・納品!$B$3:$B$202,$A89,発注・納品!$N$3:$N$202,"")>0,"受入待ち","受入完了")))) | AB89: =IF($A89="","",COUNTIFS(現地作業!$A$3:$A$202,$A89,現地作業!$L$3:$L$202,"予定")) | AC89: =IF($A89="","",COUNTIFS(現地作業!$A$3:$A$202,$A89,現地作業!$L$3:$L$202,"完了")) | AD89: =IF(N($AB89)=0,"",IF(_xlfn.MINIFS(現地作業!$C$3:$C$202,現地作業!$A$3:$A$202,$A89,現地作業!$L$3:$L$202,"予定",現地作業!$C$3:$C$202,">="&TODAY())=0,"",_xlfn.MINIFS(現地作業!$C$3:$C$202,現地作業!$A$3:$A$202,$A89,現地作業!$L$3:$L$202,"予定",現地作業!$C$3:$C$202,">="&TODAY()))) | AF89: =IF($A89="","",SUM(月次工数計画!$G$94:$AD$94)) | AG89: =IF($A89="","",SUMIFS(工数明細!$G$3:$G$302,工数明細!$B$3:$B$302,$A89)) | AH89: =IF($AE89="","",$AE89-N($AG89)) | AI89: =IF(N($AE89)=0,"",$AG89/$AE89) | AJ89: =IF(N($AE89)=0,"",IF($AG89>$AE89,"超過",IF($AG89>=$AE89*0.9,"注意","適正")))
N90: =IF($J90="","",YEAR($J90)-IF(MONTH($J90)<マスタ!$B$4,1,0)) | O90: =IF($J90="","","Q"&(INT(MOD(MONTH($J90)-マスタ!$B$4+12,12)/3)+1)) | P90: =IF($L90="","",IF($M90<>"",$M90-$L90,IF(TODAY()>$L90,TODAY()-$L90,0))) | R90: =IF($Q90="","",$Q90*N($F90)) | T90: =IF($A90="","",SUMIFS(発注・納品!$H$3:$H$202,発注・納品!$B$3:$B$202,$A90)) | U90: =IF($Q90="","",N($S90)+N($T90)) | V90: =IF($Q90="","",$Q90-N($U90)) | W90: =IF(N($Q90)=0,"",$V90/$Q90) | X90: =IF($A90="","",COUNTIFS(発注・納品!$B$3:$B$202,$A90)) | Y90: =IF($A90="","",COUNTIFS(発注・納品!$B$3:$B$202,$A90,発注・納品!$M$3:$M$202,"")) | Z90: =IF(N($X90)=0,"",IF(_xlfn.MAXIFS(発注・納品!$M$3:$M$202,発注・納品!$B$3:$B$202,$A90)=0,"",_xlfn.MAXIFS(発注・納品!$M$3:$M$202,発注・納品!$B$3:$B$202,$A90))) | AA90: =IF($A90="","",IF(N($X90)=0,"機器なし",IF(N($Y90)>0,"入荷待ち",IF(COUNTIFS(発注・納品!$B$3:$B$202,$A90,発注・納品!$N$3:$N$202,"")>0,"受入待ち","受入完了")))) | AB90: =IF($A90="","",COUNTIFS(現地作業!$A$3:$A$202,$A90,現地作業!$L$3:$L$202,"予定")) | AC90: =IF($A90="","",COUNTIFS(現地作業!$A$3:$A$202,$A90,現地作業!$L$3:$L$202,"完了")) | AD90: =IF(N($AB90)=0,"",IF(_xlfn.MINIFS(現地作業!$C$3:$C$202,現地作業!$A$3:$A$202,$A90,現地作業!$L$3:$L$202,"予定",現地作業!$C$3:$C$202,">="&TODAY())=0,"",_xlfn.MINIFS(現地作業!$C$3:$C$202,現地作業!$A$3:$A$202,$A90,現地作業!$L$3:$L$202,"予定",現地作業!$C$3:$C$202,">="&TODAY()))) | AF90: =IF($A90="","",SUM(月次工数計画!$G$95:$AD$95)) | AG90: =IF($A90="","",SUMIFS(工数明細!$G$3:$G$302,工数明細!$B$3:$B$302,$A90)) | AH90: =IF($AE90="","",$AE90-N($AG90)) | AI90: =IF(N($AE90)=0,"",$AG90/$AE90) | AJ90: =IF(N($AE90)=0,"",IF($AG90>$AE90,"超過",IF($AG90>=$AE90*0.9,"注意","適正")))
N91: =IF($J91="","",YEAR($J91)-IF(MONTH($J91)<マスタ!$B$4,1,0)) | O91: =IF($J91="","","Q"&(INT(MOD(MONTH($J91)-マスタ!$B$4+12,12)/3)+1)) | P91: =IF($L91="","",IF($M91<>"",$M91-$L91,IF(TODAY()>$L91,TODAY()-$L91,0))) | R91: =IF($Q91="","",$Q91*N($F91)) | T91: =IF($A91="","",SUMIFS(発注・納品!$H$3:$H$202,発注・納品!$B$3:$B$202,$A91)) | U91: =IF($Q91="","",N($S91)+N($T91)) | V91: =IF($Q91="","",$Q91-N($U91)) | W91: =IF(N($Q91)=0,"",$V91/$Q91) | X91: =IF($A91="","",COUNTIFS(発注・納品!$B$3:$B$202,$A91)) | Y91: =IF($A91="","",COUNTIFS(発注・納品!$B$3:$B$202,$A91,発注・納品!$M$3:$M$202,"")) | Z91: =IF(N($X91)=0,"",IF(_xlfn.MAXIFS(発注・納品!$M$3:$M$202,発注・納品!$B$3:$B$202,$A91)=0,"",_xlfn.MAXIFS(発注・納品!$M$3:$M$202,発注・納品!$B$3:$B$202,$A91))) | AA91: =IF($A91="","",IF(N($X91)=0,"機器なし",IF(N($Y91)>0,"入荷待ち",IF(COUNTIFS(発注・納品!$B$3:$B$202,$A91,発注・納品!$N$3:$N$202,"")>0,"受入待ち","受入完了")))) | AB91: =IF($A91="","",COUNTIFS(現地作業!$A$3:$A$202,$A91,現地作業!$L$3:$L$202,"予定")) | AC91: =IF($A91="","",COUNTIFS(現地作業!$A$3:$A$202,$A91,現地作業!$L$3:$L$202,"完了")) | AD91: =IF(N($AB91)=0,"",IF(_xlfn.MINIFS(現地作業!$C$3:$C$202,現地作業!$A$3:$A$202,$A91,現地作業!$L$3:$L$202,"予定",現地作業!$C$3:$C$202,">="&TODAY())=0,"",_xlfn.MINIFS(現地作業!$C$3:$C$202,現地作業!$A$3:$A$202,$A91,現地作業!$L$3:$L$202,"予定",現地作業!$C$3:$C$202,">="&TODAY()))) | AF91: =IF($A91="","",SUM(月次工数計画!$G$96:$AD$96)) | AG91: =IF($A91="","",SUMIFS(工数明細!$G$3:$G$302,工数明細!$B$3:$B$302,$A91)) | AH91: =IF($AE91="","",$AE91-N($AG91)) | AI91: =IF(N($AE91)=0,"",$AG91/$AE91) | AJ91: =IF(N($AE91)=0,"",IF($AG91>$AE91,"超過",IF($AG91>=$AE91*0.9,"注意","適正")))
N92: =IF($J92="","",YEAR($J92)-IF(MONTH($J92)<マスタ!$B$4,1,0)) | O92: =IF($J92="","","Q"&(INT(MOD(MONTH($J92)-マスタ!$B$4+12,12)/3)+1)) | P92: =IF($L92="","",IF($M92<>"",$M92-$L92,IF(TODAY()>$L92,TODAY()-$L92,0))) | R92: =IF($Q92="","",$Q92*N($F92)) | T92: =IF($A92="","",SUMIFS(発注・納品!$H$3:$H$202,発注・納品!$B$3:$B$202,$A92)) | U92: =IF($Q92="","",N($S92)+N($T92)) | V92: =IF($Q92="","",$Q92-N($U92)) | W92: =IF(N($Q92)=0,"",$V92/$Q92) | X92: =IF($A92="","",COUNTIFS(発注・納品!$B$3:$B$202,$A92)) | Y92: =IF($A92="","",COUNTIFS(発注・納品!$B$3:$B$202,$A92,発注・納品!$M$3:$M$202,"")) | Z92: =IF(N($X92)=0,"",IF(_xlfn.MAXIFS(発注・納品!$M$3:$M$202,発注・納品!$B$3:$B$202,$A92)=0,"",_xlfn.MAXIFS(発注・納品!$M$3:$M$202,発注・納品!$B$3:$B$202,$A92))) | AA92: =IF($A92="","",IF(N($X92)=0,"機器なし",IF(N($Y92)>0,"入荷待ち",IF(COUNTIFS(発注・納品!$B$3:$B$202,$A92,発注・納品!$N$3:$N$202,"")>0,"受入待ち","受入完了")))) | AB92: =IF($A92="","",COUNTIFS(現地作業!$A$3:$A$202,$A92,現地作業!$L$3:$L$202,"予定")) | AC92: =IF($A92="","",COUNTIFS(現地作業!$A$3:$A$202,$A92,現地作業!$L$3:$L$202,"完了")) | AD92: =IF(N($AB92)=0,"",IF(_xlfn.MINIFS(現地作業!$C$3:$C$202,現地作業!$A$3:$A$202,$A92,現地作業!$L$3:$L$202,"予定",現地作業!$C$3:$C$202,">="&TODAY())=0,"",_xlfn.MINIFS(現地作業!$C$3:$C$202,現地作業!$A$3:$A$202,$A92,現地作業!$L$3:$L$202,"予定",現地作業!$C$3:$C$202,">="&TODAY()))) | AF92: =IF($A92="","",SUM(月次工数計画!$G$97:$AD$97)) | AG92: =IF($A92="","",SUMIFS(工数明細!$G$3:$G$302,工数明細!$B$3:$B$302,$A92)) | AH92: =IF($AE92="","",$AE92-N($AG92)) | AI92: =IF(N($AE92)=0,"",$AG92/$AE92) | AJ92: =IF(N($AE92)=0,"",IF($AG92>$AE92,"超過",IF($AG92>=$AE92*0.9,"注意","適正")))
N93: =IF($J93="","",YEAR($J93)-IF(MONTH($J93)<マスタ!$B$4,1,0)) | O93: =IF($J93="","","Q"&(INT(MOD(MONTH($J93)-マスタ!$B$4+12,12)/3)+1)) | P93: =IF($L93="","",IF($M93<>"",$M93-$L93,IF(TODAY()>$L93,TODAY()-$L93,0))) | R93: =IF($Q93="","",$Q93*N($F93)) | T93: =IF($A93="","",SUMIFS(発注・納品!$H$3:$H$202,発注・納品!$B$3:$B$202,$A93)) | U93: =IF($Q93="","",N($S93)+N($T93)) | V93: =IF($Q93="","",$Q93-N($U93)) | W93: =IF(N($Q93)=0,"",$V93/$Q93) | X93: =IF($A93="","",COUNTIFS(発注・納品!$B$3:$B$202,$A93)) | Y93: =IF($A93="","",COUNTIFS(発注・納品!$B$3:$B$202,$A93,発注・納品!$M$3:$M$202,"")) | Z93: =IF(N($X93)=0,"",IF(_xlfn.MAXIFS(発注・納品!$M$3:$M$202,発注・納品!$B$3:$B$202,$A93)=0,"",_xlfn.MAXIFS(発注・納品!$M$3:$M$202,発注・納品!$B$3:$B$202,$A93))) | AA93: =IF($A93="","",IF(N($X93)=0,"機器なし",IF(N($Y93)>0,"入荷待ち",IF(COUNTIFS(発注・納品!$B$3:$B$202,$A93,発注・納品!$N$3:$N$202,"")>0,"受入待ち","受入完了")))) | AB93: =IF($A93="","",COUNTIFS(現地作業!$A$3:$A$202,$A93,現地作業!$L$3:$L$202,"予定")) | AC93: =IF($A93="","",COUNTIFS(現地作業!$A$3:$A$202,$A93,現地作業!$L$3:$L$202,"完了")) | AD93: =IF(N($AB93)=0,"",IF(_xlfn.MINIFS(現地作業!$C$3:$C$202,現地作業!$A$3:$A$202,$A93,現地作業!$L$3:$L$202,"予定",現地作業!$C$3:$C$202,">="&TODAY())=0,"",_xlfn.MINIFS(現地作業!$C$3:$C$202,現地作業!$A$3:$A$202,$A93,現地作業!$L$3:$L$202,"予定",現地作業!$C$3:$C$202,">="&TODAY()))) | AF93: =IF($A93="","",SUM(月次工数計画!$G$98:$AD$98)) | AG93: =IF($A93="","",SUMIFS(工数明細!$G$3:$G$302,工数明細!$B$3:$B$302,$A93)) | AH93: =IF($AE93="","",$AE93-N($AG93)) | AI93: =IF(N($AE93)=0,"",$AG93/$AE93) | AJ93: =IF(N($AE93)=0,"",IF($AG93>$AE93,"超過",IF($AG93>=$AE93*0.9,"注意","適正")))
N94: =IF($J94="","",YEAR($J94)-IF(MONTH($J94)<マスタ!$B$4,1,0)) | O94: =IF($J94="","","Q"&(INT(MOD(MONTH($J94)-マスタ!$B$4+12,12)/3)+1)) | P94: =IF($L94="","",IF($M94<>"",$M94-$L94,IF(TODAY()>$L94,TODAY()-$L94,0))) | R94: =IF($Q94="","",$Q94*N($F94)) | T94: =IF($A94="","",SUMIFS(発注・納品!$H$3:$H$202,発注・納品!$B$3:$B$202,$A94)) | U94: =IF($Q94="","",N($S94)+N($T94)) | V94: =IF($Q94="","",$Q94-N($U94)) | W94: =IF(N($Q94)=0,"",$V94/$Q94) | X94: =IF($A94="","",COUNTIFS(発注・納品!$B$3:$B$202,$A94)) | Y94: =IF($A94="","",COUNTIFS(発注・納品!$B$3:$B$202,$A94,発注・納品!$M$3:$M$202,"")) | Z94: =IF(N($X94)=0,"",IF(_xlfn.MAXIFS(発注・納品!$M$3:$M$202,発注・納品!$B$3:$B$202,$A94)=0,"",_xlfn.MAXIFS(発注・納品!$M$3:$M$202,発注・納品!$B$3:$B$202,$A94))) | AA94: =IF($A94="","",IF(N($X94)=0,"機器なし",IF(N($Y94)>0,"入荷待ち",IF(COUNTIFS(発注・納品!$B$3:$B$202,$A94,発注・納品!$N$3:$N$202,"")>0,"受入待ち","受入完了")))) | AB94: =IF($A94="","",COUNTIFS(現地作業!$A$3:$A$202,$A94,現地作業!$L$3:$L$202,"予定")) | AC94: =IF($A94="","",COUNTIFS(現地作業!$A$3:$A$202,$A94,現地作業!$L$3:$L$202,"完了")) | AD94: =IF(N($AB94)=0,"",IF(_xlfn.MINIFS(現地作業!$C$3:$C$202,現地作業!$A$3:$A$202,$A94,現地作業!$L$3:$L$202,"予定",現地作業!$C$3:$C$202,">="&TODAY())=0,"",_xlfn.MINIFS(現地作業!$C$3:$C$202,現地作業!$A$3:$A$202,$A94,現地作業!$L$3:$L$202,"予定",現地作業!$C$3:$C$202,">="&TODAY()))) | AF94: =IF($A94="","",SUM(月次工数計画!$G$99:$AD$99)) | AG94: =IF($A94="","",SUMIFS(工数明細!$G$3:$G$302,工数明細!$B$3:$B$302,$A94)) | AH94: =IF($AE94="","",$AE94-N($AG94)) | AI94: =IF(N($AE94)=0,"",$AG94/$AE94) | AJ94: =IF(N($AE94)=0,"",IF($AG94>$AE94,"超過",IF($AG94>=$AE94*0.9,"注意","適正")))
N95: =IF($J95="","",YEAR($J95)-IF(MONTH($J95)<マスタ!$B$4,1,0)) | O95: =IF($J95="","","Q"&(INT(MOD(MONTH($J95)-マスタ!$B$4+12,12)/3)+1)) | P95: =IF($L95="","",IF($M95<>"",$M95-$L95,IF(TODAY()>$L95,TODAY()-$L95,0))) | R95: =IF($Q95="","",$Q95*N($F95)) | T95: =IF($A95="","",SUMIFS(発注・納品!$H$3:$H$202,発注・納品!$B$3:$B$202,$A95)) | U95: =IF($Q95="","",N($S95)+N($T95)) | V95: =IF($Q95="","",$Q95-N($U95)) | W95: =IF(N($Q95)=0,"",$V95/$Q95) | X95: =IF($A95="","",COUNTIFS(発注・納品!$B$3:$B$202,$A95)) | Y95: =IF($A95="","",COUNTIFS(発注・納品!$B$3:$B$202,$A95,発注・納品!$M$3:$M$202,"")) | Z95: =IF(N($X95)=0,"",IF(_xlfn.MAXIFS(発注・納品!$M$3:$M$202,発注・納品!$B$3:$B$202,$A95)=0,"",_xlfn.MAXIFS(発注・納品!$M$3:$M$202,発注・納品!$B$3:$B$202,$A95))) | AA95: =IF($A95="","",IF(N($X95)=0,"機器なし",IF(N($Y95)>0,"入荷待ち",IF(COUNTIFS(発注・納品!$B$3:$B$202,$A95,発注・納品!$N$3:$N$202,"")>0,"受入待ち","受入完了")))) | AB95: =IF($A95="","",COUNTIFS(現地作業!$A$3:$A$202,$A95,現地作業!$L$3:$L$202,"予定")) | AC95: =IF($A95="","",COUNTIFS(現地作業!$A$3:$A$202,$A95,現地作業!$L$3:$L$202,"完了")) | AD95: =IF(N($AB95)=0,"",IF(_xlfn.MINIFS(現地作業!$C$3:$C$202,現地作業!$A$3:$A$202,$A95,現地作業!$L$3:$L$202,"予定",現地作業!$C$3:$C$202,">="&TODAY())=0,"",_xlfn.MINIFS(現地作業!$C$3:$C$202,現地作業!$A$3:$A$202,$A95,現地作業!$L$3:$L$202,"予定",現地作業!$C$3:$C$202,">="&TODAY()))) | AF95: =IF($A95="","",SUM(月次工数計画!$G$100:$AD$100)) | AG95: =IF($A95="","",SUMIFS(工数明細!$G$3:$G$302,工数明細!$B$3:$B$302,$A95)) | AH95: =IF($AE95="","",$AE95-N($AG95)) | AI95: =IF(N($AE95)=0,"",$AG95/$AE95) | AJ95: =IF(N($AE95)=0,"",IF($AG95>$AE95,"超過",IF($AG95>=$AE95*0.9,"注意","適正")))
N96: =IF($J96="","",YEAR($J96)-IF(MONTH($J96)<マスタ!$B$4,1,0)) | O96: =IF($J96="","","Q"&(INT(MOD(MONTH($J96)-マスタ!$B$4+12,12)/3)+1)) | P96: =IF($L96="","",IF($M96<>"",$M96-$L96,IF(TODAY()>$L96,TODAY()-$L96,0))) | R96: =IF($Q96="","",$Q96*N($F96)) | T96: =IF($A96="","",SUMIFS(発注・納品!$H$3:$H$202,発注・納品!$B$3:$B$202,$A96)) | U96: =IF($Q96="","",N($S96)+N($T96)) | V96: =IF($Q96="","",$Q96-N($U96)) | W96: =IF(N($Q96)=0,"",$V96/$Q96) | X96: =IF($A96="","",COUNTIFS(発注・納品!$B$3:$B$202,$A96)) | Y96: =IF($A96="","",COUNTIFS(発注・納品!$B$3:$B$202,$A96,発注・納品!$M$3:$M$202,"")) | Z96: =IF(N($X96)=0,"",IF(_xlfn.MAXIFS(発注・納品!$M$3:$M$202,発注・納品!$B$3:$B$202,$A96)=0,"",_xlfn.MAXIFS(発注・納品!$M$3:$M$202,発注・納品!$B$3:$B$202,$A96))) | AA96: =IF($A96="","",IF(N($X96)=0,"機器なし",IF(N($Y96)>0,"入荷待ち",IF(COUNTIFS(発注・納品!$B$3:$B$202,$A96,発注・納品!$N$3:$N$202,"")>0,"受入待ち","受入完了")))) | AB96: =IF($A96="","",COUNTIFS(現地作業!$A$3:$A$202,$A96,現地作業!$L$3:$L$202,"予定")) | AC96: =IF($A96="","",COUNTIFS(現地作業!$A$3:$A$202,$A96,現地作業!$L$3:$L$202,"完了")) | AD96: =IF(N($AB96)=0,"",IF(_xlfn.MINIFS(現地作業!$C$3:$C$202,現地作業!$A$3:$A$202,$A96,現地作業!$L$3:$L$202,"予定",現地作業!$C$3:$C$202,">="&TODAY())=0,"",_xlfn.MINIFS(現地作業!$C$3:$C$202,現地作業!$A$3:$A$202,$A96,現地作業!$L$3:$L$202,"予定",現地作業!$C$3:$C$202,">="&TODAY()))) | AF96: =IF($A96="","",SUM(月次工数計画!$G$101:$AD$101)) | AG96: =IF($A96="","",SUMIFS(工数明細!$G$3:$G$302,工数明細!$B$3:$B$302,$A96)) | AH96: =IF($AE96="","",$AE96-N($AG96)) | AI96: =IF(N($AE96)=0,"",$AG96/$AE96) | AJ96: =IF(N($AE96)=0,"",IF($AG96>$AE96,"超過",IF($AG96>=$AE96*0.9,"注意","適正")))
N97: =IF($J97="","",YEAR($J97)-IF(MONTH($J97)<マスタ!$B$4,1,0)) | O97: =IF($J97="","","Q"&(INT(MOD(MONTH($J97)-マスタ!$B$4+12,12)/3)+1)) | P97: =IF($L97="","",IF($M97<>"",$M97-$L97,IF(TODAY()>$L97,TODAY()-$L97,0))) | R97: =IF($Q97="","",$Q97*N($F97)) | T97: =IF($A97="","",SUMIFS(発注・納品!$H$3:$H$202,発注・納品!$B$3:$B$202,$A97)) | U97: =IF($Q97="","",N($S97)+N($T97)) | V97: =IF($Q97="","",$Q97-N($U97)) | W97: =IF(N($Q97)=0,"",$V97/$Q97) | X97: =IF($A97="","",COUNTIFS(発注・納品!$B$3:$B$202,$A97)) | Y97: =IF($A97="","",COUNTIFS(発注・納品!$B$3:$B$202,$A97,発注・納品!$M$3:$M$202,"")) | Z97: =IF(N($X97)=0,"",IF(_xlfn.MAXIFS(発注・納品!$M$3:$M$202,発注・納品!$B$3:$B$202,$A97)=0,"",_xlfn.MAXIFS(発注・納品!$M$3:$M$202,発注・納品!$B$3:$B$202,$A97))) | AA97: =IF($A97="","",IF(N($X97)=0,"機器なし",IF(N($Y97)>0,"入荷待ち",IF(COUNTIFS(発注・納品!$B$3:$B$202,$A97,発注・納品!$N$3:$N$202,"")>0,"受入待ち","受入完了")))) | AB97: =IF($A97="","",COUNTIFS(現地作業!$A$3:$A$202,$A97,現地作業!$L$3:$L$202,"予定")) | AC97: =IF($A97="","",COUNTIFS(現地作業!$A$3:$A$202,$A97,現地作業!$L$3:$L$202,"完了")) | AD97: =IF(N($AB97)=0,"",IF(_xlfn.MINIFS(現地作業!$C$3:$C$202,現地作業!$A$3:$A$202,$A97,現地作業!$L$3:$L$202,"予定",現地作業!$C$3:$C$202,">="&TODAY())=0,"",_xlfn.MINIFS(現地作業!$C$3:$C$202,現地作業!$A$3:$A$202,$A97,現地作業!$L$3:$L$202,"予定",現地作業!$C$3:$C$202,">="&TODAY()))) | AF97: =IF($A97="","",SUM(月次工数計画!$G$102:$AD$102)) | AG97: =IF($A97="","",SUMIFS(工数明細!$G$3:$G$302,工数明細!$B$3:$B$302,$A97)) | AH97: =IF($AE97="","",$AE97-N($AG97)) | AI97: =IF(N($AE97)=0,"",$AG97/$AE97) | AJ97: =IF(N($AE97)=0,"",IF($AG97>$AE97,"超過",IF($AG97>=$AE97*0.9,"注意","適正")))
N98: =IF($J98="","",YEAR($J98)-IF(MONTH($J98)<マスタ!$B$4,1,0)) | O98: =IF($J98="","","Q"&(INT(MOD(MONTH($J98)-マスタ!$B$4+12,12)/3)+1)) | P98: =IF($L98="","",IF($M98<>"",$M98-$L98,IF(TODAY()>$L98,TODAY()-$L98,0))) | R98: =IF($Q98="","",$Q98*N($F98)) | T98: =IF($A98="","",SUMIFS(発注・納品!$H$3:$H$202,発注・納品!$B$3:$B$202,$A98)) | U98: =IF($Q98="","",N($S98)+N($T98)) | V98: =IF($Q98="","",$Q98-N($U98)) | W98: =IF(N($Q98)=0,"",$V98/$Q98) | X98: =IF($A98="","",COUNTIFS(発注・納品!$B$3:$B$202,$A98)) | Y98: =IF($A98="","",COUNTIFS(発注・納品!$B$3:$B$202,$A98,発注・納品!$M$3:$M$202,"")) | Z98: =IF(N($X98)=0,"",IF(_xlfn.MAXIFS(発注・納品!$M$3:$M$202,発注・納品!$B$3:$B$202,$A98)=0,"",_xlfn.MAXIFS(発注・納品!$M$3:$M$202,発注・納品!$B$3:$B$202,$A98))) | AA98: =IF($A98="","",IF(N($X98)=0,"機器なし",IF(N($Y98)>0,"入荷待ち",IF(COUNTIFS(発注・納品!$B$3:$B$202,$A98,発注・納品!$N$3:$N$202,"")>0,"受入待ち","受入完了")))) | AB98: =IF($A98="","",COUNTIFS(現地作業!$A$3:$A$202,$A98,現地作業!$L$3:$L$202,"予定")) | AC98: =IF($A98="","",COUNTIFS(現地作業!$A$3:$A$202,$A98,現地作業!$L$3:$L$202,"完了")) | AD98: =IF(N($AB98)=0,"",IF(_xlfn.MINIFS(現地作業!$C$3:$C$202,現地作業!$A$3:$A$202,$A98,現地作業!$L$3:$L$202,"予定",現地作業!$C$3:$C$202,">="&TODAY())=0,"",_xlfn.MINIFS(現地作業!$C$3:$C$202,現地作業!$A$3:$A$202,$A98,現地作業!$L$3:$L$202,"予定",現地作業!$C$3:$C$202,">="&TODAY()))) | AF98: =IF($A98="","",SUM(月次工数計画!$G$103:$AD$103)) | AG98: =IF($A98="","",SUMIFS(工数明細!$G$3:$G$302,工数明細!$B$3:$B$302,$A98)) | AH98: =IF($AE98="","",$AE98-N($AG98)) | AI98: =IF(N($AE98)=0,"",$AG98/$AE98) | AJ98: =IF(N($AE98)=0,"",IF($AG98>$AE98,"超過",IF($AG98>=$AE98*0.9,"注意","適正")))
N99: =IF($J99="","",YEAR($J99)-IF(MONTH($J99)<マスタ!$B$4,1,0)) | O99: =IF($J99="","","Q"&(INT(MOD(MONTH($J99)-マスタ!$B$4+12,12)/3)+1)) | P99: =IF($L99="","",IF($M99<>"",$M99-$L99,IF(TODAY()>$L99,TODAY()-$L99,0))) | R99: =IF($Q99="","",$Q99*N($F99)) | T99: =IF($A99="","",SUMIFS(発注・納品!$H$3:$H$202,発注・納品!$B$3:$B$202,$A99)) | U99: =IF($Q99="","",N($S99)+N($T99)) | V99: =IF($Q99="","",$Q99-N($U99)) | W99: =IF(N($Q99)=0,"",$V99/$Q99) | X99: =IF($A99="","",COUNTIFS(発注・納品!$B$3:$B$202,$A99)) | Y99: =IF($A99="","",COUNTIFS(発注・納品!$B$3:$B$202,$A99,発注・納品!$M$3:$M$202,"")) | Z99: =IF(N($X99)=0,"",IF(_xlfn.MAXIFS(発注・納品!$M$3:$M$202,発注・納品!$B$3:$B$202,$A99)=0,"",_xlfn.MAXIFS(発注・納品!$M$3:$M$202,発注・納品!$B$3:$B$202,$A99))) | AA99: =IF($A99="","",IF(N($X99)=0,"機器なし",IF(N($Y99)>0,"入荷待ち",IF(COUNTIFS(発注・納品!$B$3:$B$202,$A99,発注・納品!$N$3:$N$202,"")>0,"受入待ち","受入完了")))) | AB99: =IF($A99="","",COUNTIFS(現地作業!$A$3:$A$202,$A99,現地作業!$L$3:$L$202,"予定")) | AC99: =IF($A99="","",COUNTIFS(現地作業!$A$3:$A$202,$A99,現地作業!$L$3:$L$202,"完了")) | AD99: =IF(N($AB99)=0,"",IF(_xlfn.MINIFS(現地作業!$C$3:$C$202,現地作業!$A$3:$A$202,$A99,現地作業!$L$3:$L$202,"予定",現地作業!$C$3:$C$202,">="&TODAY())=0,"",_xlfn.MINIFS(現地作業!$C$3:$C$202,現地作業!$A$3:$A$202,$A99,現地作業!$L$3:$L$202,"予定",現地作業!$C$3:$C$202,">="&TODAY()))) | AF99: =IF($A99="","",SUM(月次工数計画!$G$104:$AD$104)) | AG99: =IF($A99="","",SUMIFS(工数明細!$G$3:$G$302,工数明細!$B$3:$B$302,$A99)) | AH99: =IF($AE99="","",$AE99-N($AG99)) | AI99: =IF(N($AE99)=0,"",$AG99/$AE99) | AJ99: =IF(N($AE99)=0,"",IF($AG99>$AE99,"超過",IF($AG99>=$AE99*0.9,"注意","適正")))
N100: =IF($J100="","",YEAR($J100)-IF(MONTH($J100)<マスタ!$B$4,1,0)) | O100: =IF($J100="","","Q"&(INT(MOD(MONTH($J100)-マスタ!$B$4+12,12)/3)+1)) | P100: =IF($L100="","",IF($M100<>"",$M100-$L100,IF(TODAY()>$L100,TODAY()-$L100,0))) | R100: =IF($Q100="","",$Q100*N($F100)) | T100: =IF($A100="","",SUMIFS(発注・納品!$H$3:$H$202,発注・納品!$B$3:$B$202,$A100)) | U100: =IF($Q100="","",N($S100)+N($T100)) | V100: =IF($Q100="","",$Q100-N($U100)) | W100: =IF(N($Q100)=0,"",$V100/$Q100) | X100: =IF($A100="","",COUNTIFS(発注・納品!$B$3:$B$202,$A100)) | Y100: =IF($A100="","",COUNTIFS(発注・納品!$B$3:$B$202,$A100,発注・納品!$M$3:$M$202,"")) | Z100: =IF(N($X100)=0,"",IF(_xlfn.MAXIFS(発注・納品!$M$3:$M$202,発注・納品!$B$3:$B$202,$A100)=0,"",_xlfn.MAXIFS(発注・納品!$M$3:$M$202,発注・納品!$B$3:$B$202,$A100))) | AA100: =IF($A100="","",IF(N($X100)=0,"機器なし",IF(N($Y100)>0,"入荷待ち",IF(COUNTIFS(発注・納品!$B$3:$B$202,$A100,発注・納品!$N$3:$N$202,"")>0,"受入待ち","受入完了")))) | AB100: =IF($A100="","",COUNTIFS(現地作業!$A$3:$A$202,$A100,現地作業!$L$3:$L$202,"予定")) | AC100: =IF($A100="","",COUNTIFS(現地作業!$A$3:$A$202,$A100,現地作業!$L$3:$L$202,"完了")) | AD100: =IF(N($AB100)=0,"",IF(_xlfn.MINIFS(現地作業!$C$3:$C$202,現地作業!$A$3:$A$202,$A100,現地作業!$L$3:$L$202,"予定",現地作業!$C$3:$C$202,">="&TODAY())=0,"",_xlfn.MINIFS(現地作業!$C$3:$C$202,現地作業!$A$3:$A$202,$A100,現地作業!$L$3:$L$202,"予定",現地作業!$C$3:$C$202,">="&TODAY()))) | AF100: =IF($A100="","",SUM(月次工数計画!$G$105:$AD$105)) | AG100: =IF($A100="","",SUMIFS(工数明細!$G$3:$G$302,工数明細!$B$3:$B$302,$A100)) | AH100: =IF($AE100="","",$AE100-N($AG100)) | AI100: =IF(N($AE100)=0,"",$AG100/$AE100) | AJ100: =IF(N($AE100)=0,"",IF($AG100>$AE100,"超過",IF($AG100>=$AE100*0.9,"注意","適正")))
...

Sheet 工数明細
A1: 工数明細 │ 日々の工数を入れると、案件管理の「実績工数」と月次工数計画の「実績」に積み上がります
A2: 日付 | B2: 案件ID | C2: 案件名 | D2: 担当者 | E2: 作業ステップ | F2: 工数(時間) | G2: 工数(人日) | H2: 作業内容・メモ | I2: 年月
A3: 46176 | B3: P-001 | C3: =IF($B3="","",IFERROR(INDEX(案件管理!$B$3:$B$202,MATCH($B3,案件管理!$A$3:$A$202,0)),"←IDが未登録です")) -> 本社ネットワーク更改 | D3: 山田 太郎 | E3: 現地作業 | F3: 8 | G3: =IF(N($F3)=0,"",$F3/マスタ!$B$5) -> 1 | H3: L3スイッチ設置・疎通確認（※サンプル行） | I3: =IF($A3="","",YEAR($A3)*100+MONTH($A3)) -> 202606
A4: 46177 | B4: P-001 | C4: =IF($B4="","",IFERROR(INDEX(案件管理!$B$3:$B$202,MATCH($B4,案件管理!$A$3:$A$202,0)),"←IDが未登録です")) -> 本社ネットワーク更改 | D4: 山田 太郎 | E4: 現地作業 | F4: 6 | G4: =IF(N($F4)=0,"",$F4/マスタ!$B$5) -> 0.75 | H4: 配線作業（※サンプル行） | I4: =IF($A4="","",YEAR($A4)*100+MONTH($A4)) -> 202606
A5: 46204 | B5: P-001 | C5: =IF($B5="","",IFERROR(INDEX(案件管理!$B$3:$B$202,MATCH($B5,案件管理!$A$3:$A$202,0)),"←IDが未登録です")) -> 本社ネットワーク更改 | D5: 佐藤 花子 | E5: テスト | F5: 4 | G5: =IF(N($F5)=0,"",$F5/マスタ!$B$5) -> 0.5 | H5: 受入試験の立会い（※サンプル行） | I5: =IF($A5="","",YEAR($A5)*100+MONTH($A5)) -> 202607
A6: 46178 | B6: P-002 | C6: =IF($B6="","",IFERROR(INDEX(案件管理!$B$3:$B$202,MATCH($B6,案件管理!$A$3:$A$202,0)),"←IDが未登録です")) -> 基幹システム保守（年間） | D6: 佐藤 花子 | E6: テスト | F6: 4 | G6: =IF(N($F6)=0,"",$F6/マスタ!$B$5) -> 0.5 | H6: 定期点検レポート作成（※サンプル行） | I6: =IF($A6="","",YEAR($A6)*100+MONTH($A6)) -> 202606
C7: =IF($B7="","",IFERROR(INDEX(案件管理!$B$3:$B$202,MATCH($B7,案件管理!$A$3:$A$202,0)),"←IDが未登録です")) | G7: =IF(N($F7)=0,"",$F7/マスタ!$B$5) | I7: =IF($A7="","",YEAR($A7)*100+MONTH($A7))
C8: =IF($B8="","",IFERROR(INDEX(案件管理!$B$3:$B$202,MATCH($B8,案件管理!$A$3:$A$202,0)),"←IDが未登録です")) | G8: =IF(N($F8)=0,"",$F8/マスタ!$B$5) | I8: =IF($A8="","",YEAR($A8)*100+MONTH($A8))
C9: =IF($B9="","",IFERROR(INDEX(案件管理!$B$3:$B$202,MATCH($B9,案件管理!$A$3:$A$202,0)),"←IDが未登録です")) | G9: =IF(N($F9)=0,"",$F9/マスタ!$B$5) | I9: =IF($A9="","",YEAR($A9)*100+MONTH($A9))
C10: =IF($B10="","",IFERROR(INDEX(案件管理!$B$3:$B$202,MATCH($B10,案件管理!$A$3:$A$202,0)),"←IDが未登録です")) | G10: =IF(N($F10)=0,"",$F10/マスタ!$B$5) | I10: =IF($A10="","",YEAR($A10)*100+MONTH($A10))
C11: =IF($B11="","",IFERROR(INDEX(案件管理!$B$3:$B$202,MATCH($B11,案件管理!$A$3:$A$202,0)),"←IDが未登録です")) | G11: =IF(N($F11)=0,"",$F11/マスタ!$B$5) | I11: =IF($A11="","",YEAR($A11)*100+MONTH($A11))
C12: =IF($B12="","",IFERROR(INDEX(案件管理!$B$3:$B$202,MATCH($B12,案件管理!$A$3:$A$202,0)),"←IDが未登録です")) | G12: =IF(N($F12)=0,"",$F12/マスタ!$B$5) | I12: =IF($A12="","",YEAR($A12)*100+MONTH($A12))
C13: =IF($B13="","",IFERROR(INDEX(案件管理!$B$3:$B$202,MATCH($B13,案件管理!$A$3:$A$202,0)),"←IDが未登録です")) | G13: =IF(N($F13)=0,"",$F13/マスタ!$B$5) | I13: =IF($A13="","",YEAR($A13)*100+MONTH($A13))
C14: =IF($B14="","",IFERROR(INDEX(案件管理!$B$3:$B$202,MATCH($B14,案件管理!$A$3:$A$202,0)),"←IDが未登録です")) | G14: =IF(N($F14)=0,"",$F14/マスタ!$B$5) | I14: =IF($A14="","",YEAR($A14)*100+MONTH($A14))
C15: =IF($B15="","",IFERROR(INDEX(案件管理!$B$3:$B$202,MATCH($B15,案件管理!$A$3:$A$202,0)),"←IDが未登録です")) | G15: =IF(N($F15)=0,"",$F15/マスタ!$B$5) | I15: =IF($A15="","",YEAR($A15)*100+MONTH($A15))
C16: =IF($B16="","",IFERROR(INDEX(案件管理!$B$3:$B$202,MATCH($B16,案件管理!$A$3:$A$202,0)),"←IDが未登録です")) | G16: =IF(N($F16)=0,"",$F16/マスタ!$B$5) | I16: =IF($A16="","",YEAR($A16)*100+MONTH($A16))
C17: =IF($B17="","",IFERROR(INDEX(案件管理!$B$3:$B$202,MATCH($B17,案件管理!$A$3:$A$202,0)),"←IDが未登録です")) | G17: =IF(N($F17)=0,"",$F17/マスタ!$B$5) | I17: =IF($A17="","",YEAR($A17)*100+MONTH($A17))
C18: =IF($B18="","",IFERROR(INDEX(案件管理!$B$3:$B$202,MATCH($B18,案件管理!$A$3:$A$202,0)),"←IDが未登録です")) | G18: =IF(N($F18)=0,"",$F18/マスタ!$B$5) | I18: =IF($A18="","",YEAR($A18)*100+MONTH($A18))
... C302: =IF($B302="","",IFERROR(INDEX(案件管理!$B$3:$B$202,MATCH($B302,案件管理!$A$3:$A$202,0)),"←IDが未登録です")) | G302: =IF(N($F302)=0,"",$F302/マスタ!$B$5) | I302: =IF($A302="","",YEAR($A302)*100+MONTH($A302))
A304: 「工数(人日)」＝ 工数(時間) ÷ マスタ!B5（1人日あたりの時間）。「年月」は月次集計用の自動計算です。

Sheet 月次工数計画
A1: 月次工数計画 │ どの案件に、何月、何人日を投入するか
A3: 開始年月 | B3: =マスタ!$B$7 -> 46113 | C3: ← マスタ!B7 で変更できます。変えると列見出しがずれるので、入力済みの数値も合わせて動かしてください。
A5: ■ 計画（人日） … 青いセルに「何月に何人日」を入力してください
A6: （集計キー：編集しないでください） | G6: =YEAR(G7)*100+MONTH(G7) -> 202604 | H6: =YEAR(H7)*100+MONTH(H7) -> 202605 | I6: =YEAR(I7)*100+MONTH(I7) -> 202606 | J6: =YEAR(J7)*100+MONTH(J7) -> 202607 | K6: =YEAR(K7)*100+MONTH(K7) -> 202608 | L6: =YEAR(L7)*100+MONTH(L7) -> 202609 | M6: =YEAR(M7)*100+MONTH(M7) -> 202610 | N6: =YEAR(N7)*100+MONTH(N7) -> 202611 | ... AD6: =YEAR(AD7)*100+MONTH(AD7) -> 202803
A7: 案件ID | B7: 案件名 | C7: 担当者 | D7: 予定工数 | E7: 月次 計画計 | F7: 差異 (未配分) | G7: =EDATE(マスタ!$B$7,0) -> 46113 | H7: =EDATE(マスタ!$B$7,1) -> 46143 | I7: =EDATE(マスタ!$B$7,2) -> 46174 | J7: =EDATE(マスタ!$B$7,3) -> 46204 | K7: =EDATE(マスタ!$B$7,4) -> 46235 | L7: =EDATE(マスタ!$B$7,5) -> 46266 | M7: =EDATE(マスタ!$B$7,6) -> 46296 | N7: =EDATE(マスタ!$B$7,7) -> 46327 | O7: =EDATE(マスタ!$B$7,8) -> 46357 | P7: =EDATE(マスタ!$B$7,9) -> 46388 | Q7: =EDATE(マスタ!$B$7,10) -> 46419 | R7: =EDATE(マスタ!$B$7,11) -> 46447 | S7: =EDATE(マスタ!$B$7,12) -> 46478 | T7: =EDATE(マスタ!$B$7,13) -> 46508 | U7: =EDATE(マスタ!$B$7,14) -> 46539 | V7: =EDATE(マスタ!$B$7,15) -> 46569 | W7: =EDATE(マスタ!$B$7,16) -> 46600 | X7: =EDATE(マスタ!$B$7,17) -> 46631 | Y7: =EDATE(マスタ!$B$7,18) -> 46661 | Z7: =EDATE(マスタ!$B$7,19) -> 46692 | AA7: =EDATE(マスタ!$B$7,20) -> 46722 | AB7: =EDATE(マスタ!$B$7,21) -> 46753 | AC7: =EDATE(マスタ!$B$7,22) -> 46784 | AD7: =EDATE(マスタ!$B$7,23) -> 46813
A8: =IF(案件管理!$A$3:$A$3="","",案件管理!$A$3:$A$3) -> P-001 | B8: =IF($A8="","",案件管理!$B$3:$B$3) -> 本社ネットワーク更改 | C8: =IF($A8="","",案件管理!$D$3:$D$3) -> 山田 太郎 | D8: =IF($A8="","",案件管理!$AE$3:$AE$3) -> 45 | E8: =IF($A8="","",SUM($G8:$AD8)) -> 45 | F8: =IF($A8="","",N($D8)-N($E8)) -> 0 | I8: 15 | J8: 20 | K8: 10
A9: =IF(案件管理!$A$4:$A$4="","",案件管理!$A$4:$A$4) -> P-002 | B9: =IF($A9="","",案件管理!$B$4:$B$4) -> 基幹システム保守（年間） | C9: =IF($A9="","",案件管理!$D$4:$D$4) -> 佐藤 花子 | D9: =IF($A9="","",案件管理!$AE$4:$AE$4) -> 12 | E9: =IF($A9="","",SUM($G9:$AD9)) -> 12 | F9: =IF($A9="","",N($D9)-N($E9)) -> 0 | G9: 4 | H9: 4 | I9: 4
A10: =IF(案件管理!$A$5:$A$5="","",案件管理!$A$5:$A$5) -> P-003 | B10: =IF($A10="","",案件管理!$B$5:$B$5) -> Webサイトリニューアル | C10: =IF($A10="","",案件管理!$D$5:$D$5) -> 鈴木 一郎 | D10: =IF($A10="","",案件管理!$AE$5:$AE$5) -> 30 | E10: =IF($A10="","",SUM($G10:$AD10)) -> 30 | F10: =IF($A10="","",N($D10)-N($E10)) -> 0 | N10: 5 | O10: 10 | P10: 10 | Q10: 5
A11: =IF(案件管理!$A$6:$A$6="","",案件管理!$A$6:$A$6) | B11: =IF($A11="","",案件管理!$B$6:$B$6) | C11: =IF($A11="","",案件管理!$D$6:$D$6) | D11: =IF($A11="","",案件管理!$AE$6:$AE$6) | E11: =IF($A11="","",SUM($G11:$AD11)) | F11: =IF($A11="","",N($D11)-N($E11))
A12: =IF(案件管理!$A$7:$A$7="","",案件管理!$A$7:$A$7) | B12: =IF($A12="","",案件管理!$B$7:$B$7) | C12: =IF($A12="","",案件管理!$D$7:$D$7) | D12: =IF($A12="","",案件管理!$AE$7:$AE$7) | E12: =IF($A12="","",SUM($G12:$AD12)) | F12: =IF($A12="","",N($D12)-N($E12))
A13: =IF(案件管理!$A$8:$A$8="","",案件管理!$A$8:$A$8) | B13: =IF($A13="","",案件管理!$B$8:$B$8) | C13: =IF($A13="","",案件管理!$D$8:$D$8) | D13: =IF($A13="","",案件管理!$AE$8:$AE$8) | E13: =IF($A13="","",SUM($G13:$AD13)) | F13: =IF($A13="","",N($D13)-N($E13))
A14: =IF(案件管理!$A$9:$A$9="","",案件管理!$A$9:$A$9) | B14: =IF($A14="","",案件管理!$B$9:$B$9) | C14: =IF($A14="","",案件管理!$D$9:$D$9) | D14: =IF($A14="","",案件管理!$AE$9:$AE$9) | E14: =IF($A14="","",SUM($G14:$AD14)) | F14: =IF($A14="","",N($D14)-N($E14))
A15: =IF(案件管理!$A$10:$A$10="","",案件管理!$A$10:$A$10) | B15: =IF($A15="","",案件管理!$B$10:$B$10) | C15: =IF($A15="","",案件管理!$D$10:$D$10) | D15: =IF($A15="","",案件管理!$AE$10:$AE$10) | E15: =IF($A15="","",SUM($G15:$AD15)) | F15: =IF($A15="","",N($D15)-N($E15))
A16: =IF(案件管理!$A$11:$A$11="","",案件管理!$A$11:$A$11) | B16: =IF($A16="","",案件管理!$B$11:$B$11) | C16: =IF($A16="","",案件管理!$D$11:$D$11) | D16: =IF($A16="","",案件管理!$AE$11:$AE$11) | E16: =IF($A16="","",SUM($G16:$AD16)) | F16: =IF($A16="","",N($D16)-N($E16))
A17: =IF(案件管理!$A$12:$A$12="","",案件管理!$A$12:$A$12) | B17: =IF($A17="","",案件管理!$B$12:$B$12) | C17: =IF($A17="","",案件管理!$D$12:$D$12) | D17: =IF($A17="","",案件管理!$AE$12:$AE$12) | E17: =IF($A17="","",SUM($G17:$AD17)) | F17: =IF($A17="","",N($D17)-N($E17))
A18: =IF(案件管理!$A$13:$A$13="","",案件管理!$A$13:$A$13) | B18: =IF($A18="","",案件管理!$B$13:$B$13) | C18: =IF($A18="","",案件管理!$D$13:$D$13) | D18: =IF($A18="","",案件管理!$AE$13:$AE$13) | E18: =IF($A18="","",SUM($G18:$AD18)) | F18: =IF($A18="","",N($D18)-N($E18))
A19: =IF(案件管理!$A$14:$A$14="","",案件管理!$A$14:$A$14) | B19: =IF($A19="","",案件管理!$B$14:$B$14) | C19: =IF($A19="","",案件管理!$D$14:$D$14) | D19: =IF($A19="","",案件管理!$AE$14:$AE$14) | E19: =IF($A19="","",SUM($G19:$AD19)) | F19: =IF($A19="","",N($D19)-N($E19))
A20: =IF(案件管理!$A$15:$A$15="","",案件管理!$A$15:$A$15) | B20: =IF($A20="","",案件管理!$B$15:$B$15) | C20: =IF($A20="","",案件管理!$D$15:$D$15) | D20: =IF($A20="","",案件管理!$AE$15:$AE$15) | E20: =IF($A20="","",SUM($G20:$AD20)) | F20: =IF($A20="","",N($D20)-N($E20))
A21: =IF(案件管理!$A$16:$A$16="","",案件管理!$A$16:$A$16) | B21: =IF($A21="","",案件管理!$B$16:$B$16) | C21: =IF($A21="","",案件管理!$D$16:$D$16) | D21: =IF($A21="","",案件管理!$AE$16:$AE$16) | E21: =IF($A21="","",SUM($G21:$AD21)) | F21: =IF($A21="","",N($D21)-N($E21))
A22: =IF(案件管理!$A$17:$A$17="","",案件管理!$A$17:$A$17) | B22: =IF($A22="","",案件管理!$B$17:$B$17) | C22: =IF($A22="","",案件管理!$D$17:$D$17) | D22: =IF($A22="","",案件管理!$AE$17:$AE$17) | E22: =IF($A22="","",SUM($G22:$AD22)) | F22: =IF($A22="","",N($D22)-N($E22))
A23: =IF(案件管理!$A$18:$A$18="","",案件管理!$A$18:$A$18) | B23: =IF($A23="","",案件管理!$B$18:$B$18) | C23: =IF($A23="","",案件管理!$D$18:$D$18) | D23: =IF($A23="","",案件管理!$AE$18:$AE$18) | E23: =IF($A23="","",SUM($G23:$AD23)) | F23: =IF($A23="","",N($D23)-N($E23))
A24: =IF(案件管理!$A$19:$A$19="","",案件管理!$A$19:$A$19) | B24: =IF($A24="","",案件管理!$B$19:$B$19) | C24: =IF($A24="","",案件管理!$D$19:$D$19) | D24: =IF($A24="","",案件管理!$AE$19:$AE$19) | E24: =IF($A24="","",SUM($G24:$AD24)) | F24: =IF($A24="","",N($D24)-N($E24))
A25: =IF(案件管理!$A$20:$A$20="","",案件管理!$A$20:$A$20) | B25: =IF($A25="","",案件管理!$B$20:$B$20) | C25: =IF($A25="","",案件管理!$D$20:$D$20) | D25: =IF($A25="","",案件管理!$AE$20:$AE$20) | E25: =IF($A25="","",SUM($G25:$AD25)) | F25: =IF($A25="","",N($D25)-N($E25))
A26: =IF(案件管理!$A$21:$A$21="","",案件管理!$A$21:$A$21) | B26: =IF($A26="","",案件管理!$B$21:$B$21) | C26: =IF($A26="","",案件管理!$D$21:$D$21) | D26: =IF($A26="","",案件管理!$AE$21:$AE$21) | E26: =IF($A26="","",SUM($G26:$AD26)) | F26: =IF($A26="","",N($D26)-N($E26))
A27: =IF(案件管理!$A$22:$A$22="","",案件管理!$A$22:$A$22) | B27: =IF($A27="","",案件管理!$B$22:$B$22) | C27: =IF($A27="","",案件管理!$D$22:$D$22) | D27: =IF($A27="","",案件管理!$AE$22:$AE$22) | E27: =IF($A27="","",SUM($G27:$AD27)) | F27: =IF($A27="","",N($D27)-N($E27))
A28: =IF(案件管理!$A$23:$A$23="","",案件管理!$A$23:$A$23) | B28: =IF($A28="","",案件管理!$B$23:$B$23) | C28: =IF($A28="","",案件管理!$D$23:$D$23) | D28: =IF($A28="","",案件管理!$AE$23:$AE$23) | E28: =IF($A28="","",SUM($G28:$AD28)) | F28: =IF($A28="","",N($D28)-N($E28))
A29: =IF(案件管理!$A$24:$A$24="","",案件管理!$A$24:$A$24) | B29: =IF($A29="","",案件管理!$B$24:$B$24) | C29: =IF($A29="","",案件管理!$D$24:$D$24) | D29: =IF($A29="","",案件管理!$AE$24:$AE$24) | E29: =IF($A29="","",SUM($G29:$AD29)) | F29: =IF($A29="","",N($D29)-N($E29))
A30: =IF(案件管理!$A$25:$A$25="","",案件管理!$A$25:$A$25) | B30: =IF($A30="","",案件管理!$B$25:$B$25) | C30: =IF($A30="","",案件管理!$D$25:$D$25) | D30: =IF($A30="","",案件管理!$AE$25:$AE$25) | E30: =IF($A30="","",SUM($G30:$AD30)) | F30: =IF($A30="","",N($D30)-N($E30))
A31: =IF(案件管理!$A$26:$A$26="","",案件管理!$A$26:$A$26) | B31: =IF($A31="","",案件管理!$B$26:$B$26) | C31: =IF($A31="","",案件管理!$D$26:$D$26) | D31: =IF($A31="","",案件管理!$AE$26:$AE$26) | E31: =IF($A31="","",SUM($G31:$AD31)) | F31: =IF($A31="","",N($D31)-N($E31))
A32: =IF(案件管理!$A$27:$A$27="","",案件管理!$A$27:$A$27) | B32: =IF($A32="","",案件管理!$B$27:$B$27) | C32: =IF($A32="","",案件管理!$D$27:$D$27) | D32: =IF($A32="","",案件管理!$AE$27:$AE$27) | E32: =IF($A32="","",SUM($G32:$AD32)) | F32: =IF($A32="","",N($D32)-N($E32))
A33: =IF(案件管理!$A$28:$A$28="","",案件管理!$A$28:$A$28) | B33: =IF($A33="","",案件管理!$B$28:$B$28) | C33: =IF($A33="","",案件管理!$D$28:$D$28) | D33: =IF($A33="","",案件管理!$AE$28:$AE$28) | E33: =IF($A33="","",SUM($G33:$AD33)) | F33: =IF($A33="","",N($D33)-N($E33))
A34: =IF(案件管理!$A$29:$A$29="","",案件管理!$A$29:$A$29) | B34: =IF($A34="","",案件管理!$B$29:$B$29) | C34: =IF($A34="","",案件管理!$D$29:$D$29) | D34: =IF($A34="","",案件管理!$AE$29:$AE$29) | E34: =IF($A34="","",SUM($G34:$AD34)) | F34: =IF($A34="","",N($D34)-N($E34))
A35: =IF(案件管理!$A$30:$A$30="","",案件管理!$A$30:$A$30) | B35: =IF($A35="","",案件管理!$B$30:$B$30) | C35: =IF($A35="","",案件管理!$D$30:$D$30) | D35: =IF($A35="","",案件管理!$AE$30:$AE$30) | E35: =IF($A35="","",SUM($G35:$AD35)) | F35: =IF($A35="","",N($D35)-N($E35))
A36: =IF(案件管理!$A$31:$A$31="","",案件管理!$A$31:$A$31) | B36: =IF($A36="","",案件管理!$B$31:$B$31) | C36: =IF($A36="","",案件管理!$D$31:$D$31) | D36: =IF($A36="","",案件管理!$AE$31:$AE$31) | E36: =IF($A36="","",SUM($G36:$AD36)) | F36: =IF($A36="","",N($D36)-N($E36))
A37: =IF(案件管理!$A$32:$A$32="","",案件管理!$A$32:$A$32) | B37: =IF($A37="","",案件管理!$B$32:$B$32) | C37: =IF($A37="","",案件管理!$D$32:$D$32) | D37: =IF($A37="","",案件管理!$AE$32:$AE$32) | E37: =IF($A37="","",SUM($G37:$AD37)) | F37: =IF($A37="","",N($D37)-N($E37))
A38: =IF(案件管理!$A$33:$A$33="","",案件管理!$A$33:$A$33) | B38: =IF($A38="","",案件管理!$B$33:$B$33) | C38: =IF($A38="","",案件管理!$D$33:$D$33) | D38: =IF($A38="","",案件管理!$AE$33:$AE$33) | E38: =IF($A38="","",SUM($G38:$AD38)) | F38: =IF($A38="","",N($D38)-N($E38))
A39: =IF(案件管理!$A$34:$A$34="","",案件管理!$A$34:$A$34) | B39: =IF($A39="","",案件管理!$B$34:$B$34) | C39: =IF($A39="","",案件管理!$D$34:$D$34) | D39: =IF($A39="","",案件管理!$AE$34:$AE$34) | E39: =IF($A39="","",SUM($G39:$AD39)) | F39: =IF($A39="","",N($D39)-N($E39))
A40: =IF(案件管理!$A$35:$A$35="","",案件管理!$A$35:$A$35) | B40: =IF($A40="","",案件管理!$B$35:$B$35) | C40: =IF($A40="","",案件管理!$D$35:$D$35) | D40: =IF($A40="","",案件管理!$AE$35:$AE$35) | E40: =IF($A40="","",SUM($G40:$AD40)) | F40: =IF($A40="","",N($D40)-N($E40))
A41: =IF(案件管理!$A$36:$A$36="","",案件管理!$A$36:$A$36) | B41: =IF($A41="","",案件管理!$B$36:$B$36) | C41: =IF($A41="","",案件管理!$D$36:$D$36) | D41: =IF($A41="","",案件管理!$AE$36:$AE$36) | E41: =IF($A41="","",SUM($G41:$AD41)) | F41: =IF($A41="","",N($D41)-N($E41))
A42: =IF(案件管理!$A$37:$A$37="","",案件管理!$A$37:$A$37) | B42: =IF($A42="","",案件管理!$B$37:$B$37) | C42: =IF($A42="","",案件管理!$D$37:$D$37) | D42: =IF($A42="","",案件管理!$AE$37:$AE$37) | E42: =IF($A42="","",SUM($G42:$AD42)) | F42: =IF($A42="","",N($D42)-N($E42))
A43: =IF(案件管理!$A$38:$A$38="","",案件管理!$A$38:$A$38) | B43: =IF($A43="","",案件管理!$B$38:$B$38) | C43: =IF($A43="","",案件管理!$D$38:$D$38) | D43: =IF($A43="","",案件管理!$AE$38:$AE$38) | E43: =IF($A43="","",SUM($G43:$AD43)) | F43: =IF($A43="","",N($D43)-N($E43))
A44: =IF(案件管理!$A$39:$A$39="","",案件管理!$A$39:$A$39) | B44: =IF($A44="","",案件管理!$B$39:$B$39) | C44: =IF($A44="","",案件管理!$D$39:$D$39) | D44: =IF($A44="","",案件管理!$AE$39:$AE$39) | E44: =IF($A44="","",SUM($G44:$AD44)) | F44: =IF($A44="","",N($D44)-N($E44))
A45: =IF(案件管理!$A$40:$A$40="","",案件管理!$A$40:$A$40) | B45: =IF($A45="","",案件管理!$B$40:$B$40) | C45: =IF($A45="","",案件管理!$D$40:$D$40) | D45: =IF($A45="","",案件管理!$AE$40:$AE$40) | E45: =IF($A45="","",SUM($G45:$AD45)) | F45: =IF($A45="","",N($D45)-N($E45))
A46: =IF(案件管理!$A$41:$A$41="","",案件管理!$A$41:$A$41) | B46: =IF($A46="","",案件管理!$B$41:$B$41) | C46: =IF($A46="","",案件管理!$D$41:$D$41) | D46: =IF($A46="","",案件管理!$AE$41:$AE$41) | E46: =IF($A46="","",SUM($G46:$AD46)) | F46: =IF($A46="","",N($D46)-N($E46))
A47: =IF(案件管理!$A$42:$A$42="","",案件管理!$A$42:$A$42) | B47: =IF($A47="","",案件管理!$B$42:$B$42) | C47: =IF($A47="","",案件管理!$D$42:$D$42) | D47: =IF($A47="","",案件管理!$AE$42:$AE$42) | E47: =IF($A47="","",SUM($G47:$AD47)) | F47: =IF($A47="","",N($D47)-N($E47))
A48: =IF(案件管理!$A$43:$A$43="","",案件管理!$A$43:$A$43) | B48: =IF($A48="","",案件管理!$B$43:$B$43) | C48: =IF($A48="","",案件管理!$D$43:$D$43) | D48: =IF($A48="","",案件管理!$AE$43:$AE$43) | E48: =IF($A48="","",SUM($G48:$AD48)) | F48: =IF($A48="","",N($D48)-N($E48))
A49: =IF(案件管理!$A$44:$A$44="","",案件管理!$A$44:$A$44) | B49: =IF($A49="","",案件管理!$B$44:$B$44) | C49: =IF($A49="","",案件管理!$D$44:$D$44) | D49: =IF($A49="","",案件管理!$AE$44:$AE$44) | E49: =IF($A49="","",SUM($G49:$AD49)) | F49: =IF($A49="","",N($D49)-N($E49))
A50: =IF(案件管理!$A$45:$A$45="","",案件管理!$A$45:$A$45) | B50: =IF($A50="","",案件管理!$B$45:$B$45) | C50: =IF($A50="","",案件管理!$D$45:$D$45) | D50: =IF($A50="","",案件管理!$AE$45:$AE$45) | E50: =IF($A50="","",SUM($G50:$AD50)) | F50: =IF($A50="","",N($D50)-N($E50))
A51: =IF(案件管理!$A$46:$A$46="","",案件管理!$A$46:$A$46) | B51: =IF($A51="","",案件管理!$B$46:$B$46) | C51: =IF($A51="","",案件管理!$D$46:$D$46) | D51: =IF($A51="","",案件管理!$AE$46:$AE$46) | E51: =IF($A51="","",SUM($G51:$AD51)) | F51: =IF($A51="","",N($D51)-N($E51))
A52: =IF(案件管理!$A$47:$A$47="","",案件管理!$A$47:$A$47) | B52: =IF($A52="","",案件管理!$B$47:$B$47) | C52: =IF($A52="","",案件管理!$D$47:$D$47) | D52: =IF($A52="","",案件管理!$AE$47:$AE$47) | E52: =IF($A52="","",SUM($G52:$AD52)) | F52: =IF($A52="","",N($D52)-N($E52))
A53: =IF(案件管理!$A$48:$A$48="","",案件管理!$A$48:$A$48) | B53: =IF($A53="","",案件管理!$B$48:$B$48) | C53: =IF($A53="","",案件管理!$D$48:$D$48) | D53: =IF($A53="","",案件管理!$AE$48:$AE$48) | E53: =IF($A53="","",SUM($G53:$AD53)) | F53: =IF($A53="","",N($D53)-N($E53))
A54: =IF(案件管理!$A$49:$A$49="","",案件管理!$A$49:$A$49) | B54: =IF($A54="","",案件管理!$B$49:$B$49) | C54: =IF($A54="","",案件管理!$D$49:$D$49) | D54: =IF($A54="","",案件管理!$AE$49:$AE$49) | E54: =IF($A54="","",SUM($G54:$AD54)) | F54: =IF($A54="","",N($D54)-N($E54))
A55: =IF(案件管理!$A$50:$A$50="","",案件管理!$A$50:$A$50) | B55: =IF($A55="","",案件管理!$B$50:$B$50) | C55: =IF($A55="","",案件管理!$D$50:$D$50) | D55: =IF($A55="","",案件管理!$AE$50:$AE$50) | E55: =IF($A55="","",SUM($G55:$AD55)) | F55: =IF($A55="","",N($D55)-N($E55))
A56: =IF(案件管理!$A$51:$A$51="","",案件管理!$A$51:$A$51) | B56: =IF($A56="","",案件管理!$B$51:$B$51) | C56: =IF($A56="","",案件管理!$D$51:$D$51) | D56: =IF($A56="","",案件管理!$AE$51:$AE$51) | E56: =IF($A56="","",SUM($G56:$AD56)) | F56: =IF($A56="","",N($D56)-N($E56))
A57: =IF(案件管理!$A$52:$A$52="","",案件管理!$A$52:$A$52) | B57: =IF($A57="","",案件管理!$B$52:$B$52) | C57: =IF($A57="","",案件管理!$D$52:$D$52) | D57: =IF($A57="","",案件管理!$AE$52:$AE$52) | E57: =IF($A57="","",SUM($G57:$AD57)) | F57: =IF($A57="","",N($D57)-N($E57))
A58: =IF(案件管理!$A$53:$A$53="","",案件管理!$A$53:$A$53) | B58: =IF($A58="","",案件管理!$B$53:$B$53) | C58: =IF($A58="","",案件管理!$D$53:$D$53) | D58: =IF($A58="","",案件管理!$AE$53:$AE$53) | E58: =IF($A58="","",SUM($G58:$AD58)) | F58: =IF($A58="","",N($D58)-N($E58))
A59: =IF(案件管理!$A$54:$A$54="","",案件管理!$A$54:$A$54) | B59: =IF($A59="","",案件管理!$B$54:$B$54) | C59: =IF($A59="","",案件管理!$D$54:$D$54) | D59: =IF($A59="","",案件管理!$AE$54:$AE$54) | E59: =IF($A59="","",SUM($G59:$AD59)) | F59: =IF($A59="","",N($D59)-N($E59))
A60: =IF(案件管理!$A$55:$A$55="","",案件管理!$A$55:$A$55) | B60: =IF($A60="","",案件管理!$B$55:$B$55) | C60: =IF($A60="","",案件管理!$D$55:$D$55) | D60: =IF($A60="","",案件管理!$AE$55:$AE$55) | E60: =IF($A60="","",SUM($G60:$AD60)) | F60: =IF($A60="","",N($D60)-N($E60))
A61: =IF(案件管理!$A$56:$A$56="","",案件管理!$A$56:$A$56) | B61: =IF($A61="","",案件管理!$B$56:$B$56) | C61: =IF($A61="","",案件管理!$D$56:$D$56) | D61: =IF($A61="","",案件管理!$AE$56:$AE$56) | E61: =IF($A61="","",SUM($G61:$AD61)) | F61: =IF($A61="","",N($D61)-N($E61))
A62: =IF(案件管理!$A$57:$A$57="","",案件管理!$A$57:$A$57) | B62: =IF($A62="","",案件管理!$B$57:$B$57) | C62: =IF($A62="","",案件管理!$D$57:$D$57) | D62: =IF($A62="","",案件管理!$AE$57:$AE$57) | E62: =IF($A62="","",SUM($G62:$AD62)) | F62: =IF($A62="","",N($D62)-N($E62))
A63: =IF(案件管理!$A$58:$A$58="","",案件管理!$A$58:$A$58) | B63: =IF($A63="","",案件管理!$B$58:$B$58) | C63: =IF($A63="","",案件管理!$D$58:$D$58) | D63: =IF($A63="","",案件管理!$AE$58:$AE$58) | E63: =IF($A63="","",SUM($G63:$AD63)) | F63: =IF($A63="","",N($D63)-N($E63))
A64: =IF(案件管理!$A$59:$A$59="","",案件管理!$A$59:$A$59) | B64: =IF($A64="","",案件管理!$B$59:$B$59) | C64: =IF($A64="","",案件管理!$D$59:$D$59) | D64: =IF($A64="","",案件管理!$AE$59:$AE$59) | E64: =IF($A64="","",SUM($G64:$AD64)) | F64: =IF($A64="","",N($D64)-N($E64))
A65: =IF(案件管理!$A$60:$A$60="","",案件管理!$A$60:$A$60) | B65: =IF($A65="","",案件管理!$B$60:$B$60) | C65: =IF($A65="","",案件管理!$D$60:$D$60) | D65: =IF($A65="","",案件管理!$AE$60:$AE$60) | E65: =IF($A65="","",SUM($G65:$AD65)) | F65: =IF($A65="","",N($D65)-N($E65))
A66: =IF(案件管理!$A$61:$A$61="","",案件管理!$A$61:$A$61) | B66: =IF($A66="","",案件管理!$B$61:$B$61) | C66: =IF($A66="","",案件管理!$D$61:$D$61) | D66: =IF($A66="","",案件管理!$AE$61:$AE$61) | E66: =IF($A66="","",SUM($G66:$AD66)) | F66: =IF($A66="","",N($D66)-N($E66))
A67: =IF(案件管理!$A$62:$A$62="","",案件管理!$A$62:$A$62) | B67: =IF($A67="","",案件管理!$B$62:$B$62) | C67: =IF($A67="","",案件管理!$D$62:$D$62) | D67: =IF($A67="","",案件管理!$AE$62:$AE$62) | E67: =IF($A67="","",SUM($G67:$AD67)) | F67: =IF($A67="","",N($D67)-N($E67))
A68: =IF(案件管理!$A$63:$A$63="","",案件管理!$A$63:$A$63) | B68: =IF($A68="","",案件管理!$B$63:$B$63) | C68: =IF($A68="","",案件管理!$D$63:$D$63) | D68: =IF($A68="","",案件管理!$AE$63:$AE$63) | E68: =IF($A68="","",SUM($G68:$AD68)) | F68: =IF($A68="","",N($D68)-N($E68))
A69: =IF(案件管理!$A$64:$A$64="","",案件管理!$A$64:$A$64) | B69: =IF($A69="","",案件管理!$B$64:$B$64) | C69: =IF($A69="","",案件管理!$D$64:$D$64) | D69: =IF($A69="","",案件管理!$AE$64:$AE$64) | E69: =IF($A69="","",SUM($G69:$AD69)) | F69: =IF($A69="","",N($D69)-N($E69))
A70: =IF(案件管理!$A$65:$A$65="","",案件管理!$A$65:$A$65) | B70: =IF($A70="","",案件管理!$B$65:$B$65) | C70: =IF($A70="","",案件管理!$D$65:$D$65) | D70: =IF($A70="","",案件管理!$AE$65:$AE$65) | E70: =IF($A70="","",SUM($G70:$AD70)) | F70: =IF($A70="","",N($D70)-N($E70))
A71: =IF(案件管理!$A$66:$A$66="","",案件管理!$A$66:$A$66) | B71: =IF($A71="","",案件管理!$B$66:$B$66) | C71: =IF($A71="","",案件管理!$D$66:$D$66) | D71: =IF($A71="","",案件管理!$AE$66:$AE$66) | E71: =IF($A71="","",SUM($G71:$AD71)) | F71: =IF($A71="","",N($D71)-N($E71))
A72: =IF(案件管理!$A$67:$A$67="","",案件管理!$A$67:$A$67) | B72: =IF($A72="","",案件管理!$B$67:$B$67) | C72: =IF($A72="","",案件管理!$D$67:$D$67) | D72: =IF($A72="","",案件管理!$AE$67:$AE$67) | E72: =IF($A72="","",SUM($G72:$AD72)) | F72: =IF($A72="","",N($D72)-N($E72))
A73: =IF(案件管理!$A$68:$A$68="","",案件管理!$A$68:$A$68) | B73: =IF($A73="","",案件管理!$B$68:$B$68) | C73: =IF($A73="","",案件管理!$D$68:$D$68) | D73: =IF($A73="","",案件管理!$AE$68:$AE$68) | E73: =IF($A73="","",SUM($G73:$AD73)) | F73: =IF($A73="","",N($D73)-N($E73))
A74: =IF(案件管理!$A$69:$A$69="","",案件管理!$A$69:$A$69) | B74: =IF($A74="","",案件管理!$B$69:$B$69) | C74: =IF($A74="","",案件管理!$D$69:$D$69) | D74: =IF($A74="","",案件管理!$AE$69:$AE$69) | E74: =IF($A74="","",SUM($G74:$AD74)) | F74: =IF($A74="","",N($D74)-N($E74))
A75: =IF(案件管理!$A$70:$A$70="","",案件管理!$A$70:$A$70) | B75: =IF($A75="","",案件管理!$B$70:$B$70) | C75: =IF($A75="","",案件管理!$D$70:$D$70) | D75: =IF($A75="","",案件管理!$AE$70:$AE$70) | E75: =IF($A75="","",SUM($G75:$AD75)) | F75: =IF($A75="","",N($D75)-N($E75))
A76: =IF(案件管理!$A$71:$A$71="","",案件管理!$A$71:$A$71) | B76: =IF($A76="","",案件管理!$B$71:$B$71) | C76: =IF($A76="","",案件管理!$D$71:$D$71) | D76: =IF($A76="","",案件管理!$AE$71:$AE$71) | E76: =IF($A76="","",SUM($G76:$AD76)) | F76: =IF($A76="","",N($D76)-N($E76))
A77: =IF(案件管理!$A$72:$A$72="","",案件管理!$A$72:$A$72) | B77: =IF($A77="","",案件管理!$B$72:$B$72) | C77: =IF($A77="","",案件管理!$D$72:$D$72) | D77: =IF($A77="","",案件管理!$AE$72:$AE$72) | E77: =IF($A77="","",SUM($G77:$AD77)) | F77: =IF($A77="","",N($D77)-N($E77))
A78: =IF(案件管理!$A$73:$A$73="","",案件管理!$A$73:$A$73) | B78: =IF($A78="","",案件管理!$B$73:$B$73) | C78: =IF($A78="","",案件管理!$D$73:$D$73) | D78: =IF($A78="","",案件管理!$AE$73:$AE$73) | E78: =IF($A78="","",SUM($G78:$AD78)) | F78: =IF($A78="","",N($D78)-N($E78))
A79: =IF(案件管理!$A$74:$A$74="","",案件管理!$A$74:$A$74) | B79: =IF($A79="","",案件管理!$B$74:$B$74) | C79: =IF($A79="","",案件管理!$D$74:$D$74) | D79: =IF($A79="","",案件管理!$AE$74:$AE$74) | E79: =IF($A79="","",SUM($G79:$AD79)) | F79: =IF($A79="","",N($D79)-N($E79))
A80: =IF(案件管理!$A$75:$A$75="","",案件管理!$A$75:$A$75) | B80: =IF($A80="","",案件管理!$B$75:$B$75) | C80: =IF($A80="","",案件管理!$D$75:$D$75) | D80: =IF($A80="","",案件管理!$AE$75:$AE$75) | E80: =IF($A80="","",SUM($G80:$AD80)) | F80: =IF($A80="","",N($D80)-N($E80))
A81: =IF(案件管理!$A$76:$A$76="","",案件管理!$A$76:$A$76) | B81: =IF($A81="","",案件管理!$B$76:$B$76) | C81: =IF($A81="","",案件管理!$D$76:$D$76) | D81: =IF($A81="","",案件管理!$AE$76:$AE$76) | E81: =IF($A81="","",SUM($G81:$AD81)) | F81: =IF($A81="","",N($D81)-N($E81))
A82: =IF(案件管理!$A$77:$A$77="","",案件管理!$A$77:$A$77) | B82: =IF($A82="","",案件管理!$B$77:$B$77) | C82: =IF($A82="","",案件管理!$D$77:$D$77) | D82: =IF($A82="","",案件管理!$AE$77:$AE$77) | E82: =IF($A82="","",SUM($G82:$AD82)) | F82: =IF($A82="","",N($D82)-N($E82))
A83: =IF(案件管理!$A$78:$A$78="","",案件管理!$A$78:$A$78) | B83: =IF($A83="","",案件管理!$B$78:$B$78) | C83: =IF($A83="","",案件管理!$D$78:$D$78) | D83: =IF($A83="","",案件管理!$AE$78:$AE$78) | E83: =IF($A83="","",SUM($G83:$AD83)) | F83: =IF($A83="","",N($D83)-N($E83))
A84: =IF(案件管理!$A$79:$A$79="","",案件管理!$A$79:$A$79) | B84: =IF($A84="","",案件管理!$B$79:$B$79) | C84: =IF($A84="","",案件管理!$D$79:$D$79) | D84: =IF($A84="","",案件管理!$AE$79:$AE$79) | E84: =IF($A84="","",SUM($G84:$AD84)) | F84: =IF($A84="","",N($D84)-N($E84))
A85: =IF(案件管理!$A$80:$A$80="","",案件管理!$A$80:$A$80) | B85: =IF($A85="","",案件管理!$B$80:$B$80) | C85: =IF($A85="","",案件管理!$D$80:$D$80) | D85: =IF($A85="","",案件管理!$AE$80:$AE$80) | E85: =IF($A85="","",SUM($G85:$AD85)) | F85: =IF($A85="","",N($D85)-N($E85))
A86: =IF(案件管理!$A$81:$A$81="","",案件管理!$A$81:$A$81) | B86: =IF($A86="","",案件管理!$B$81:$B$81) | C86: =IF($A86="","",案件管理!$D$81:$D$81) | D86: =IF($A86="","",案件管理!$AE$81:$AE$81) | E86: =IF($A86="","",SUM($G86:$AD86)) | F86: =IF($A86="","",N($D86)-N($E86))
A87: =IF(案件管理!$A$82:$A$82="","",案件管理!$A$82:$A$82) | B87: =IF($A87="","",案件管理!$B$82:$B$82) | C87: =IF($A87="","",案件管理!$D$82:$D$82) | D87: =IF($A87="","",案件管理!$AE$82:$AE$82) | E87: =IF($A87="","",SUM($G87:$AD87)) | F87: =IF($A87="","",N($D87)-N($E87))
A88: =IF(案件管理!$A$83:$A$83="","",案件管理!$A$83:$A$83) | B88: =IF($A88="","",案件管理!$B$83:$B$83) | C88: =IF($A88="","",案件管理!$D$83:$D$83) | D88: =IF($A88="","",案件管理!$AE$83:$AE$83) | E88: =IF($A88="","",SUM($G88:$AD88)) | F88: =IF($A88="","",N($D88)-N($E88))
A89: =IF(案件管理!$A$84:$A$84="","",案件管理!$A$84:$A$84) | B89: =IF($A89="","",案件管理!$B$84:$B$84) | C89: =IF($A89="","",案件管理!$D$84:$D$84) | D89: =IF($A89="","",案件管理!$AE$84:$AE$84) | E89: =IF($A89="","",SUM($G89:$AD89)) | F89: =IF($A89="","",N($D89)-N($E89))
A90: =IF(案件管理!$A$85:$A$85="","",案件管理!$A$85:$A$85) | B90: =IF($A90="","",案件管理!$B$85:$B$85) | C90: =IF($A90="","",案件管理!$D$85:$D$85) | D90: =IF($A90="","",案件管理!$AE$85:$AE$85) | E90: =IF($A90="","",SUM($G90:$AD90)) | F90: =IF($A90="","",N($D90)-N($E90))
A91: =IF(案件管理!$A$86:$A$86="","",案件管理!$A$86:$A$86) | B91: =IF($A91="","",案件管理!$B$86:$B$86) | C91: =IF($A91="","",案件管理!$D$86:$D$86) | D91: =IF($A91="","",案件管理!$AE$86:$AE$86) | E91: =IF($A91="","",SUM($G91:$AD91)) | F91: =IF($A91="","",N($D91)-N($E91))
A92: =IF(案件管理!$A$87:$A$87="","",案件管理!$A$87:$A$87) | B92: =IF($A92="","",案件管理!$B$87:$B$87) | C92: =IF($A92="","",案件管理!$D$87:$D$87) | D92: =IF($A92="","",案件管理!$AE$87:$AE$87) | E92: =IF($A92="","",SUM($G92:$AD92)) | F92: =IF($A92="","",N($D92)-N($E92))
A93: =IF(案件管理!$A$88:$A$88="","",案件管理!$A$88:$A$88) | B93: =IF($A93="","",案件管理!$B$88:$B$88) | C93: =IF($A93="","",案件管理!$D$88:$D$88) | D93: =IF($A93="","",案件管理!$AE$88:$AE$88) | E93: =IF($A93="","",SUM($G93:$AD93)) | F93: =IF($A93="","",N($D93)-N($E93))
A94: =IF(案件管理!$A$89:$A$89="","",案件管理!$A$89:$A$89) | B94: =IF($A94="","",案件管理!$B$89:$B$89) | C94: =IF($A94="","",案件管理!$D$89:$D$89) | D94: =IF($A94="","",案件管理!$AE$89:$AE$89) | E94: =IF($A94="","",SUM($G94:$AD94)) | F94: =IF($A94="","",N($D94)-N($E94))
A95: =IF(案件管理!$A$90:$A$90="","",案件管理!$A$90:$A$90) | B95: =IF($A95="","",案件管理!$B$90:$B$90) | C95: =IF($A95="","",案件管理!$D$90:$D$90) | D95: =IF($A95="","",案件管理!$AE$90:$AE$90) | E95: =IF($A95="","",SUM($G95:$AD95)) | F95: =IF($A95="","",N($D95)-N($E95))
A96: =IF(案件管理!$A$91:$A$91="","",案件管理!$A$91:$A$91) | B96: =IF($A96="","",案件管理!$B$91:$B$91) | C96: =IF($A96="","",案件管理!$D$91:$D$91) | D96: =IF($A96="","",案件管理!$AE$91:$AE$91) | E96: =IF($A96="","",SUM($G96:$AD96)) | F96: =IF($A96="","",N($D96)-N($E96))
A97: =IF(案件管理!$A$92:$A$92="","",案件管理!$A$92:$A$92) | B97: =IF($A97="","",案件管理!$B$92:$B$92) | C97: =IF($A97="","",案件管理!$D$92:$D$92) | D97: =IF($A97="","",案件管理!$AE$92:$AE$92) | E97: =IF($A97="","",SUM($G97:$AD97)) | F97: =IF($A97="","",N($D97)-N($E97))
A98: =IF(案件管理!$A$93:$A$93="","",案件管理!$A$93:$A$93) | B98: =IF($A98="","",案件管理!$B$93:$B$93) | C98: =IF($A98="","",案件管理!$D$93:$D$93) | D98: =IF($A98="","",案件管理!$AE$93:$AE$93) | E98: =IF($A98="","",SUM($G98:$AD98)) | F98: =IF($A98="","",N($D98)-N($E98))
A99: =IF(案件管理!$A$94:$A$94="","",案件管理!$A$94:$A$94) | B99: =IF($A99="","",案件管理!$B$94:$B$94) | C99: =IF($A99="","",案件管理!$D$94:$D$94) | D99: =IF($A99="","",案件管理!$AE$94:$AE$94) | E99: =IF($A99="","",SUM($G99:$AD99)) | F99: =IF($A99="","",N($D99)-N($E99))
A100: =IF(案件管理!$A$95:$A$95="","",案件管理!$A$95:$A$95) | B100: =IF($A100="","",案件管理!$B$95:$B$95) | C100: =IF($A100="","",案件管理!$D$95:$D$95) | D100: =IF($A100="","",案件管理!$AE$95:$AE$95) | E100: =IF($A100="","",SUM($G100:$AD100)) | F100: =IF($A100="","",N($D100)-N($E100))
A101: =IF(案件管理!$A$96:$A$96="","",案件管理!$A$96:$A$96) | B101: =IF($A101="","",案件管理!$B$96:$B$96) | C101: =IF($A101="","",案件管理!$D$96:$D$96) | D101: =IF($A101="","",案件管理!$AE$96:$AE$96) | E101: =IF($A101="","",SUM($G101:$AD101)) | F101: =IF($A101="","",N($D101)-N($E101))
A102: =IF(案件管理!$A$97:$A$97="","",案件管理!$A$97:$A$97) | B102: =IF($A102="","",案件管理!$B$97:$B$97) | C102: =IF($A102="","",案件管理!$D$97:$D$97) | D102: =IF($A102="","",案件管理!$AE$97:$AE$97) | E102: =IF($A102="","",SUM($G102:$AD102)) | F102: =IF($A102="","",N($D102)-N($E102))
...

Sheet 発注・納品
A1: 発注・納品 │ 機器の発注から受入までを1明細1行で管理
A2: 発注No | B2: 案件ID | C2: 案件名 | D2: 品名・型番 | E2: メーカー | F2: 数量 | G2: 仕入単価 | H2: 金額 | I2: 発注先 | J2: 発注日 | K2: 希望納期 | L2: 回答納期 | M2: 入荷日 | N2: 受入日 | O2: 納品状況 | P2: 納期差異 | Q2: 備考
A3: O-001 | B3: P-001 | C3: =IF($B3="","",IFERROR(INDEX(案件管理!$B$3:$B$202,MATCH($B3,案件管理!$A$3:$A$202,0)),"←IDが未登録です")) -> 本社ネットワーク更改 | D3: L3スイッチ XG-4800-24P | E3: アライドテレシス | F3: 4 | G3: 320000 | H3: =IF(N($F3)*N($G3)=0,"",$F3*$G3) -> 1280000 | I3: A商事 | J3: 46167 | K3: 46188 | L3: 46191 | M3: 46191 | N3: 46192 | O3: =IF($B3="","",IF($N3<>"","受入済",IF($M3<>"","入荷済（受入待ち）",IF($J3<>"","発注済","未発注")))) -> 受入済 | P3: =IF($L3="","",IF($M3<>"",$M3-$L3,IF(TODAY()>$L3,TODAY()-$L3,0))) -> 0 | Q3: ※サンプル行です。
A4: O-002 | B4: P-001 | C4: =IF($B4="","",IFERROR(INDEX(案件管理!$B$3:$B$202,MATCH($B4,案件管理!$A$3:$A$202,0)),"←IDが未登録です")) -> 本社ネットワーク更改 | D4: 光メディアコンバータ MC-200 | E4: アライドテレシス | F4: 8 | G4: 45000 | H4: =IF(N($F4)*N($G4)=0,"",$F4*$G4) -> 360000 | I4: A商事 | J4: 46167 | K4: 46188 | L4: 46213 | O4: =IF($B4="","",IF($N4<>"","受入済",IF($M4<>"","入荷済（受入待ち）",IF($J4<>"","発注済","未発注")))) -> 発注済 | P4: =IF($L4="","",IF($M4<>"",$M4-$L4,IF(TODAY()>$L4,TODAY()-$L4,0))) -> 67 | Q4: ※サンプル行です。納期回答が遅く入荷待ち。
A5: O-003 | B5: P-001 | C5: =IF($B5="","",IFERROR(INDEX(案件管理!$B$3:$B$202,MATCH($B5,案件管理!$A$3:$A$202,0)),"←IDが未登録です")) -> 本社ネットワーク更改 | D5: 19インチラック 24U | E5: Cネットワークス | F5: 1 | G5: 180000 | H5: =IF(N($F5)*N($G5)=0,"",$F5*$G5) -> 180000 | I5: Cネットワークス | J5: 46170 | K5: 46193 | L5: 46193 | M5: 46192 | O5: =IF($B5="","",IF($N5<>"","受入済",IF($M5<>"","入荷済（受入待ち）",IF($J5<>"","発注済","未発注")))) -> 入荷済（受入待ち） | P5: =IF($L5="","",IF($M5<>"",$M5-$L5,IF(TODAY()>$L5,TODAY()-$L5,0))) -> -1 | Q5: ※サンプル行です。入荷済み・受入待ち。
C6: =IF($B6="","",IFERROR(INDEX(案件管理!$B$3:$B$202,MATCH($B6,案件管理!$A$3:$A$202,0)),"←IDが未登録です")) | H6: =IF(N($F6)*N($G6)=0,"",$F6*$G6) | O6: =IF($B6="","",IF($N6<>"","受入済",IF($M6<>"","入荷済（受入待ち）",IF($J6<>"","発注済","未発注")))) | P6: =IF($L6="","",IF($M6<>"",$M6-$L6,IF(TODAY()>$L6,TODAY()-$L6,0)))
C7: =IF($B7="","",IFERROR(INDEX(案件管理!$B$3:$B$202,MATCH($B7,案件管理!$A$3:$A$202,0)),"←IDが未登録です")) | H7: =IF(N($F7)*N($G7)=0,"",$F7*$G7) | O7: =IF($B7="","",IF($N7<>"","受入済",IF($M7<>"","入荷済（受入待ち）",IF($J7<>"","発注済","未発注")))) | P7: =IF($L7="","",IF($M7<>"",$M7-$L7,IF(TODAY()>$L7,TODAY()-$L7,0)))
C8: =IF($B8="","",IFERROR(INDEX(案件管理!$B$3:$B$202,MATCH($B8,案件管理!$A$3:$A$202,0)),"←IDが未登録です")) | H8: =IF(N($F8)*N($G8)=0,"",$F8*$G8) | O8: =IF($B8="","",IF($N8<>"","受入済",IF($M8<>"","入荷済（受入待ち）",IF($J8<>"","発注済","未発注")))) | P8: =IF($L8="","",IF($M8<>"",$M8-$L8,IF(TODAY()>$L8,TODAY()-$L8,0)))
C9: =IF($B9="","",IFERROR(INDEX(案件管理!$B$3:$B$202,MATCH($B9,案件管理!$A$3:$A$202,0)),"←IDが未登録です")) | H9: =IF(N($F9)*N($G9)=0,"",$F9*$G9) | O9: =IF($B9="","",IF($N9<>"","受入済",IF($M9<>"","入荷済（受入待ち）",IF($J9<>"","発注済","未発注")))) | P9: =IF($L9="","",IF($M9<>"",$M9-$L9,IF(TODAY()>$L9,TODAY()-$L9,0)))
C10: =IF($B10="","",IFERROR(INDEX(案件管理!$B$3:$B$202,MATCH($B10,案件管理!$A$3:$A$202,0)),"←IDが未登録です")) | H10: =IF(N($F10)*N($G10)=0,"",$F10*$G10) | O10: =IF($B10="","",IF($N10<>"","受入済",IF($M10<>"","入荷済（受入待ち）",IF($J10<>"","発注済","未発注")))) | P10: =IF($L10="","",IF($M10<>"",$M10-$L10,IF(TODAY()>$L10,TODAY()-$L10,0)))
C11: =IF($B11="","",IFERROR(INDEX(案件管理!$B$3:$B$202,MATCH($B11,案件管理!$A$3:$A$202,0)),"←IDが未登録です")) | H11: =IF(N($F11)*N($G11)=0,"",$F11*$G11) | O11: =IF($B11="","",IF($N11<>"","受入済",IF($M11<>"","入荷済（受入待ち）",IF($J11<>"","発注済","未発注")))) | P11: =IF($L11="","",IF($M11<>"",$M11-$L11,IF(TODAY()>$L11,TODAY()-$L11,0)))
C12: =IF($B12="","",IFERROR(INDEX(案件管理!$B$3:$B$202,MATCH($B12,案件管理!$A$3:$A$202,0)),"←IDが未登録です")) | H12: =IF(N($F12)*N($G12)=0,"",$F12*$G12) | O12: =IF($B12="","",IF($N12<>"","受入済",IF($M12<>"","入荷済（受入待ち）",IF($J12<>"","発注済","未発注")))) | P12: =IF($L12="","",IF($M12<>"",$M12-$L12,IF(TODAY()>$L12,TODAY()-$L12,0)))
C13: =IF($B13="","",IFERROR(INDEX(案件管理!$B$3:$B$202,MATCH($B13,案件管理!$A$3:$A$202,0)),"←IDが未登録です")) | H13: =IF(N($F13)*N($G13)=0,"",$F13*$G13) | O13: =IF($B13="","",IF($N13<>"","受入済",IF($M13<>"","入荷済（受入待ち）",IF($J13<>"","発注済","未発注")))) | P13: =IF($L13="","",IF($M13<>"",$M13-$L13,IF(TODAY()>$L13,TODAY()-$L13,0)))
C14: =IF($B14="","",IFERROR(INDEX(案件管理!$B$3:$B$202,MATCH($B14,案件管理!$A$3:$A$202,0)),"←IDが未登録です")) | H14: =IF(N($F14)*N($G14)=0,"",$F14*$G14) | O14: =IF($B14="","",IF($N14<>"","受入済",IF($M14<>"","入荷済（受入待ち）",IF($J14<>"","発注済","未発注")))) | P14: =IF($L14="","",IF($M14<>"",$M14-$L14,IF(TODAY()>$L14,TODAY()-$L14,0)))
C15: =IF($B15="","",IFERROR(INDEX(案件管理!$B$3:$B$202,MATCH($B15,案件管理!$A$3:$A$202,0)),"←IDが未登録です")) | H15: =IF(N($F15)*N($G15)=0,"",$F15*$G15) | O15: =IF($B15="","",IF($N15<>"","受入済",IF($M15<>"","入荷済（受入待ち）",IF($J15<>"","発注済","未発注")))) | P15: =IF($L15="","",IF($M15<>"",$M15-$L15,IF(TODAY()>$L15,TODAY()-$L15,0)))
C16: =IF($B16="","",IFERROR(INDEX(案件管理!$B$3:$B$202,MATCH($B16,案件管理!$A$3:$A$202,0)),"←IDが未登録です")) | H16: =IF(N($F16)*N($G16)=0,"",$F16*$G16) | O16: =IF($B16="","",IF($N16<>"","受入済",IF($M16<>"","入荷済（受入待ち）",IF($J16<>"","発注済","未発注")))) | P16: =IF($L16="","",IF($M16<>"",$M16-$L16,IF(TODAY()>$L16,TODAY()-$L16,0)))
C17: =IF($B17="","",IFERROR(INDEX(案件管理!$B$3:$B$202,MATCH($B17,案件管理!$A$3:$A$202,0)),"←IDが未登録です")) | H17: =IF(N($F17)*N($G17)=0,"",$F17*$G17) | O17: =IF($B17="","",IF($N17<>"","受入済",IF($M17<>"","入荷済（受入待ち）",IF($J17<>"","発注済","未発注")))) | P17: =IF($L17="","",IF($M17<>"",$M17-$L17,IF(TODAY()>$L17,TODAY()-$L17,0)))
... C202: =IF($B202="","",IFERROR(INDEX(案件管理!$B$3:$B$202,MATCH($B202,案件管理!$A$3:$A$202,0)),"←IDが未登録です")) | H202: =IF(N($F202)*N($G202)=0,"",$F202*$G202) | O202: =IF($B202="","",IF($N202<>"","受入済",IF($M202<>"","入荷済（受入待ち）",IF($J202<>"","発注済","未発注")))) | P202: =IF($L202="","",IF($M202<>"",$M202-$L202,IF(TODAY()>$L202,TODAY()-$L202,0)))
A204: 金額（数量×仕入単価）は案件管理の「機器原価」に自動集計されます。納期差異は回答納期に対するズレで、未入荷なら今日までの経過日数を表示します。

Sheet 現地作業
A1: 現地作業 │ 現地に行く日の予定と実施記録（工数そのものは工数明細に入れてください）
A2: 案件ID | B2: 案件名 | C2: 作業日 | D2: 曜日 | E2: 開始 | F2: 終了 | G2: 休憩(h) | H2: 実働時間 | I2: 作業場所 | J2: 作業者 | K2: 作業区分 | L2: 状態 | M2: 作業内容 | N2: 備考
A3: P-001 | B3: =IF($A3="","",IFERROR(INDEX(案件管理!$B$3:$B$202,MATCH($A3,案件管理!$A$3:$A$202,0)),"←IDが未登録です")) -> 本社ネットワーク更改 | C3: 46176 | D3: =IF($C3="","",CHOOSE(WEEKDAY($C3,1),"日","月","火","水","木","金","土")) -> 水 | E3: 0.375 | F3: 0.75 | G3: 1 | H3: =IF(OR($E3="",$F3=""),"",($F3-$E3)*24-N($G3)) -> 8 | I3: アルファ商事 本社 3F サーバ室 | J3: 山田 太郎 | K3: 搬入・設置 | L3: 完了 | M3: L3スイッチ設置・疎通確認 | N3: ※サンプル行です。
A4: P-001 | B4: =IF($A4="","",IFERROR(INDEX(案件管理!$B$3:$B$202,MATCH($A4,案件管理!$A$3:$A$202,0)),"←IDが未登録です")) -> 本社ネットワーク更改 | C4: 46177 | D4: =IF($C4="","",CHOOSE(WEEKDAY($C4,1),"日","月","火","水","木","金","土")) -> 木 | E4: 0.375 | F4: 0.66666667 | G4: 1 | H4: =IF(OR($E4="",$F4=""),"",($F4-$E4)*24-N($G4)) -> 6 | I4: アルファ商事 本社 各フロア | J4: 山田 太郎 | K4: 配線 | L4: 完了 | M4: フロア配線の敷設 | N4: ※サンプル行です。
A5: P-001 | B5: =IF($A5="","",IFERROR(INDEX(案件管理!$B$3:$B$202,MATCH($A5,案件管理!$A$3:$A$202,0)),"←IDが未登録です")) -> 本社ネットワーク更改 | C5: 46309 | D5: =IF($C5="","",CHOOSE(WEEKDAY($C5,1),"日","月","火","水","木","金","土")) -> 水 | E5: 0.41666667 | F5: 0.70833333 | G5: 1 | H5: =IF(OR($E5="",$F5=""),"",($F5-$E5)*24-N($G5)) -> 6 | I5: アルファ商事 本社 3F サーバ室 | J5: 山田/佐藤 | K5: 移行作業 | L5: 予定 | M5: 本番切替（夜間立会いあり） | N5: ※サンプル行です。これから行く予定の作業。
B6: =IF($A6="","",IFERROR(INDEX(案件管理!$B$3:$B$202,MATCH($A6,案件管理!$A$3:$A$202,0)),"←IDが未登録です")) | D6: =IF($C6="","",CHOOSE(WEEKDAY($C6,1),"日","月","火","水","木","金","土")) | H6: =IF(OR($E6="",$F6=""),"",($F6-$E6)*24-N($G6))
B7: =IF($A7="","",IFERROR(INDEX(案件管理!$B$3:$B$202,MATCH($A7,案件管理!$A$3:$A$202,0)),"←IDが未登録です")) | D7: =IF($C7="","",CHOOSE(WEEKDAY($C7,1),"日","月","火","水","木","金","土")) | H7: =IF(OR($E7="",$F7=""),"",($F7-$E7)*24-N($G7))
B8: =IF($A8="","",IFERROR(INDEX(案件管理!$B$3:$B$202,MATCH($A8,案件管理!$A$3:$A$202,0)),"←IDが未登録です")) | D8: =IF($C8="","",CHOOSE(WEEKDAY($C8,1),"日","月","火","水","木","金","土")) | H8: =IF(OR($E8="",$F8=""),"",($F8-$E8)*24-N($G8))
B9: =IF($A9="","",IFERROR(INDEX(案件管理!$B$3:$B$202,MATCH($A9,案件管理!$A$3:$A$202,0)),"←IDが未登録です")) | D9: =IF($C9="","",CHOOSE(WEEKDAY($C9,1),"日","月","火","水","木","金","土")) | H9: =IF(OR($E9="",$F9=""),"",($F9-$E9)*24-N($G9))
B10: =IF($A10="","",IFERROR(INDEX(案件管理!$B$3:$B$202,MATCH($A10,案件管理!$A$3:$A$202,0)),"←IDが未登録です")) | D10: =IF($C10="","",CHOOSE(WEEKDAY($C10,1),"日","月","火","水","木","金","土")) | H10: =IF(OR($E10="",$F10=""),"",($F10-$E10)*24-N($G10))
B11: =IF($A11="","",IFERROR(INDEX(案件管理!$B$3:$B$202,MATCH($A11,案件管理!$A$3:$A$202,0)),"←IDが未登録です")) | D11: =IF($C11="","",CHOOSE(WEEKDAY($C11,1),"日","月","火","水","木","金","土")) | H11: =IF(OR($E11="",$F11=""),"",($F11-$E11)*24-N($G11))
B12: =IF($A12="","",IFERROR(INDEX(案件管理!$B$3:$B$202,MATCH($A12,案件管理!$A$3:$A$202,0)),"←IDが未登録です")) | D12: =IF($C12="","",CHOOSE(WEEKDAY($C12,1),"日","月","火","水","木","金","土")) | H12: =IF(OR($E12="",$F12=""),"",($F12-$E12)*24-N($G12))
B13: =IF($A13="","",IFERROR(INDEX(案件管理!$B$3:$B$202,MATCH($A13,案件管理!$A$3:$A$202,0)),"←IDが未登録です")) | D13: =IF($C13="","",CHOOSE(WEEKDAY($C13,1),"日","月","火","水","木","金","土")) | H13: =IF(OR($E13="",$F13=""),"",($F13-$E13)*24-N($G13))
B14: =IF($A14="","",IFERROR(INDEX(案件管理!$B$3:$B$202,MATCH($A14,案件管理!$A$3:$A$202,0)),"←IDが未登録です")) | D14: =IF($C14="","",CHOOSE(WEEKDAY($C14,1),"日","月","火","水","木","金","土")) | H14: =IF(OR($E14="",$F14=""),"",($F14-$E14)*24-N($G14))
B15: =IF($A15="","",IFERROR(INDEX(案件管理!$B$3:$B$202,MATCH($A15,案件管理!$A$3:$A$202,0)),"←IDが未登録です")) | D15: =IF($C15="","",CHOOSE(WEEKDAY($C15,1),"日","月","火","水","木","金","土")) | H15: =IF(OR($E15="",$F15=""),"",($F15-$E15)*24-N($G15))
B16: =IF($A16="","",IFERROR(INDEX(案件管理!$B$3:$B$202,MATCH($A16,案件管理!$A$3:$A$202,0)),"←IDが未登録です")) | D16: =IF($C16="","",CHOOSE(WEEKDAY($C16,1),"日","月","火","水","木","金","土")) | H16: =IF(OR($E16="",$F16=""),"",($F16-$E16)*24-N($G16))
B17: =IF($A17="","",IFERROR(INDEX(案件管理!$B$3:$B$202,MATCH($A17,案件管理!$A$3:$A$202,0)),"←IDが未登録です")) | D17: =IF($C17="","",CHOOSE(WEEKDAY($C17,1),"日","月","火","水","木","金","土")) | H17: =IF(OR($E17="",$F17=""),"",($F17-$E17)*24-N($G17))
... B202: =IF($A202="","",IFERROR(INDEX(案件管理!$B$3:$B$202,MATCH($A202,案件管理!$A$3:$A$202,0)),"←IDが未登録です")) | D202: =IF($C202="","",CHOOSE(WEEKDAY($C202,1),"日","月","火","水","木","金","土")) | H202: =IF(OR($E202="",$F202=""),"",($F202-$E202)*24-N($G202))
A204: 状態が「予定」で今日以降の作業日のうち、いちばん近い日が案件管理の「次回現地作業日」に出ます。土日の行はピンク色になります。

Sheet ダッシュボード
B1: ダッシュボード │ 年度を選ぶと自動で集計されます
B3: 集計対象の年度 | C3: =マスタ!$B$6 -> 2026 | D3: ← マスタ!B6 の値を見ています。ここに直接 2027 などと入力して切り替えてもOKです。
B5: ■ クォーター別サマリ
B6: 項目 | C6: Q1 | D6: Q2 | E6: Q3 | F6: Q4 | G6: 年度合計
B7: 案件数 | C7: =COUNTIFS(案件管理!$N$3:$N$202,$C$3,案件管理!$O$3:$O$202,C6,案件管理!$A$3:$A$202,"<>") -> 2 | D7: =COUNTIFS(案件管理!$N$3:$N$202,$C$3,案件管理!$O$3:$O$202,D6,案件管理!$A$3:$A$202,"<>") -> 0 | E7: =COUNTIFS(案件管理!$N$3:$N$202,$C$3,案件管理!$O$3:$O$202,E6,案件管理!$A$3:$A$202,"<>") -> 1 | F7: =COUNTIFS(案件管理!$N$3:$N$202,$C$3,案件管理!$O$3:$O$202,F6,案件管理!$A$3:$A$202,"<>") -> 0 | G7: =SUM(C7:F7) -> 3
B8: 受注金額 | C8: =SUMIFS(案件管理!$Q$3:$Q$202,案件管理!$N$3:$N$202,$C$3,案件管理!$O$3:$O$202,C6) -> 6000000 | D8: =SUMIFS(案件管理!$Q$3:$Q$202,案件管理!$N$3:$N$202,$C$3,案件管理!$O$3:$O$202,D6) -> 0 | E8: =SUMIFS(案件管理!$Q$3:$Q$202,案件管理!$N$3:$N$202,$C$3,案件管理!$O$3:$O$202,E6) -> 3000000 | F8: =SUMIFS(案件管理!$Q$3:$Q$202,案件管理!$N$3:$N$202,$C$3,案件管理!$O$3:$O$202,F6) -> 0 | G8: =SUM(C8:F8) -> 9000000
B9: 加重金額（確度反映） | C9: =SUMIFS(案件管理!$R$3:$R$202,案件管理!$N$3:$N$202,$C$3,案件管理!$O$3:$O$202,C6) -> 6000000 | D9: =SUMIFS(案件管理!$R$3:$R$202,案件管理!$N$3:$N$202,$C$3,案件管理!$O$3:$O$202,D6) -> 0 | E9: =SUMIFS(案件管理!$R$3:$R$202,案件管理!$N$3:$N$202,$C$3,案件管理!$O$3:$O$202,E6) -> 1500000 | F9: =SUMIFS(案件管理!$R$3:$R$202,案件管理!$N$3:$N$202,$C$3,案件管理!$O$3:$O$202,F6) -> 0 | G9: =SUM(C9:F9) -> 7500000
B10: 機器原価 | C10: =SUMIFS(案件管理!$T$3:$T$202,案件管理!$N$3:$N$202,$C$3,案件管理!$O$3:$O$202,C6) -> 1820000 | D10: =SUMIFS(案件管理!$T$3:$T$202,案件管理!$N$3:$N$202,$C$3,案件管理!$O$3:$O$202,D6) -> 0 | E10: =SUMIFS(案件管理!$T$3:$T$202,案件管理!$N$3:$N$202,$C$3,案件管理!$O$3:$O$202,E6) -> 0 | F10: =SUMIFS(案件管理!$T$3:$T$202,案件管理!$N$3:$N$202,$C$3,案件管理!$O$3:$O$202,F6) -> 0 | G10: =SUM(C10:F10) -> 1820000
B11: 原価計 | C11: =SUMIFS(案件管理!$U$3:$U$202,案件管理!$N$3:$N$202,$C$3,案件管理!$O$3:$O$202,C6) -> 2900000 | D11: =SUMIFS(案件管理!$U$3:$U$202,案件管理!$N$3:$N$202,$C$3,案件管理!$O$3:$O$202,D6) -> 0 | E11: =SUMIFS(案件管理!$U$3:$U$202,案件管理!$N$3:$N$202,$C$3,案件管理!$O$3:$O$202,E6) -> 1500000 | F11: =SUMIFS(案件管理!$U$3:$U$202,案件管理!$N$3:$N$202,$C$3,案件管理!$O$3:$O$202,F6) -> 0 | G11: =SUM(C11:F11) -> 4400000
B12: 粗利 | C12: =SUMIFS(案件管理!$V$3:$V$202,案件管理!$N$3:$N$202,$C$3,案件管理!$O$3:$O$202,C6) -> 3100000 | D12: =SUMIFS(案件管理!$V$3:$V$202,案件管理!$N$3:$N$202,$C$3,案件管理!$O$3:$O$202,D6) -> 0 | E12: =SUMIFS(案件管理!$V$3:$V$202,案件管理!$N$3:$N$202,$C$3,案件管理!$O$3:$O$202,E6) -> 1500000 | F12: =SUMIFS(案件管理!$V$3:$V$202,案件管理!$N$3:$N$202,$C$3,案件管理!$O$3:$O$202,F6) -> 0 | G12: =SUM(C12:F12) -> 4600000
B13: 粗利率 | C13: =IF(N(C8)=0,"",C12/C8) -> 0.51666667 | D13: =IF(N(D8)=0,"",D12/D8) | E13: =IF(N(E8)=0,"",E12/E8) -> 0.5 | F13: =IF(N(F8)=0,"",F12/F8) | G13: =IF(N(G8)=0,"",G12/G8) -> 0.51111111
B14: 予定工数 | C14: =SUMIFS(案件管理!$AE$3:$AE$202,案件管理!$N$3:$N$202,$C$3,案件管理!$O$3:$O$202,C6) -> 57 | D14: =SUMIFS(案件管理!$AE$3:$AE$202,案件管理!$N$3:$N$202,$C$3,案件管理!$O$3:$O$202,D6) -> 0 | E14: =SUMIFS(案件管理!$AE$3:$AE$202,案件管理!$N$3:$N$202,$C$3,案件管理!$O$3:$O$202,E6) -> 30 | F14: =SUMIFS(案件管理!$AE$3:$AE$202,案件管理!$N$3:$N$202,$C$3,案件管理!$O$3:$O$202,F6) -> 0 | G14: =SUM(C14:F14) -> 87
B15: 実績工数 | C15: =SUMIFS(案件管理!$AG$3:$AG$202,案件管理!$N$3:$N$202,$C$3,案件管理!$O$3:$O$202,C6) -> 2.75 | D15: =SUMIFS(案件管理!$AG$3:$AG$202,案件管理!$N$3:$N$202,$C$3,案件管理!$O$3:$O$202,D6) -> 0 | E15: =SUMIFS(案件管理!$AG$3:$AG$202,案件管理!$N$3:$N$202,$C$3,案件管理!$O$3:$O$202,E6) -> 0 | F15: =SUMIFS(案件管理!$AG$3:$AG$202,案件管理!$N$3:$N$202,$C$3,案件管理!$O$3:$O$202,F6) -> 0 | G15: =SUM(C15:F15) -> 2.75
B16: 工数消化率 | C16: =IF(N(C14)=0,"",C15/C14) -> 0.048245614 | D16: =IF(N(D14)=0,"",D15/D14) | E16: =IF(N(E14)=0,"",E15/E14) -> 0 | F16: =IF(N(F14)=0,"",F15/F14) | G16: =IF(N(G14)=0,"",G15/G14) -> 0.031609195
B19: ■ ステータス別（対象年度）
B20: ステータス | C20: 案件数 | D20: 受注金額 | E20: 粗利 | F20: 予定工数 | G20: 実績工数
B21: 未着手 | C21: =COUNTIFS(案件管理!$N$3:$N$202,$C$3,案件管理!$G$3:$G$202,$B21) -> 1 | D21: =SUMIFS(案件管理!$Q$3:$Q$202,案件管理!$N$3:$N$202,$C$3,案件管理!$G$3:$G$202,$B21) -> 3000000 | E21: =SUMIFS(案件管理!$V$3:$V$202,案件管理!$N$3:$N$202,$C$3,案件管理!$G$3:$G$202,$B21) -> 1500000 | F21: =SUMIFS(案件管理!$AE$3:$AE$202,案件管理!$N$3:$N$202,$C$3,案件管理!$G$3:$G$202,$B21) -> 30 | G21: =SUMIFS(案件管理!$AG$3:$AG$202,案件管理!$N$3:$N$202,$C$3,案件管理!$G$3:$G$202,$B21) -> 0
B22: 進行中 | C22: =COUNTIFS(案件管理!$N$3:$N$202,$C$3,案件管理!$G$3:$G$202,$B22) -> 1 | D22: =SUMIFS(案件管理!$Q$3:$Q$202,案件管理!$N$3:$N$202,$C$3,案件管理!$G$3:$G$202,$B22) -> 4800000 | E22: =SUMIFS(案件管理!$V$3:$V$202,案件管理!$N$3:$N$202,$C$3,案件管理!$G$3:$G$202,$B22) -> 2380000 | F22: =SUMIFS(案件管理!$AE$3:$AE$202,案件管理!$N$3:$N$202,$C$3,案件管理!$G$3:$G$202,$B22) -> 45 | G22: =SUMIFS(案件管理!$AG$3:$AG$202,案件管理!$N$3:$N$202,$C$3,案件管理!$G$3:$G$202,$B22) -> 2.25
B23: 保留 | C23: =COUNTIFS(案件管理!$N$3:$N$202,$C$3,案件管理!$G$3:$G$202,$B23) -> 0 | D23: =SUMIFS(案件管理!$Q$3:$Q$202,案件管理!$N$3:$N$202,$C$3,案件管理!$G$3:$G$202,$B23) -> 0 | E23: =SUMIFS(案件管理!$V$3:$V$202,案件管理!$N$3:$N$202,$C$3,案件管理!$G$3:$G$202,$B23) -> 0 | F23: =SUMIFS(案件管理!$AE$3:$AE$202,案件管理!$N$3:$N$202,$C$3,案件管理!$G$3:$G$202,$B23) -> 0 | G23: =SUMIFS(案件管理!$AG$3:$AG$202,案件管理!$N$3:$N$202,$C$3,案件管理!$G$3:$G$202,$B23) -> 0
B24: 完了 | C24: =COUNTIFS(案件管理!$N$3:$N$202,$C$3,案件管理!$G$3:$G$202,$B24) -> 1 | D24: =SUMIFS(案件管理!$Q$3:$Q$202,案件管理!$N$3:$N$202,$C$3,案件管理!$G$3:$G$202,$B24) -> 1200000 | E24: =SUMIFS(案件管理!$V$3:$V$202,案件管理!$N$3:$N$202,$C$3,案件管理!$G$3:$G$202,$B24) -> 720000 | F24: =SUMIFS(案件管理!$AE$3:$AE$202,案件管理!$N$3:$N$202,$C$3,案件管理!$G$3:$G$202,$B24) -> 12 | G24: =SUMIFS(案件管理!$AG$3:$AG$202,案件管理!$N$3:$N$202,$C$3,案件管理!$G$3:$G$202,$B24) -> 0.5
B25: 失注 | C25: =COUNTIFS(案件管理!$N$3:$N$202,$C$3,案件管理!$G$3:$G$202,$B25) -> 0 | D25: =SUMIFS(案件管理!$Q$3:$Q$202,案件管理!$N$3:$N$202,$C$3,案件管理!$G$3:$G$202,$B25) -> 0 | E25: =SUMIFS(案件管理!$V$3:$V$202,案件管理!$N$3:$N$202,$C$3,案件管理!$G$3:$G$202,$B25) -> 0 | F25: =SUMIFS(案件管理!$AE$3:$AE$202,案件管理!$N$3:$N$202,$C$3,案件管理!$G$3:$G$202,$B25) -> 0 | G25: =SUMIFS(案件管理!$AG$3:$AG$202,案件管理!$N$3:$N$202,$C$3,案件管理!$G$3:$G$202,$B25) -> 0
B28: ■ 担当者別（対象年度）
B29: 担当者 | C29: 案件数 | D29: 受注金額 | E29: 粗利 | F29: 予定工数 | G29: 実績工数 | H29: 工数消化率
B30: 山田 太郎 | C30: =COUNTIFS(案件管理!$N$3:$N$202,$C$3,案件管理!$D$3:$D$202,$B30) -> 1 | D30: =SUMIFS(案件管理!$Q$3:$Q$202,案件管理!$N$3:$N$202,$C$3,案件管理!$D$3:$D$202,$B30) -> 4800000 | E30: =SUMIFS(案件管理!$V$3:$V$202,案件管理!$N$3:$N$202,$C$3,案件管理!$D$3:$D$202,$B30) -> 2380000 | F30: =SUMIFS(案件管理!$AE$3:$AE$202,案件管理!$N$3:$N$202,$C$3,案件管理!$D$3:$D$202,$B30) -> 45 | G30: =SUMIFS(案件管理!$AG$3:$AG$202,案件管理!$N$3:$N$202,$C$3,案件管理!$D$3:$D$202,$B30) -> 2.25 | H30: =IF(N($F30)=0,"",$G30/$F30) -> 0.05
B31: 佐藤 花子 | C31: =COUNTIFS(案件管理!$N$3:$N$202,$C$3,案件管理!$D$3:$D$202,$B31) -> 1 | D31: =SUMIFS(案件管理!$Q$3:$Q$202,案件管理!$N$3:$N$202,$C$3,案件管理!$D$3:$D$202,$B31) -> 1200000 | E31: =SUMIFS(案件管理!$V$3:$V$202,案件管理!$N$3:$N$202,$C$3,案件管理!$D$3:$D$202,$B31) -> 720000 | F31: =SUMIFS(案件管理!$AE$3:$AE$202,案件管理!$N$3:$N$202,$C$3,案件管理!$D$3:$D$202,$B31) -> 12 | G31: =SUMIFS(案件管理!$AG$3:$AG$202,案件管理!$N$3:$N$202,$C$3,案件管理!$D$3:$D$202,$B31) -> 0.5 | H31: =IF(N($F31)=0,"",$G31/$F31) -> 0.041666667
B32: 鈴木 一郎 | C32: =COUNTIFS(案件管理!$N$3:$N$202,$C$3,案件管理!$D$3:$D$202,$B32) -> 1 | D32: =SUMIFS(案件管理!$Q$3:$Q$202,案件管理!$N$3:$N$202,$C$3,案件管理!$D$3:$D$202,$B32) -> 3000000 | E32: =SUMIFS(案件管理!$V$3:$V$202,案件管理!$N$3:$N$202,$C$3,案件管理!$D$3:$D$202,$B32) -> 1500000 | F32: =SUMIFS(案件管理!$AE$3:$AE$202,案件管理!$N$3:$N$202,$C$3,案件管理!$D$3:$D$202,$B32) -> 30 | G32: =SUMIFS(案件管理!$AG$3:$AG$202,案件管理!$N$3:$N$202,$C$3,案件管理!$D$3:$D$202,$B32) -> 0 | H32: =IF(N($F32)=0,"",$G32/$F32) -> 0
B33: （未定） | C33: =COUNTIFS(案件管理!$N$3:$N$202,$C$3,案件管理!$D$3:$D$202,$B33) -> 0 | D33: =SUMIFS(案件管理!$Q$3:$Q$202,案件管理!$N$3:$N$202,$C$3,案件管理!$D$3:$D$202,$B33) -> 0 | E33: =SUMIFS(案件管理!$V$3:$V$202,案件管理!$N$3:$N$202,$C$3,案件管理!$D$3:$D$202,$B33) -> 0 | F33: =SUMIFS(案件管理!$AE$3:$AE$202,案件管理!$N$3:$N$202,$C$3,案件管理!$D$3:$D$202,$B33) -> 0 | G33: =SUMIFS(案件管理!$AG$3:$AG$202,案件管理!$N$3:$N$202,$C$3,案件管理!$D$3:$D$202,$B33) -> 0 | H33: =IF(N($F33)=0,"",$G33/$F33)
B36: ■ いまどの作業ステップにいるか（対象年度／失注をのぞく）
B37: 作業ステップ | C37: 案件数 | D37: 受注金額 | E37: 実績工数
